Workbook
Name Action: 'Transaction Log'!$D$2:$D$159
Name Amount: 'Transaction Log'!$J$2:$J$159
Name broker_fee: 'Transaction Log'!$P$2
Name Cashflow: 'Transaction Log'!$M$2:$M$159
Name Date: 'Transaction Log'!$A$2:$A$159
Name Dividend_per_Share: 'Transaction Log'!$I$2:$I$159
Name exchange_fee: 'Transaction Log'!$P$1
Name Lot: 'Transaction Log'!$E$2:$E$159
Name Net_Amount: 'Transaction Log'!$L$2:$L$159
Name Position_Change: 'Transaction Log'!$F$2:$F$159
Name Price: 'Transaction Log'!$G$2:$G$159
Name Slicer_Growth_Percentage: #N/A
Name Slicer_Stock_Ticker: #N/A
Name Stock_Tickers: 'Transaction Log'!$C$2:$C$159
Name Total_Fee: 'Transaction Log'!$K$2:$K$159
Name Transaction_ID: 'Transaction Log'!$B$2:$B$159

Sheet Dashboard

Sheet Transaction Log
A1: Date | B1: Transaction ID | C1: Stock Tickers | D1: Action | E1: Lot | F1: Position Change | G1: Price | H1: Weighted Average Price | I1: Dividend per Share | J1: Amount | K1: Total Fee | L1: Net Amount | M1: Cashflow | O1: Exchange Fee | P1: 0.000433
A2: 45294 | B2: ="TX"&TEXT(ROW()-1,"0000") -> TX0001 | D2: Deposit | F2: {=_xlfn.IFS(Table1[[#This Row],[Action]]="Buy",Table1[[#This Row],[Lot ]],Table1[[#This Row],[Action]]="Sell",-Table1[[#This Row],[Lot ]],Table1[[#This Row],[Action]]="Dividend",0,TRUE,"")} | H2: {=IF(OR(Table1[[#This Row],[Stock Tickers]]="",Table1[[#This Row],[Action]]="Dividend"), "",IF(Table1[[#This Row],[Action]]="Buy",(SUMIFS($L2:L$2, $C2:C$2,Table1[[#This Row],[Stock Tickers]], $D2:D$2, "Buy") + Table1[[#This Row],[Amount]]) / ((SUMIFS($E2:E$2, $C2:C$2,Table1[[#This Row],[Stock Tickers]], $D2:D$2, "Buy") + Table1[[#This Row],[Lot ]])*100),LOOKUP(2, 1/($C2:C$2=Table1[[#This Row],[Stock Tickers]]), $G2:G$2)))} | J2: 100000000 | L2: =SUM(Table1[[#This Row],[Amount]]:Table1[[#This Row],[Total Fee]]) -> 100000000 | M2: =IF(OR(Table1[[#This Row],[Action]]="Buy",Table1[[#This Row],[Action]]="Withdraw"),-Table1[[#This Row],[Net Amount]],Table1[[#This Row],[Net Amount]]) -> 100000000 | O2: Broker Fee | P2: 0.0015
A3: 45296 | B3: ="TX"&TEXT(ROW()-1,"0000") -> TX0002 | C3: BBRI | D3: Buy | E3: 25 | F3: {=_xlfn.IFS(Table1[[#This Row],[Action]]="Buy",Table1[[#This Row],[Lot ]],Table1[[#This Row],[Action]]="Sell",-Table1[[#This Row],[Lot ]],Table1[[#This Row],[Action]]="Dividend",0,TRUE,"")} -> 25 | G3: 3800 | H3: {=IF(OR(Table1[[#This Row],[Stock Tickers]]="",Table1[[#This Row],[Action]]="Dividend"), "",IF(Table1[[#This Row],[Action]]="Buy",(SUMIFS($L$2:L3, $C$2:C3,Table1[[#This Row],[Stock Tickers]], $D$2:D3, "Buy") + Table1[[#This Row],[Amount]]) / ((SUMIFS($E$2:E3, $C$2:C3,Table1[[#This Row],[Stock Tickers]], $D$2:D3, "Buy") + Table1[[#This Row],[Lot ]])*100),LOOKUP(2, 1/($C$2:C3=Table1[[#This Row],[Stock Tickers]]), $G$2:G3)))} -> 3803.6727 | J3: =(Table1[[#This Row],[Lot ]]*100)*IF(Table1[[#This Row],[Action]]="Dividend",Table1[[#This Row],[Dividend per Share]],Table1[[#This Row],[Price]]) -> 9500000 | K3: =(exchange_fee+broker_fee)*J3 -> 18363.5 | L3: =SUM(Table1[[#This Row],[Amount]]:Table1[[#This Row],[Total Fee]]) -> 9518363.5 | M3: =IF(OR(Table1[[#This Row],[Action]]="Buy",Table1[[#This Row],[Action]]="Withdraw"),-Table1[[#This Row],[Net Amount]],Table1[[#This Row],[Net Amount]]) -> -9518363.5
A4: 45301 | B4: ="TX"&TEXT(ROW()-1,"0000") -> TX0003 | C4: TLKM | D4: Buy | E4: 42 | F4: {=_xlfn.IFS(Table1[[#This Row],[Action]]="Buy",Table1[[#This Row],[Lot ]],Table1[[#This Row],[Action]]="Sell",-Table1[[#This Row],[Lot ]],Table1[[#This Row],[Action]]="Dividend",0,TRUE,"")} -> 42 | G4: 3050 | H4: {=IF(OR(Table1[[#This Row],[Stock Tickers]]="",Table1[[#This Row],[Action]]="Dividend"), "",IF(Table1[[#This Row],[Action]]="Buy",(SUMIFS($L$2:L4, $C$2:C4,Table1[[#This Row],[Stock Tickers]], $D$2:D4, "Buy") + Table1[[#This Row],[Amount]]) / ((SUMIFS($E$2:E4, $C$2:C4,Table1[[#This Row],[Stock Tickers]], $D$2:D4, "Buy") + Table1[[#This Row],[Lot ]])*100),LOOKUP(2, 1/($C$2:C4=Table1[[#This Row],[Stock Tickers]]), $G$2:G4)))} -> 3052.9478 | J4: =(Table1[[#This Row],[Lot ]]*100)*IF(Table1[[#This Row],[Action]]="Dividend",Table1[[#This Row],[Dividend per Share]],Table1[[#This Row],[Price]]) -> 12810000 | K4: =(exchange_fee+broker_fee)*J4 -> 24761.73 | L4: =SUM(Table1[[#This Row],[Amount]]:Table1[[#This Row],[Total Fee]]) -> 12834762 | M4: =IF(OR(Table1[[#This Row],[Action]]="Buy",Table1[[#This Row],[Action]]="Withdraw"),-Table1[[#This Row],[Net Amount]],Table1[[#This Row],[Net Amount]]) -> -12834762
A5: 45309 | B5: ="TX"&TEXT(ROW()-1,"0000") -> TX0004 | C5: ADRO | D5: Buy | E5: 21 | F5: {=_xlfn.IFS(Table1[[#This Row],[Action]]="Buy",Table1[[#This Row],[Lot ]],Table1[[#This Row],[Action]]="Sell",-Table1[[#This Row],[Lot ]],Table1[[#This Row],[Action]]="Dividend",0,TRUE,"")} -> 21 | G5: 2530 | H5: {=IF(OR(Table1[[#This Row],[Stock Tickers]]="",Table1[[#This Row],[Action]]="Dividend"), "",IF(Table1[[#This Row],[Action]]="Buy",(SUMIFS($L$2:L5, $C$2:C5,Table1[[#This Row],[Stock Tickers]], $D$2:D5, "Buy") + Table1[[#This Row],[Amount]]) / ((SUMIFS($E$2:E5, $C$2:C5,Table1[[#This Row],[Stock Tickers]], $D$2:D5, "Buy") + Table1[[#This Row],[Lot ]])*100),LOOKUP(2, 1/($C$2:C5=Table1[[#This Row],[Stock Tickers]]), $G$2:G5)))} -> 2532.4452 | J5: =(Table1[[#This Row],[Lot ]]*100)*IF(Table1[[#This Row],[Action]]="Dividend",Table1[[#This Row],[Dividend per Share]],Table1[[#This Row],[Price]]) -> 5313000 | K5: =(exchange_fee+broker_fee)*J5 -> 10270.029 | L5: =SUM(Table1[[#This Row],[Amount]]:Table1[[#This Row],[Total Fee]]) -> 5323270 | M5: =IF(OR(Table1[[#This Row],[Action]]="Buy",Table1[[#This Row],[Action]]="Withdraw"),-Table1[[#This Row],[Net Amount]],Table1[[#This Row],[Net Amount]]) -> -5323270
A6: 45324 | B6: ="TX"&TEXT(ROW()-1,"0000") -> TX0005 | C6: BBCA | D6: Buy | E6: 7 | F6: {=_xlfn.IFS(Table1[[#This Row],[Action]]="Buy",Table1[[#This Row],[Lot ]],Table1[[#This Row],[Action]]="Sell",-Table1[[#This Row],[Lot ]],Table1[[#This Row],[Action]]="Dividend",0,TRUE,"")} -> 7 | G6: 7560 | H6: {=IF(OR(Table1[[#This Row],[Stock Tickers]]="",Table1[[#This Row],[Action]]="Dividend"), "",IF(Table1[[#This Row],[Action]]="Buy",(SUMIFS($L$2:L6, $C$2:C6,Table1[[#This Row],[Stock Tickers]], $D$2:D6, "Buy") + Table1[[#This Row],[Amount]]) / ((SUMIFS($E$2:E6, $C$2:C6,Table1[[#This Row],[Stock Tickers]], $D$2:D6, "Buy") + Table1[[#This Row],[Lot ]])*100),LOOKUP(2, 1/($C$2:C6=Table1[[#This Row],[Stock Tickers]]), $G$2:G6)))} -> 7567.3067 | J6: =(Table1[[#This Row],[Lot ]]*100)*IF(Table1[[#This Row],[Action]]="Dividend",Table1[[#This Row],[Dividend per Share]],Table1[[#This Row],[Price]]) -> 5292000 | K6: =(exchange_fee+broker_fee)*J6 -> 10229.436 | L6: =SUM(Table1[[#This Row],[Amount]]:Table1[[#This Row],[Total Fee]]) -> 5302229.4 | M6: =IF(OR(Table1[[#This Row],[Action]]="Buy",Table1[[#This Row],[Action]]="Withdraw"),-Table1[[#This Row],[Net Amount]],Table1[[#This Row],[Net Amount]]) -> -5302229.4
A7: 45329 | B7: ="TX"&TEXT(ROW()-1,"0000") -> TX0006 | C7: ASII | D7: Buy | E7: 32 | F7: {=_xlfn.IFS(Table1[[#This Row],[Action]]="Buy",Table1[[#This Row],[Lot ]],Table1[[#This Row],[Action]]="Sell",-Table1[[#This Row],[Lot ]],Table1[[#This Row],[Action]]="Dividend",0,TRUE,"")} -> 32 | G7: 5100 | H7: {=IF(OR(Table1[[#This Row],[Stock Tickers]]="",Table1[[#This Row],[Action]]="Dividend"), "",IF(Table1[[#This Row],[Action]]="Buy",(SUMIFS($L$2:L7, $C$2:C7,Table1[[#This Row],[Stock Tickers]], $D$2:D7, "Buy") + Table1[[#This Row],[Amount]]) / ((SUMIFS($E$2:E7, $C$2:C7,Table1[[#This Row],[Stock Tickers]], $D$2:D7, "Buy") + Table1[[#This Row],[Lot ]])*100),LOOKUP(2, 1/($C$2:C7=Table1[[#This Row],[Stock Tickers]]), $G$2:G7)))} -> 5104.9291 | J7: =(Table1[[#This Row],[Lot ]]*100)*IF(Table1[[#This Row],[Action]]="Dividend",Table1[[#This Row],[Dividend per Share]],Table1[[#This Row],[Price]]) -> 16320000 | K7: =(exchange_fee+broker_fee)*J7 -> 31546.56 | L7: =SUM(Table1[[#This Row],[Amount]]:Table1[[#This Row],[Total Fee]]) -> 16351547 | M7: =IF(OR(Table1[[#This Row],[Action]]="Buy",Table1[[#This Row],[Action]]="Withdraw"),-Table1[[#This Row],[Net Amount]],Table1[[#This Row],[Net Amount]]) -> -16351547
A8: 45336 | B8: ="TX"&TEXT(ROW()-1,"0000") -> TX0007 | C8: TLKM | D8: Dividend | E8: 42 | F8: {=_xlfn.IFS(Table1[[#This Row],[Action]]="Buy",Table1[[#This Row],[Lot ]],Table1[[#This Row],[Action]]="Sell",-Table1[[#This Row],[Lot ]],Table1[[#This Row],[Action]]="Dividend",0,TRUE,"")} -> 0 | H8: {=IF(OR(Table1[[#This Row],[Stock Tickers]]="",Table1[[#This Row],[Action]]="Dividend"), "",IF(Table1[[#This Row],[Action]]="Buy",(SUMIFS($L$2:L8, $C$2:C8,Table1[[#This Row],[Stock Tickers]], $D$2:D8, "Buy") + Table1[[#This Row],[Amount]]) / ((SUMIFS($E$2:E8, $C$2:C8,Table1[[#This Row],[Stock Tickers]], $D$2:D8, "Buy") + Table1[[#This Row],[Lot ]])*100),LOOKUP(2, 1/($C$2:C8=Table1[[#This Row],[Stock Tickers]]), $G$2:G8)))} | I8: 178 | J8: =(Table1[[#This Row],[Lot ]]*100)*IF(Table1[[#This Row],[Action]]="Dividend",Table1[[#This Row],[Dividend per Share]],Table1[[#This Row],[Price]]) -> 747600 | L8: =SUM(Table1[[#This Row],[Amount]]:Table1[[#This Row],[Total Fee]]) -> 747600 | M8: =IF(OR(Table1[[#This Row],[Action]]="Buy",Table1[[#This Row],[Action]]="Withdraw"),-Table1[[#This Row],[Net Amount]],Table1[[#This Row],[Net Amount]]) -> 747600
A9: 45342 | B9: ="TX"&TEXT(ROW()-1,"0000") -> TX0008 | C9: ADRO | D9: Buy | E9: 38 | F9: {=_xlfn.IFS(Table1[[#This Row],[Action]]="Buy",Table1[[#This Row],[Lot ]],Table1[[#This Row],[Action]]="Sell",-Table1[[#This Row],[Lot ]],Table1[[#This Row],[Action]]="Dividend",0,TRUE,"")} -> 38 | G9: 2910 | H9: {=IF(OR(Table1[[#This Row],[Stock Tickers]]="",Table1[[#This Row],[Action]]="Dividend"), "",IF(Table1[[#This Row],[Action]]="Buy",(SUMIFS($L$2:L9, $C$2:C9,Table1[[#This Row],[Stock Tickers]], $D$2:D9, "Buy") + Table1[[#This Row],[Amount]]) / ((SUMIFS($E$2:E9, $C$2:C9,Table1[[#This Row],[Stock Tickers]], $D$2:D9, "Buy") + Table1[[#This Row],[Lot ]])*100),LOOKUP(2, 1/($C$2:C9=Table1[[#This Row],[Stock Tickers]]), $G$2:G9)))} -> 2830.9943 | J9: =(Table1[[#This Row],[Lot ]]*100)*IF(Table1[[#This Row],[Action]]="Dividend",Table1[[#This Row],[Dividend per Share]],Table1[[#This Row],[Price]]) -> 11058000 | K9: =(exchange_fee+broker_fee)*J9 -> 21375.114 | L9: =SUM(Table1[[#This Row],[Amount]]:Table1[[#This Row],[Total Fee]]) -> 11079375 | M9: =IF(OR(Table1[[#This Row],[Action]]="Buy",Table1[[#This Row],[Action]]="Withdraw"),-Table1[[#This Row],[Net Amount]],Table1[[#This Row],[Net Amount]]) -> -11079375
A10: 45350 | B10: ="TX"&TEXT(ROW()-1,"0000") -> TX0009 | D10: Deposit | F10: {=_xlfn.IFS(Table1[[#This Row],[Action]]="Buy",Table1[[#This Row],[Lot ]],Table1[[#This Row],[Action]]="Sell",-Table1[[#This Row],[Lot ]],Table1[[#This Row],[Action]]="Dividend",0,TRUE,"")} | H10: {=IF(OR(Table1[[#This Row],[Stock Tickers]]="",Table1[[#This Row],[Action]]="Dividend"), "",IF(Table1[[#This Row],[Action]]="Buy",(SUMIFS($L$2:L10, $C$2:C10,Table1[[#This Row],[Stock Tickers]], $D$2:D10, "Buy") + Table1[[#This Row],[Amount]]) / ((SUMIFS($E$2:E10, $C$2:C10,Table1[[#This Row],[Stock Tickers]], $D$2:D10, "Buy") + Table1[[#This Row],[Lot ]])*100),LOOKUP(2, 1/($C$2:C10=Table1[[#This Row],[Stock Tickers]]), $G$2:G10)))} | J10: 65000000 | L10: =SUM(Table1[[#This Row],[Amount]]:Table1[[#This Row],[Total Fee]]) -> 65000000 | M10: =IF(OR(Table1[[#This Row],[Action]]="Buy",Table1[[#This Row],[Action]]="Withdraw"),-Table1[[#This Row],[Net Amount]],Table1[[#This Row],[Net Amount]]) -> 65000000
A11: 45354 | B11: ="TX"&TEXT(ROW()-1,"0000") -> TX0010 | C11: ITMG | D11: Buy | E11: 10 | F11: {=_xlfn.IFS(Table1[[#This Row],[Action]]="Buy",Table1[[#This Row],[Lot ]],Table1[[#This Row],[Action]]="Sell",-Table1[[#This Row],[Lot ]],Table1[[#This Row],[Action]]="Dividend",0,TRUE,"")} -> 10 | G11: 30000 | H11: {=IF(OR(Table1[[#This Row],[Stock Tickers]]="",Table1[[#This Row],[Action]]="Dividend"), "",IF(Table1[[#This Row],[Action]]="Buy",(SUMIFS($L$2:L11, $C$2:C11,Table1[[#This Row],[Stock Tickers]], $D$2:D11, "Buy") + Table1[[#This Row],[Amount]]) / ((SUMIFS($E$2:E11, $C$2:C11,Table1[[#This Row],[Stock Tickers]], $D$2:D11, "Buy") + Table1[[#This Row],[Lot ]])*100),LOOKUP(2, 1/($C$2:C11=Table1[[#This Row],[Stock Tickers]]), $G$2:G11)))} -> 30028.995 | J11: =(Table1[[#This Row],[Lot ]]*100)*IF(Table1[[#This Row],[Action]]="Dividend",Table1[[#This Row],[Dividend per Share]],Table1[[#This Row],[Price]]) -> 30000000 | K11: =(exchange_fee+broker_fee)*J11 -> 57990 | L11: =SUM(Table1[[#This Row],[Amount]]:Table1[[#This Row],[Total Fee]]) -> 30057990 | M11: =IF(OR(Table1[[#This Row],[Action]]="Buy",Table1[[#This Row],[Action]]="Withdraw"),-Table1[[#This Row],[Net Amount]],Table1[[#This Row],[Net Amount]]) -> -30057990
A12: 45356 | B12: ="TX"&TEXT(ROW()-1,"0000") -> TX0011 | C12: BBRI | D12: Buy | E12: 10 | F12: {=_xlfn.IFS(Table1[[#This Row],[Action]]="Buy",Table1[[#This Row],[Lot ]],Table1[[#This Row],[Action]]="Sell",-Table1[[#This Row],[Lot ]],Table1[[#This Row],[Action]]="Dividend",0,TRUE,"")} -> 10 | G12: 2990 | H12: {=IF(OR(Table1[[#This Row],[Stock Tickers]]="",Table1[[#This Row],[Action]]="Dividend"), "",IF(Table1[[#This Row],[Action]]="Buy",(SUMIFS($L$2:L12, $C$2:C12,Table1[[#This Row],[Stock Tickers]], $D$2:D12, "Buy") + Table1[[#This Row],[Amount]]) / ((SUMIFS($E$2:E12, $C$2:C12,Table1[[#This Row],[Stock Tickers]], $D$2:D12, "Buy") + Table1[[#This Row],[Lot ]])*100),LOOKUP(2, 1/($C$2:C12=Table1[[#This Row],[Stock Tickers]]), $G$2:G12)))} -> 3445.3651 | J12: =(Table1[[#This Row],[Lot ]]*100)*IF(Table1[[#This Row],[Action]]="Dividend",Table1[[#This Row],[Dividend per Share]],Table1[[#This Row],[Price]]) -> 2990000 | K12: =(exchange_fee+broker_fee)*J12 -> 5779.67 | L12: =SUM(Table1[[#This Row],[Amount]]:Table1[[#This Row],[Total Fee]]) -> 2995779.7 | M12: =IF(OR(Table1[[#This Row],[Action]]="Buy",Table1[[#This Row],[Action]]="Withdraw"),-Table1[[#This Row],[Net Amount]],Table1[[#This Row],[Net Amount]]) -> -2995779.7
A13: 45366 | B13: ="TX"&TEXT(ROW()-1,"0000") -> TX0012 | C13: BBCA | D13: Buy | E13: 7 | F13: {=_xlfn.IFS(Table1[[#This Row],[Action]]="Buy",Table1[[#This Row],[Lot ]],Table1[[#This Row],[Action]]="Sell",-Table1[[#This Row],[Lot ]],Table1[[#This Row],[Action]]="Dividend",0,TRUE,"")} -> 7 | G13: 7200 | H13: {=IF(OR(Table1[[#This Row],[Stock Tickers]]="",Table1[[#This Row],[Action]]="Dividend"), "",IF(Table1[[#This Row],[Action]]="Buy",(SUMIFS($L$2:L13, $C$2:C13,Table1[[#This Row],[Stock Tickers]], $D$2:D13, "Buy") + Table1[[#This Row],[Amount]]) / ((SUMIFS($E$2:E13, $C$2:C13,Table1[[#This Row],[Stock Tickers]], $D$2:D13, "Buy") + Table1[[#This Row],[Lot ]])*100),LOOKUP(2, 1/($C$2:C13=Table1[[#This Row],[Stock Tickers]]), $G$2:G13)))} -> 7329.5104 | J13: =(Table1[[#This Row],[Lot ]]*100)*IF(Table1[[#This Row],[Action]]="Dividend",Table1[[#This Row],[Dividend per Share]],Table1[[#This Row],[Price]]) -> 5040000 | K13: =(exchange_fee+broker_fee)*J13 -> 9742.32 | L13: =SUM(Table1[[#This Row],[Amount]]:Table1[[#This Row],[Total Fee]]) -> 5049742.3 | M13: =IF(OR(Table1[[#This Row],[Action]]="Buy",Table1[[#This Row],[Action]]="Withdraw"),-Table1[[#This Row],[Net Amount]],Table1[[#This Row],[Net Amount]]) -> -5049742.3
A14: 45373 | B14: ="TX"&TEXT(ROW()-1,"0000") -> TX0013 | C14: ADRO | D14: Dividend | E14: 59 | F14: {=_xlfn.IFS(Table1[[#This Row],[Action]]="Buy",Table1[[#This Row],[Lot ]],Table1[[#This Row],[Action]]="Sell",-Table1[[#This Row],[Lot ]],Table1[[#This Row],[Action]]="Dividend",0,TRUE,"")} -> 0 | H14: {=IF(OR(Table1[[#This Row],[Stock Tickers]]="",Table1[[#This Row],[Action]]="Dividend"), "",IF(Table1[[#This Row],[Action]]="Buy",(SUMIFS($L$2:L14, $C$2:C14,Table1[[#This Row],[Stock Tickers]], $D$2:D14, "Buy") + Table1[[#This Row],[Amount]]) / ((SUMIFS($E$2:E14, $C$2:C14,Table1[[#This Row],[Stock Tickers]], $D$2:D14, "Buy") + Table1[[#This Row],[Lot ]])*100),LOOKUP(2, 1/($C$2:C14=Table1[[#This Row],[Stock Tickers]]), $G$2:G14)))} | I14: 315 | J14: =(Table1[[#This Row],[Lot ]]*100)*IF(Table1[[#This Row],[Action]]="Dividend",Table1[[#This Row],[Dividend per Share]],Table1[[#This Row],[Price]]) -> 1858500 | L14: =SUM(Table1[[#This Row],[Amount]]:Table1[[#This Row],[Total Fee]]) -> 1858500 | M14: =IF(OR(Table1[[#This Row],[Action]]="Buy",Table1[[#This Row],[Action]]="Withdraw"),-Table1[[#This Row],[Net Amount]],Table1[[#This Row],[Net Amount]]) -> 1858500
A15: 45378 | B15: ="TX"&TEXT(ROW()-1,"0000") -> TX0014 | D15: Deposit | F15: {=_xlfn.IFS(Table1[[#This Row],[Action]]="Buy",Table1[[#This Row],[Lot ]],Table1[[#This Row],[Action]]="Sell",-Table1[[#This Row],[Lot ]],Table1[[#This Row],[Action]]="Dividend",0,TRUE,"")} | H15: {=IF(OR(Table1[[#This Row],[Stock Tickers]]="",Table1[[#This Row],[Action]]="Dividend"), "",IF(Table1[[#This Row],[Action]]="Buy",(SUMIFS($L$2:L15, $C$2:C15,Table1[[#This Row],[Stock Tickers]], $D$2:D15, "Buy") + Table1[[#This Row],[Amount]]) / ((SUMIFS($E$2:E15, $C$2:C15,Table1[[#This Row],[Stock Tickers]], $D$2:D15, "Buy") + Table1[[#This Row],[Lot ]])*100),LOOKUP(2, 1/($C$2:C15=Table1[[#This Row],[Stock Tickers]]), $G$2:G15)))} | J15: 45000000 | L15: =SUM(Table1[[#This Row],[Amount]]:Table1[[#This Row],[Total Fee]]) -> 45000000 | M15: =IF(OR(Table1[[#This Row],[Action]]="Buy",Table1[[#This Row],[Action]]="Withdraw"),-Table1[[#This Row],[Net Amount]],Table1[[#This Row],[Net Amount]]) -> 45000000
A16: 45386 | B16: ="TX"&TEXT(ROW()-1,"0000") -> TX0015 | C16: ICBP | D16: Buy | E16: 5 | F16: {=_xlfn.IFS(Table1[[#This Row],[Action]]="Buy",Table1[[#This Row],[Lot ]],Table1[[#This Row],[Action]]="Sell",-Table1[[#This Row],[Lot ]],Table1[[#This Row],[Action]]="Dividend",0,TRUE,"")} -> 5 | G16: 1150 | H16: {=IF(OR(Table1[[#This Row],[Stock Tickers]]="",Table1[[#This Row],[Action]]="Dividend"), "",IF(Table1[[#This Row],[Action]]="Buy",(SUMIFS($L$2:L16, $C$2:C16,Table1[[#This Row],[Stock Tickers]], $D$2:D16, "Buy") + Table1[[#This Row],[Amount]]) / ((SUMIFS($E$2:E16, $C$2:C16,Table1[[#This Row],[Stock Tickers]], $D$2:D16, "Buy") + Table1[[#This Row],[Lot ]])*100),LOOKUP(2, 1/($C$2:C16=Table1[[#This Row],[Stock Tickers]]), $G$2:G16)))} -> 1151.1115 | J16: =(Table1[[#This Row],[Lot ]]*100)*IF(Table1[[#This Row],[Action]]="Dividend",Table1[[#This Row],[Dividend per Share]],Table1[[#This Row],[Price]]) -> 575000 | K16: =(exchange_fee+broker_fee)*J16 -> 1111.475 | L16: =SUM(Table1[[#This Row],[Amount]]:Table1[[#This Row],[Total Fee]]) -> 576111.47 | M16: =IF(OR(Table1[[#This Row],[Action]]="Buy",Table1[[#This Row],[Action]]="Withdraw"),-Table1[[#This Row],[Net Amount]],Table1[[#This Row],[Net Amount]]) -> -576111.47
A17: 45392 | B17: ="TX"&TEXT(ROW()-1,"0000") -> TX0016 | C17: TLKM | D17: Buy | E17: 11 | F17: {=_xlfn.IFS(Table1[[#This Row],[Action]]="Buy",Table1[[#This Row],[Lot ]],Table1[[#This Row],[Action]]="Sell",-Table1[[#This Row],[Lot ]],Table1[[#This Row],[Action]]="Dividend",0,TRUE,"")} -> 11 | G17: 3840 | H17: {=IF(OR(Table1[[#This Row],[Stock Tickers]]="",Table1[[#This Row],[Action]]="Dividend"), "",IF(Table1[[#This Row],[Action]]="Buy",(SUMIFS($L$2:L17, $C$2:C17,Table1[[#This Row],[Stock Tickers]], $D$2:D17, "Buy") + Table1[[#This Row],[Amount]]) / ((SUMIFS($E$2:E17, $C$2:C17,Table1[[#This Row],[Stock Tickers]], $D$2:D17, "Buy") + Table1[[#This Row],[Lot ]])*100),LOOKUP(2, 1/($C$2:C17=Table1[[#This Row],[Stock Tickers]]), $G$2:G17)))} -> 3326.7073 | J17: =(Table1[[#This Row],[Lot ]]*100)*IF(Table1[[#This Row],[Action]]="Dividend",Table1[[#This Row],[Dividend per Share]],Table1[[#This Row],[Price]]) -> 4224000 | K17: =(exchange_fee+broker_fee)*J17 -> 8164.992 | L17: =SUM(Table1[[#This Row],[Amount]]:Table1[[#This Row],[Total Fee]]) -> 4232165 | M17: =IF(OR(Table1[[#This Row],[Action]]="Buy",Table1[[#This Row],[Action]]="Withdraw"),-Table1[[#This Row],[Net Amount]],Table1[[#This Row],[Net Amount]]) -> -4232165
A18: 45398 | B18: ="TX"&TEXT(ROW()-1,"0000") -> TX0017 | C18: BBRI | D18: Sell | E18: 4 | F18: {=_xlfn.IFS(Table1[[#This Row],[Action]]="Buy",Table1[[#This Row],[Lot ]],Table1[[#This Row],[Action]]="Sell",-Table1[[#This Row],[Lot ]],Table1[[#This Row],[Action]]="Dividend",0,TRUE,"")} -> -4 | G18: 6320 | H18: {=IF(OR(Table1[[#This Row],[Stock Tickers]]="",Table1[[#This Row],[Action]]="Dividend"), "",IF(Table1[[#This Row],[Action]]="Buy",(SUMIFS($L$2:L18, $C$2:C18,Table1[[#This Row],[Stock Tickers]], $D$2:D18, "Buy") + Table1[[#This Row],[Amount]]) / ((SUMIFS($E$2:E18, $C$2:C18,Table1[[#This Row],[Stock Tickers]], $D$2:D18, "Buy") + Table1[[#This Row],[Lot ]])*100),LOOKUP(2, 1/($C$2:C18=Table1[[#This Row],[Stock Tickers]]), $G$2:G18)))} -> 6320 | J18: =(Table1[[#This Row],[Lot ]]*100)*IF(Table1[[#This Row],[Action]]="Dividend",Table1[[#This Row],[Dividend per Share]],Table1[[#This Row],[Price]]) -> 2528000 | K18: =(exchange_fee+broker_fee)*J18 -> 4886.624 | L18: =SUM(Table1[[#This Row],[Amount]]:Table1[[#This Row],[Total Fee]]) -> 2532886.6 | M18: =IF(OR(Table1[[#This Row],[Action]]="Buy",Table1[[#This Row],[Action]]="Withdraw"),-Table1[[#This Row],[Net Amount]],Table1[[#This Row],[Net Amount]]) -> 2532886.6
A19: 45405 | B19: ="TX"&TEXT(ROW()-1,"0000") -> TX0018 | C19: BBCA | D19: Dividend | E19: 14 | F19: {=_xlfn.IFS(Table1[[#This Row],[Action]]="Buy",Table1[[#This Row],[Lot ]],Table1[[#This Row],[Action]]="Sell",-Table1[[#This Row],[Lot ]],Table1[[#This Row],[Action]]="Dividend",0,TRUE,"")} -> 0 | H19: {=IF(OR(Table1[[#This Row],[Stock Tickers]]="",Table1[[#This Row],[Action]]="Dividend"), "",IF(Table1[[#This Row],[Action]]="Buy",(SUMIFS($L$2:L19, $C$2:C19,Table1[[#This Row],[Stock Tickers]], $D$2:D19, "Buy") + Table1[[#This Row],[Amount]]) / ((SUMIFS($E$2:E19, $C$2:C19,Table1[[#This Row],[Stock Tickers]], $D$2:D19, "Buy") + Table1[[#This Row],[Lot ]])*100),LOOKUP(2, 1/($C$2:C19=Table1[[#This Row],[Stock Tickers]]), $G$2:G19)))} | I19: 50 | J19: =(Table1[[#This Row],[Lot ]]*100)*IF(Table1[[#This Row],[Action]]="Dividend",Table1[[#This Row],[Dividend per Share]],Table1[[#This Row],[Price]]) -> 70000 | L19: =SUM(Table1[[#This Row],[Amount]]:Table1[[#This Row],[Total Fee]]) -> 70000 | M19: =IF(OR(Table1[[#This Row],[Action]]="Buy",Table1[[#This Row],[Action]]="Withdraw"),-Table1[[#This Row],[Net Amount]],Table1[[#This Row],[Net Amount]]) -> 70000
A20: 45412 | B20: ="TX"&TEXT(ROW()-1,"0000") -> TX0019 | C20: ASII | D20: Buy | E20: 24 | F20: {=_xlfn.IFS(Table1[[#This Row],[Action]]="Buy",Table1[[#This Row],[Lot ]],Table1[[#This Row],[Action]]="Sell",-Table1[[#This Row],[Lot ]],Table1[[#This Row],[Action]]="Dividend",0,TRUE,"")} -> 24 | G20: 4410 | H20: {=IF(OR(Table1[[#This Row],[Stock Tickers]]="",Table1[[#This Row],[Action]]="Dividend"), "",IF(Table1[[#This Row],[Action]]="Buy",(SUMIFS($L$2:L20, $C$2:C20,Table1[[#This Row],[Stock Tickers]], $D$2:D20, "Buy") + Table1[[#This Row],[Amount]]) / ((SUMIFS($E$2:E20, $C$2:C20,Table1[[#This Row],[Stock Tickers]], $D$2:D20, "Buy") + Table1[[#This Row],[Lot ]])*100),LOOKUP(2, 1/($C$2:C20=Table1[[#This Row],[Stock Tickers]]), $G$2:G20)))} -> 4692.5007 | J20: =(Table1[[#This Row],[Lot ]]*100)*IF(Table1[[#This Row],[Action]]="Dividend",Table1[[#This Row],[Dividend per Share]],Table1[[#This Row],[Price]]) -> 10584000 | K20: =(exchange_fee+broker_fee)*J20 -> 20458.872 | L20: =SUM(Table1[[#This Row],[Amount]]:Table1[[#This Row],[Total Fee]]) -> 10604459 | M20: =IF(OR(Table1[[#This Row],[Action]]="Buy",Table1[[#This Row],[Action]]="Withdraw"),-Table1[[#This Row],[Net Amount]],Table1[[#This Row],[Net Amount]]) -> -10604459
A21: 45417 | B21: ="TX"&TEXT(ROW()-1,"0000") -> TX0020 | C21: BBRI | D21: Sell | E21: 10 | F21: {=_xlfn.IFS(Table1[[#This Row],[Action]]="Buy",Table1[[#This Row],[Lot ]],Table1[[#This Row],[Action]]="Sell",-Table1[[#This Row],[Lot ]],Table1[[#This Row],[Action]]="Dividend",0,TRUE,"")} -> -10 | G21: 6570 | H21: {=IF(OR(Table1[[#This Row],[Stock Tickers]]="",Table1[[#This Row],[Action]]="Dividend"), "",IF(Table1[[#This Row],[Action]]="Buy",(SUMIFS($L$2:L21, $C$2:C21,Table1[[#This Row],[Stock Tickers]], $D$2:D21, "Buy") + Table1[[#This Row],[Amount]]) / ((SUMIFS($E$2:E21, $C$2:C21,Table1[[#This Row],[Stock Tickers]], $D$2:D21, "Buy") + Table1[[#This Row],[Lot ]])*100),LOOKUP(2, 1/($C$2:C21=Table1[[#This Row],[Stock Tickers]]), $G$2:G21)))} -> 6570 | J21: =(Table1[[#This Row],[Lot ]]*100)*IF(Table1[[#This Row],[Action]]="Dividend",Table1[[#This Row],[Dividend per Share]],Table1[[#This Row],[Price]]) -> 6570000 | K21: =(exchange_fee+broker_fee)*J21 -> 12699.81 | L21: =SUM(Table1[[#This Row],[Amount]]:Table1[[#This Row],[Total Fee]]) -> 6582699.8 | M21: =IF(OR(Table1[[#This Row],[Action]]="Buy",Table1[[#This Row],[Action]]="Withdraw"),-Table1[[#This Row],[Net Amount]],Table1[[#This Row],[Net Amount]]) -> 6582699.8
A22: 45418 | B22: ="TX"&TEXT(ROW()-1,"0000") -> TX0021 | C22: GOTO | D22: Buy | E22: 100 | F22: {=_xlfn.IFS(Table1[[#This Row],[Action]]="Buy",Table1[[#This Row],[Lot ]],Table1[[#This Row],[Action]]="Sell",-Table1[[#This Row],[Lot ]],Table1[[#This Row],[Action]]="Dividend",0,TRUE,"")} -> 100 | G22: 128 | H22: {=IF(OR(Table1[[#This Row],[Stock Tickers]]="",Table1[[#This Row],[Action]]="Dividend"), "",IF(Table1[[#This Row],[Action]]="Buy",(SUMIFS($L$2:L22, $C$2:C22,Table1[[#This Row],[Stock Tickers]], $D$2:D22, "Buy") + Table1[[#This Row],[Amount]]) / ((SUMIFS($E$2:E22, $C$2:C22,Table1[[#This Row],[Stock Tickers]], $D$2:D22, "Buy") + Table1[[#This Row],[Lot ]])*100),LOOKUP(2, 1/($C$2:C22=Table1[[#This Row],[Stock Tickers]]), $G$2:G22)))} -> 128.12371 | J22: =(Table1[[#This Row],[Lot ]]*100)*IF(Table1[[#This Row],[Action]]="Dividend",Table1[[#This Row],[Dividend per Share]],Table1[[#This Row],[Price]]) -> 1280000 | K22: =(exchange_fee+broker_fee)*J22 -> 2474.24 | L22: =SUM(Table1[[#This Row],[Amount]]:Table1[[#This Row],[Total Fee]]) -> 1282474.2 | M22: =IF(OR(Table1[[#This Row],[Action]]="Buy",Table1[[#This Row],[Action]]="Withdraw"),-Table1[[#This Row],[Net Amount]],Table1[[#This Row],[Net Amount]]) -> -1282474.2
A23: 45429 | B23: ="TX"&TEXT(ROW()-1,"0000") -> TX0022 | C23: ADRO | D23: Buy | E23: 14 | F23: {=_xlfn.IFS(Table1[[#This Row],[Action]]="Buy",Table1[[#This Row],[Lot ]],Table1[[#This Row],[Action]]="Sell",-Table1[[#This Row],[Lot ]],Table1[[#This Row],[Action]]="Dividend",0,TRUE,"")} -> 14 | G23: 1870 | H23: {=IF(OR(Table1[[#This Row],[Stock Tickers]]="",Table1[[#This Row],[Action]]="Dividend"), "",IF(Table1[[#This Row],[Action]]="Buy",(SUMIFS($L$2:L23, $C$2:C23,Table1[[#This Row],[Stock Tickers]], $D$2:D23, "Buy") + Table1[[#This Row],[Amount]]) / ((SUMIFS($E$2:E23, $C$2:C23,Table1[[#This Row],[Stock Tickers]], $D$2:D23, "Buy") + Table1[[#This Row],[Lot ]])*100),LOOKUP(2, 1/($C$2:C23=Table1[[#This Row],[Stock Tickers]]), $G$2:G23)))} -> 2487.7823 | J23: =(Table1[[#This Row],[Lot ]]*100)*IF(Table1[[#This Row],[Action]]="Dividend",Table1[[#This Row],[Dividend per Share]],Table1[[#This Row],[Price]]) -> 2618000 | K23: =(exchange_fee+broker_fee)*J23 -> 5060.594 | L23: =SUM(Table1[[#This Row],[Amount]]:Table1[[#This Row],[Total Fee]]) -> 2623060.6 | M23: =IF(OR(Table1[[#This Row],[Action]]="Buy",Table1[[#This Row],[Action]]="Withdraw"),-Table1[[#This Row],[Net Amount]],Table1[[#This Row],[Net Amount]]) -> -2623060.6
A24: 45436 | B24: ="TX"&TEXT(ROW()-1,"0000") -> TX0023 | C24: ASII | D24: Dividend | E24: 56 | F24: {=_xlfn.IFS(Table1[[#This Row],[Action]]="Buy",Table1[[#This Row],[Lot ]],Table1[[#This Row],[Action]]="Sell",-Table1[[#This Row],[Lot ]],Table1[[#This Row],[Action]]="Dividend",0,TRUE,"")} -> 0 | H24: {=IF(OR(Table1[[#This Row],[Stock Tickers]]="",Table1[[#This Row],[Action]]="Dividend"), "",IF(Table1[[#This Row],[Action]]="Buy",(SUMIFS($L$2:L24, $C$2:C24,Table1[[#This Row],[Stock Tickers]], $D$2:D24, "Buy") + Table1[[#This Row],[Amount]]) / ((SUMIFS($E$2:E24, $C$2:C24,Table1[[#This Row],[Stock Tickers]], $D$2:D24, "Buy") + Table1[[#This Row],[Lot ]])*100),LOOKUP(2, 1/($C$2:C24=Table1[[#This Row],[Stock Tickers]]), $G$2:G24)))} | I24: 519 | J24: =(Table1[[#This Row],[Lot ]]*100)*IF(Table1[[#This Row],[Action]]="Dividend",Table1[[#This Row],[Dividend per Share]],Table1[[#This Row],[Price]]) -> 2906400 | L24: =SUM(Table1[[#This Row],[Amount]]:Table1[[#This Row],[Total Fee]]) -> 2906400 | M24: =IF(OR(Table1[[#This Row],[Action]]="Buy",Table1[[#This Row],[Action]]="Withdraw"),-Table1[[#This Row],[Net Amount]],Table1[[#This Row],[Net Amount]]) -> 2906400
A25: 45442 | B25: ="TX"&TEXT(ROW()-1,"0000") -> TX0024 | C25: BBRI | D25: Buy | E25: 12 | F25: {=_xlfn.IFS(Table1[[#This Row],[Action]]="Buy",Table1[[#This Row],[Lot ]],Table1[[#This Row],[Action]]="Sell",-Table1[[#This Row],[Lot ]],Table1[[#This Row],[Action]]="Dividend",0,TRUE,"")} -> 12 | G25: 4440 | H25: {=IF(OR(Table1[[#This Row],[Stock Tickers]]="",Table1[[#This Row],[Action]]="Dividend"), "",IF(Table1[[#This Row],[Action]]="Buy",(SUMIFS($L$2:L25, $C$2:C25,Table1[[#This Row],[Stock Tickers]], $D$2:D25, "Buy") + Table1[[#This Row],[Amount]]) / ((SUMIFS($E$2:E25, $C$2:C25,Table1[[#This Row],[Stock Tickers]], $D$2:D25, "Buy") + Table1[[#This Row],[Lot ]])*100),LOOKUP(2, 1/($C$2:C25=Table1[[#This Row],[Stock Tickers]]), $G$2:G25)))} -> 3928.8885 | J25: =(Table1[[#This Row],[Lot ]]*100)*IF(Table1[[#This Row],[Action]]="Dividend",Table1[[#This Row],[Dividend per Share]],Table1[[#This Row],[Price]]) -> 5328000 | K25: =(exchange_fee+broker_fee)*J25 -> 10299.024 | L25: =SUM(Table1[[#This Row],[Amount]]:Table1[[#This Row],[Total Fee]]) -> 5338299 | M25: =IF(OR(Table1[[#This Row],[Action]]="Buy",Table1[[#This Row],[Action]]="Withdraw"),-Table1[[#This Row],[Net Amount]],Table1[[#This Row],[Net Amount]]) -> -5338299
A26: 45449 | B26: ="TX"&TEXT(ROW()-1,"0000") -> TX0025 | C26: ITMG | D26: Buy | E26: 5 | F26: {=_xlfn.IFS(Table1[[#This Row],[Action]]="Buy",Table1[[#This Row],[Lot ]],Table1[[#This Row],[Action]]="Sell",-Table1[[#This Row],[Lot ]],Table1[[#This Row],[Action]]="Dividend",0,TRUE,"")} -> 5 | G26: 31100 | H26: {=IF(OR(Table1[[#This Row],[Stock Tickers]]="",Table1[[#This Row],[Action]]="Dividend"), "",IF(Table1[[#This Row],[Action]]="Buy",(SUMIFS($L$2:L26, $C$2:C26,Table1[[#This Row],[Stock Tickers]], $D$2:D26, "Buy") + Table1[[#This Row],[Amount]]) / ((SUMIFS($E$2:E26, $C$2:C26,Table1[[#This Row],[Stock Tickers]], $D$2:D26, "Buy") + Table1[[#This Row],[Lot ]])*100),LOOKUP(2, 1/($C$2:C26=Table1[[#This Row],[Stock Tickers]]), $G$2:G26)))} -> 30594.024 | J26: =(Table1[[#This Row],[Lot ]]*100)*IF(Table1[[#This Row],[Action]]="Dividend",Table1[[#This Row],[Dividend per Share]],Table1[[#This Row],[Price]]) -> 15550000 | K26: =(exchange_fee+broker_fee)*J26 -> 30058.15 | L26: =SUM(Table1[[#This Row],[Amount]]:Table1[[#This Row],[Total Fee]]) -> 15580058 | M26: =IF(OR(Table1[[#This Row],[Action]]="Buy",Table1[[#This Row],[Action]]="Withdraw"),-Table1[[#This Row],[Net Amount]],Table1[[#This Row],[Net Amount]]) -> -15580058
A27: 45455 | B27: ="TX"&TEXT(ROW()-1,"0000") -> TX0026 | C27: ICBP | D27: Buy | E27: 7 | F27: {=_xlfn.IFS(Table1[[#This Row],[Action]]="Buy",Table1[[#This Row],[Lot ]],Table1[[#This Row],[Action]]="Sell",-Table1[[#This Row],[Lot ]],Table1[[#This Row],[Action]]="Dividend",0,TRUE,"")} -> 7 | G27: 1060 | H27: {=IF(OR(Table1[[#This Row],[Stock Tickers]]="",Table1[[#This Row],[Action]]="Dividend"), "",IF(Table1[[#This Row],[Action]]="Buy",(SUMIFS($L$2:L27, $C$2:C27,Table1[[#This Row],[Stock Tickers]], $D$2:D27, "Buy") + Table1[[#This Row],[Amount]]) / ((SUMIFS($E$2:E27, $C$2:C27,Table1[[#This Row],[Stock Tickers]], $D$2:D27, "Buy") + Table1[[#This Row],[Lot ]])*100),LOOKUP(2, 1/($C$2:C27=Table1[[#This Row],[Stock Tickers]]), $G$2:G27)))} -> 1085.0241 | J27: =(Table1[[#This Row],[Lot ]]*100)*IF(Table1[[#This Row],[Action]]="Dividend",Table1[[#This Row],[Dividend per Share]],Table1[[#This Row],[Price]]) -> 742000 | K27: =(exchange_fee+broker_fee)*J27 -> 1434.286 | L27: =SUM(Table1[[#This Row],[Amount]]:Table1[[#This Row],[Total Fee]]) -> 743434.29 | M27: =IF(OR(Table1[[#This Row],[Action]]="Buy",Table1[[#This Row],[Action]]="Withdraw"),-Table1[[#This Row],[Net Amount]],Table1[[#This Row],[Net Amount]]) -> -743434.29
A28: 45461 | B28: ="TX"&TEXT(ROW()-1,"0000") -> TX0027 | C28: BBCA | D28: Buy | E28: 6 | F28: {=_xlfn.IFS(Table1[[#This Row],[Action]]="Buy",Table1[[#This Row],[Lot ]],Table1[[#This Row],[Action]]="Sell",-Table1[[#This Row],[Lot ]],Table1[[#This Row],[Action]]="Dividend",0,TRUE,"")} -> 6 | G28: 6190 | H28: {=IF(OR(Table1[[#This Row],[Stock Tickers]]="",Table1[[#This Row],[Action]]="Dividend"), "",IF(Table1[[#This Row],[Action]]="Buy",(SUMIFS($L$2:L28, $C$2:C28,Table1[[#This Row],[Stock Tickers]], $D$2:D28, "Buy") + Table1[[#This Row],[Amount]]) / ((SUMIFS($E$2:E28, $C$2:C28,Table1[[#This Row],[Stock Tickers]], $D$2:D28, "Buy") + Table1[[#This Row],[Lot ]])*100),LOOKUP(2, 1/($C$2:C28=Table1[[#This Row],[Stock Tickers]]), $G$2:G28)))} -> 6841.2119 | J28: =(Table1[[#This Row],[Lot ]]*100)*IF(Table1[[#This Row],[Action]]="Dividend",Table1[[#This Row],[Dividend per Share]],Table1[[#This Row],[Price]]) -> 3714000 | K28: =(exchange_fee+broker_fee)*J28 -> 7179.162 | L28: =SUM(Table1[[#This Row],[Amount]]:Table1[[#This Row],[Total Fee]]) -> 3721179.2 | M28: =IF(OR(Table1[[#This Row],[Action]]="Buy",Table1[[#This Row],[Action]]="Withdraw"),-Table1[[#This Row],[Net Amount]],Table1[[#This Row],[Net Amount]]) -> -3721179.2
A29: 45470 | B29: ="TX"&TEXT(ROW()-1,"0000") -> TX0028 | D29: Deposit | F29: {=_xlfn.IFS(Table1[[#This Row],[Action]]="Buy",Table1[[#This Row],[Lot ]],Table1[[#This Row],[Action]]="Sell",-Table1[[#This Row],[Lot ]],Table1[[#This Row],[Action]]="Dividend",0,TRUE,"")} | H29: {=IF(OR(Table1[[#This Row],[Stock Tickers]]="",Table1[[#This Row],[Action]]="Dividend"), "",IF(Table1[[#This Row],[Action]]="Buy",(SUMIFS($L$2:L29, $C$2:C29,Table1[[#This Row],[Stock Tickers]], $D$2:D29, "Buy") + Table1[[#This Row],[Amount]]) / ((SUMIFS($E$2:E29, $C$2:C29,Table1[[#This Row],[Stock Tickers]], $D$2:D29, "Buy") + Table1[[#This Row],[Lot ]])*100),LOOKUP(2, 1/($C$2:C29=Table1[[#This Row],[Stock Tickers]]), $G$2:G29)))} | J29: 60000000 | L29: =SUM(Table1[[#This Row],[Amount]]:Table1[[#This Row],[Total Fee]]) -> 60000000 | M29: =IF(OR(Table1[[#This Row],[Action]]="Buy",Table1[[#This Row],[Action]]="Withdraw"),-Table1[[#This Row],[Net Amount]],Table1[[#This Row],[Net Amount]]) -> 60000000
A30: 45473 | B30: ="TX"&TEXT(ROW()-1,"0000") -> TX0029 | C30: ITMG | D30: Dividend | E30: 15 | F30: {=_xlfn.IFS(Table1[[#This Row],[Action]]="Buy",Table1[[#This Row],[Lot ]],Table1[[#This Row],[Action]]="Sell",-Table1[[#This Row],[Lot ]],Table1[[#This Row],[Action]]="Dividend",0,TRUE,"")} -> 0 | H30: {=IF(OR(Table1[[#This Row],[Stock Tickers]]="",Table1[[#This Row],[Action]]="Dividend"), "",IF(Table1[[#This Row],[Action]]="Buy",(SUMIFS($L$2:L30, $C$2:C30,Table1[[#This Row],[Stock Tickers]], $D$2:D30, "Buy") + Table1[[#This Row],[Amount]]) / ((SUMIFS($E$2:E30, $C$2:C30,Table1[[#This Row],[Stock Tickers]], $D$2:D30, "Buy") + Table1[[#This Row],[Lot ]])*100),LOOKUP(2, 1/($C$2:C30=Table1[[#This Row],[Stock Tickers]]), $G$2:G30)))} | I30: 2975 | J30: =(Table1[[#This Row],[Lot ]]*100)*IF(Table1[[#This Row],[Action]]="Dividend",Table1[[#This Row],[Dividend per Share]],Table1[[#This Row],[Price]]) -> 4462500 | L30: =SUM(Table1[[#This Row],[Amount]]:Table1[[#This Row],[Total Fee]]) -> 4462500 | M30: =IF(OR(Table1[[#This Row],[Action]]="Buy",Table1[[#This Row],[Action]]="Withdraw"),-Table1[[#This Row],[Net Amount]],Table1[[#This Row],[Net Amount]]) -> 4462500
A31: 45480 | B31: ="TX"&TEXT(ROW()-1,"0000") -> TX0030 | C31: ASII | D31: Buy | E31: 12 | F31: {=_xlfn.IFS(Table1[[#This Row],[Action]]="Buy",Table1[[#This Row],[Lot ]],Table1[[#This Row],[Action]]="Sell",-Table1[[#This Row],[Lot ]],Table1[[#This Row],[Action]]="Dividend",0,TRUE,"")} -> 12 | G31: 4950 | H31: {=IF(OR(Table1[[#This Row],[Stock Tickers]]="",Table1[[#This Row],[Action]]="Dividend"), "",IF(Table1[[#This Row],[Action]]="Buy",(SUMIFS($L$2:L31, $C$2:C31,Table1[[#This Row],[Stock Tickers]], $D$2:D31, "Buy") + Table1[[#This Row],[Amount]]) / ((SUMIFS($E$2:E31, $C$2:C31,Table1[[#This Row],[Stock Tickers]], $D$2:D31, "Buy") + Table1[[#This Row],[Lot ]])*100),LOOKUP(2, 1/($C$2:C31=Table1[[#This Row],[Stock Tickers]]), $G$2:G31)))} -> 4855.9359 | J31: =(Table1[[#This Row],[Lot ]]*100)*IF(Table1[[#This Row],[Action]]="Dividend",Table1[[#This Row],[Dividend per Share]],Table1[[#This Row],[Price]]) -> 5940000 | K31: =(exchange_fee+broker_fee)*J31 -> 11482.02 | L31: =SUM(Table1[[#This Row],[Amount]]:Table1[[#This Row],[Total Fee]]) -> 5951482 | M31: =IF(OR(Table1[[#This Row],[Action]]="Buy",Table1[[#This Row],[Action]]="Withdraw"),-Table1[[#This Row],[Net Amount]],Table1[[#This Row],[Net Amount]]) -> -5951482
A32: 45481 | B32: ="TX"&TEXT(ROW()-1,"0000") -> TX0031 | C32: ITMG | D32: Buy | E32: 14 | F32: {=_xlfn.IFS(Table1[[#This Row],[Action]]="Buy",Table1[[#This Row],[Lot ]],Table1[[#This Row],[Action]]="Sell",-Table1[[#This Row],[Lot ]],Table1[[#This Row],[Action]]="Dividend",0,TRUE,"")} -> 14 | G32: 27300 | H32: {=IF(OR(Table1[[#This Row],[Stock Tickers]]="",Table1[[#This Row],[Action]]="Dividend"), "",IF(Table1[[#This Row],[Action]]="Buy",(SUMIFS($L$2:L32, $C$2:C32,Table1[[#This Row],[Stock Tickers]], $D$2:D32, "Buy") + Table1[[#This Row],[Amount]]) / ((SUMIFS($E$2:E32, $C$2:C32,Table1[[#This Row],[Stock Tickers]], $D$2:D32, "Buy") + Table1[[#This Row],[Lot ]])*100),LOOKUP(2, 1/($C$2:C32=Table1[[#This Row],[Stock Tickers]]), $G$2:G32)))} -> 28407.425 | J32: =(Table1[[#This Row],[Lot ]]*100)*IF(Table1[[#This Row],[Action]]="Dividend",Table1[[#This Row],[Dividend per Share]],Table1[[#This Row],[Price]]) -> 38220000 | K32: =(exchange_fee+broker_fee)*J32 -> 73879.26 | L32: =SUM(Table1[[#This Row],[Amount]]:Table1[[#This Row],[Total Fee]]) -> 38293879 | M32: =IF(OR(Table1[[#This Row],[Action]]="Buy",Table1[[#This Row],[Action]]="Withdraw"),-Table1[[#This Row],[Net Amount]],Table1[[#This Row],[Net Amount]]) -> -38293879
A33: 45488 | B33: ="TX"&TEXT(ROW()-1,"0000") -> TX0032 | C33: BBRI | D33: Buy | E33: 9 | F33: {=_xlfn.IFS(Table1[[#This Row],[Action]]="Buy",Table1[[#This Row],[Lot ]],Table1[[#This Row],[Action]]="Sell",-Table1[[#This Row],[Lot ]],Table1[[#This Row],[Action]]="Dividend",0,TRUE,"")} -> 9 | G33: 4170 | H33: {=IF(OR(Table1[[#This Row],[Stock Tickers]]="",Table1[[#This Row],[Action]]="Dividend"), "",IF(Table1[[#This Row],[Action]]="Buy",(SUMIFS($L$2:L33, $C$2:C33,Table1[[#This Row],[Stock Tickers]], $D$2:D33, "Buy") + Table1[[#This Row],[Amount]]) / ((SUMIFS($E$2:E33, $C$2:C33,Table1[[#This Row],[Stock Tickers]], $D$2:D33, "Buy") + Table1[[#This Row],[Lot ]])*100),LOOKUP(2, 1/($C$2:C33=Table1[[#This Row],[Stock Tickers]]), $G$2:G33)))} -> 3902.4149 | J33: =(Table1[[#This Row],[Lot ]]*100)*IF(Table1[[#This Row],[Action]]="Dividend",Table1[[#This Row],[Dividend per Share]],Table1[[#This Row],[Price]]) -> 3753000 | K33: =(exchange_fee+broker_fee)*J33 -> 7254.549 | L33: =SUM(Table1[[#This Row],[Amount]]:Table1[[#This Row],[Total Fee]]) -> 3760254.5 | M33: =IF(OR(Table1[[#This Row],[Action]]="Buy",Table1[[#This Row],[Action]]="Withdraw"),-Table1[[#This Row],[Net Amount]],Table1[[#This Row],[Net Amount]]) -> -3760254.5
A34: 45495 | B34: ="TX"&TEXT(ROW()-1,"0000") -> TX0033 | D34: Deposit | F34: {=_xlfn.IFS(Table1[[#This Row],[Action]]="Buy",Table1[[#This Row],[Lot ]],Table1[[#This Row],[Action]]="Sell",-Table1[[#This Row],[Lot ]],Table1[[#This Row],[Action]]="Dividend",0,TRUE,"")} | H34: {=IF(OR(Table1[[#This Row],[Stock Tickers]]="",Table1[[#This Row],[Action]]="Dividend"), "",IF(Table1[[#This Row],[Action]]="Buy",(SUMIFS($L$2:L34, $C$2:C34,Table1[[#This Row],[Stock Tickers]], $D$2:D34, "Buy") + Table1[[#This Row],[Amount]]) / ((SUMIFS($E$2:E34, $C$2:C34,Table1[[#This Row],[Stock Tickers]], $D$2:D34, "Buy") + Table1[[#This Row],[Lot ]])*100),LOOKUP(2, 1/($C$2:C34=Table1[[#This Row],[Stock Tickers]]), $G$2:G34)))} | J34: 100000000 | L34: =SUM(Table1[[#This Row],[Amount]]:Table1[[#This Row],[Total Fee]]) -> 100000000 | M34: =IF(OR(Table1[[#This Row],[Action]]="Buy",Table1[[#This Row],[Action]]="Withdraw"),-Table1[[#This Row],[Net Amount]],Table1[[#This Row],[Net Amount]]) -> 100000000
A35: 45504 | B35: ="TX"&TEXT(ROW()-1,"0000") -> TX0034 | C35: TLKM | D35: Buy | E35: 15 | F35: {=_xlfn.IFS(Table1[[#This Row],[Action]]="Buy",Table1[[#This Row],[Lot ]],Table1[[#This Row],[Action]]="Sell",-Table1[[#This Row],[Lot ]],Table1[[#This Row],[Action]]="Dividend",0,TRUE,"")} -> 15 | G35: 3220 | H35: {=IF(OR(Table1[[#This Row],[Stock Tickers]]="",Table1[[#This Row],[Action]]="Dividend"), "",IF(Table1[[#This Row],[Action]]="Buy",(SUMIFS($L$2:L35, $C$2:C35,Table1[[#This Row],[Stock Tickers]], $D$2:D35, "Buy") + Table1[[#This Row],[Amount]]) / ((SUMIFS($E$2:E35, $C$2:C35,Table1[[#This Row],[Stock Tickers]], $D$2:D35, "Buy") + Table1[[#This Row],[Lot ]])*100),LOOKUP(2, 1/($C$2:C35=Table1[[#This Row],[Stock Tickers]]), $G$2:G35)))} -> 3221.2365 | J35: =(Table1[[#This Row],[Lot ]]*100)*IF(Table1[[#This Row],[Action]]="Dividend",Table1[[#This Row],[Dividend per Share]],Table1[[#This Row],[Price]]) -> 4830000 | K35: =(exchange_fee+broker_fee)*J35 -> 9336.39 | L35: =SUM(Table1[[#This Row],[Amount]]:Table1[[#This Row],[Total Fee]]) -> 4839336.4 | M35: =IF(OR(Table1[[#This Row],[Action]]="Buy",Table1[[#This Row],[Action]]="Withdraw"),-Table1[[#This Row],[Net Amount]],Table1[[#This Row],[Net Amount]]) -> -4839336.4
A36: 45512 | B36: ="TX"&TEXT(ROW()-1,"0000") -> TX0035 | C36: BBCA | D36: Sell | E36: 5 | F36: {=_xlfn.IFS(Table1[[#This Row],[Action]]="Buy",Table1[[#This Row],[Lot ]],Table1[[#This Row],[Action]]="Sell",-Table1[[#This Row],[Lot ]],Table1[[#This Row],[Action]]="Dividend",0,TRUE,"")} -> -5 | G36: 9350 | H36: {=IF(OR(Table1[[#This Row],[Stock Tickers]]="",Table1[[#This Row],[Action]]="Dividend"), "",IF(Table1[[#This Row],[Action]]="Buy",(SUMIFS($L$2:L36, $C$2:C36,Table1[[#This Row],[Stock Tickers]], $D$2:D36, "Buy") + Table1[[#This Row],[Amount]]) / ((SUMIFS($E$2:E36, $C$2:C36,Table1[[#This Row],[Stock Tickers]], $D$2:D36, "Buy") + Table1[[#This Row],[Lot ]])*100),LOOKUP(2, 1/($C$2:C36=Table1[[#This Row],[Stock Tickers]]), $G$2:G36)))} -> 9350 | J36: =(Table1[[#This Row],[Lot ]]*100)*IF(Table1[[#This Row],[Action]]="Dividend",Table1[[#This Row],[Dividend per Share]],Table1[[#This Row],[Price]]) -> 4675000 | K36: =(exchange_fee+broker_fee)*J36 -> 9036.775 | L36: =SUM(Table1[[#This Row],[Amount]]:Table1[[#This Row],[Total Fee]]) -> 4684036.8 | M36: =IF(OR(Table1[[#This Row],[Action]]="Buy",Table1[[#This Row],[Action]]="Withdraw"),-Table1[[#This Row],[Net Amount]],Table1[[#This Row],[Net Amount]]) -> 4684036.8
A37: 45512 | B37: ="TX"&TEXT(ROW()-1,"0000") -> TX0036 | C37: ADRO | D37: Buy | E37: 16 | F37: {=_xlfn.IFS(Table1[[#This Row],[Action]]="Buy",Table1[[#This Row],[Lot ]],Table1[[#This Row],[Action]]="Sell",-Table1[[#This Row],[Lot ]],Table1[[#This Row],[Action]]="Dividend",0,TRUE,"")} -> 16 | G37: 1990 | H37: {=IF(OR(Table1[[#This Row],[Stock Tickers]]="",Table1[[#This Row],[Action]]="Dividend"), "",IF(Table1[[#This Row],[Action]]="Buy",(SUMIFS($L$2:L37, $C$2:C37,Table1[[#This Row],[Stock Tickers]], $D$2:D37, "Buy") + Table1[[#This Row],[Amount]]) / ((SUMIFS($E$2:E37, $C$2:C37,Table1[[#This Row],[Stock Tickers]], $D$2:D37, "Buy") + Table1[[#This Row],[Lot ]])*100),LOOKUP(2, 1/($C$2:C37=Table1[[#This Row],[Stock Tickers]]), $G$2:G37)))} -> 2419.0343 | J37: =(Table1[[#This Row],[Lot ]]*100)*IF(Table1[[#This Row],[Action]]="Dividend",Table1[[#This Row],[Dividend per Share]],Table1[[#This Row],[Price]]) -> 3184000 | K37: =(exchange_fee+broker_fee)*J37 -> 6154.672 | L37: =SUM(Table1[[#This Row],[Amount]]:Table1[[#This Row],[Total Fee]]) -> 3190154.7 | M37: =IF(OR(Table1[[#This Row],[Action]]="Buy",Table1[[#This Row],[Action]]="Withdraw"),-Table1[[#This Row],[Net Amount]],Table1[[#This Row],[Net Amount]]) -> -3190154.7
A38: 45515 | B38: ="TX"&TEXT(ROW()-1,"0000") -> TX0037 | D38: Deposit | F38: {=_xlfn.IFS(Table1[[#This Row],[Action]]="Buy",Table1[[#This Row],[Lot ]],Table1[[#This Row],[Action]]="Sell",-Table1[[#This Row],[Lot ]],Table1[[#This Row],[Action]]="Dividend",0,TRUE,"")} | H38: {=IF(OR(Table1[[#This Row],[Stock Tickers]]="",Table1[[#This Row],[Action]]="Dividend"), "",IF(Table1[[#This Row],[Action]]="Buy",(SUMIFS($L$2:L38, $C$2:C38,Table1[[#This Row],[Stock Tickers]], $D$2:D38, "Buy") + Table1[[#This Row],[Amount]]) / ((SUMIFS($E$2:E38, $C$2:C38,Table1[[#This Row],[Stock Tickers]], $D$2:D38, "Buy") + Table1[[#This Row],[Lot ]])*100),LOOKUP(2, 1/($C$2:C38=Table1[[#This Row],[Stock Tickers]]), $G$2:G38)))} | J38: 45000000 | L38: =SUM(Table1[[#This Row],[Amount]]:Table1[[#This Row],[Total Fee]]) -> 45000000 | M38: =IF(OR(Table1[[#This Row],[Action]]="Buy",Table1[[#This Row],[Action]]="Withdraw"),-Table1[[#This Row],[Net Amount]],Table1[[#This Row],[Net Amount]]) -> 45000000
A39: 45523 | B39: ="TX"&TEXT(ROW()-1,"0000") -> TX0038 | C39: ICBP | D39: Dividend | E39: 12 | F39: {=_xlfn.IFS(Table1[[#This Row],[Action]]="Buy",Table1[[#This Row],[Lot ]],Table1[[#This Row],[Action]]="Sell",-Table1[[#This Row],[Lot ]],Table1[[#This Row],[Action]]="Dividend",0,TRUE,"")} -> 0 | H39: {=IF(OR(Table1[[#This Row],[Stock Tickers]]="",Table1[[#This Row],[Action]]="Dividend"), "",IF(Table1[[#This Row],[Action]]="Buy",(SUMIFS($L$2:L39, $C$2:C39,Table1[[#This Row],[Stock Tickers]], $D$2:D39, "Buy") + Table1[[#This Row],[Amount]]) / ((SUMIFS($E$2:E39, $C$2:C39,Table1[[#This Row],[Stock Tickers]], $D$2:D39, "Buy") + Table1[[#This Row],[Lot ]])*100),LOOKUP(2, 1/($C$2:C39=Table1[[#This Row],[Stock Tickers]]), $G$2:G39)))} | I39: 200 | J39: =(Table1[[#This Row],[Lot ]]*100)*IF(Table1[[#This Row],[Action]]="Dividend",Table1[[#This Row],[Dividend per Share]],Table1[[#This Row],[Price]]) -> 240000 | L39: =SUM(Table1[[#This Row],[Amount]]:Table1[[#This Row],[Total Fee]]) -> 240000 | M39: =IF(OR(Table1[[#This Row],[Action]]="Buy",Table1[[#This Row],[Action]]="Withdraw"),-Table1[[#This Row],[Net Amount]],Table1[[#This Row],[Net Amount]]) -> 240000
A40: 45525 | B40: ="TX"&TEXT(ROW()-1,"0000") -> TX0039 | C40: BBRI | D40: Buy | E40: 34 | F40: {=_xlfn.IFS(Table1[[#This Row],[Action]]="Buy",Table1[[#This Row],[Lot ]],Table1[[#This Row],[Action]]="Sell",-Table1[[#This Row],[Lot ]],Table1[[#This Row],[Action]]="Dividend",0,TRUE,"")} -> 34 | G40: 3810 | H40: {=IF(OR(Table1[[#This Row],[Stock Tickers]]="",Table1[[#This Row],[Action]]="Dividend"), "",IF(Table1[[#This Row],[Action]]="Buy",(SUMIFS($L$2:L40, $C$2:C40,Table1[[#This Row],[Stock Tickers]], $D$2:D40, "Buy") + Table1[[#This Row],[Amount]]) / ((SUMIFS($E$2:E40, $C$2:C40,Table1[[#This Row],[Stock Tickers]], $D$2:D40, "Buy") + Table1[[#This Row],[Lot ]])*100),LOOKUP(2, 1/($C$2:C40=Table1[[#This Row],[Stock Tickers]]), $G$2:G40)))} -> 3834.3336 | J40: =(Table1[[#This Row],[Lot ]]*100)*IF(Table1[[#This Row],[Action]]="Dividend",Table1[[#This Row],[Dividend per Share]],Table1[[#This Row],[Price]]) -> 12954000 | K40: =(exchange_fee+broker_fee)*J40 -> 25040.082 | L40: =SUM(Table1[[#This Row],[Amount]]:Table1[[#This Row],[Total Fee]]) -> 12979040 | M40: =IF(OR(Table1[[#This Row],[Action]]="Buy",Table1[[#This Row],[Action]]="Withdraw"),-Table1[[#This Row],[Net Amount]],Table1[[#This Row],[Net Amount]]) -> -12979040
A41: 45532 | B41: ="TX"&TEXT(ROW()-1,"0000") -> TX0040 | C41: ASII | D41: Buy | E41: 29 | F41: {=_xlfn.IFS(Table1[[#This Row],[Action]]="Buy",Table1[[#This Row],[Lot ]],Table1[[#This Row],[Action]]="Sell",-Table1[[#This Row],[Lot ]],Table1[[#This Row],[Action]]="Dividend",0,TRUE,"")} -> 29 | G41: 5300 | H41: {=IF(OR(Table1[[#This Row],[Stock Tickers]]="",Table1[[#This Row],[Action]]="Dividend"), "",IF(Table1[[#This Row],[Action]]="Buy",(SUMIFS($L$2:L41, $C$2:C41,Table1[[#This Row],[Stock Tickers]], $D$2:D41, "Buy") + Table1[[#This Row],[Amount]]) / ((SUMIFS($E$2:E41, $C$2:C41,Table1[[#This Row],[Stock Tickers]], $D$2:D41, "Buy") + Table1[[#This Row],[Lot ]])*100),LOOKUP(2, 1/($C$2:C41=Table1[[#This Row],[Stock Tickers]]), $G$2:G41)))} -> 5053.7458 | J41: =(Table1[[#This Row],[Lot ]]*100)*IF(Table1[[#This Row],[Action]]="Dividend",Table1[[#This Row],[Dividend per Share]],Table1[[#This Row],[Price]]) -> 15370000 | K41: =(exchange_fee+broker_fee)*J41 -> 29710.21 | L41: =SUM(Table1[[#This Row],[Amount]]:Table1[[#This Row],[Total Fee]]) -> 15399710 | M41: =IF(OR(Table1[[#This Row],[Action]]="Buy",Table1[[#This Row],[Action]]="Withdraw"),-Table1[[#This Row],[Net Amount]],Table1[[#This Row],[Net Amount]]) -> -15399710
A42: 45536 | B42: ="TX"&TEXT(ROW()-1,"0000") -> TX0041 | C42: GOTO | D42: Buy | E42: 34 | F42: {=_xlfn.IFS(Table1[[#This Row],[Action]]="Buy",Table1[[#This Row],[Lot ]],Table1[[#This Row],[Action]]="Sell",-Table1[[#This Row],[Lot ]],Table1[[#This Row],[Action]]="Dividend",0,TRUE,"")} -> 34 | G42: 112 | H42: {=IF(OR(Table1[[#This Row],[Stock Tickers]]="",Table1[[#This Row],[Action]]="Dividend"), "",IF(Table1[[#This Row],[Action]]="Buy",(SUMIFS($L$2:L42, $C$2:C42,Table1[[#This Row],[Stock Tickers]], $D$2:D42, "Buy") + Table1[[#This Row],[Amount]]) / ((SUMIFS($E$2:E42, $C$2:C42,Table1[[#This Row],[Stock Tickers]], $D$2:D42, "Buy") + Table1[[#This Row],[Lot ]])*100),LOOKUP(2, 1/($C$2:C42=Table1[[#This Row],[Stock Tickers]]), $G$2:G42)))} -> 121.7149 | J42: =(Table1[[#This Row],[Lot ]]*100)*IF(Table1[[#This Row],[Action]]="Dividend",Table1[[#This Row],[Dividend per Share]],Table1[[#This Row],[Price]]) -> 380800 | K42: =(exchange_fee+broker_fee)*J42 -> 736.0864 | L42: =SUM(Table1[[#This Row],[Amount]]:Table1[[#This Row],[Total Fee]]) -> 381536.09 | M42: =IF(OR(Table1[[#This Row],[Action]]="Buy",Table1[[#This Row],[Action]]="Withdraw"),-Table1[[#This Row],[Net Amount]],Table1[[#This Row],[Net Amount]]) -> -381536.09
A43: 45539 | B43: ="TX"&TEXT(ROW()-1,"0000") -> TX0042 | D43: Deposit | F43: {=_xlfn.IFS(Table1[[#This Row],[Action]]="Buy",Table1[[#This Row],[Lot ]],Table1[[#This Row],[Action]]="Sell",-Table1[[#This Row],[Lot ]],Table1[[#This Row],[Action]]="Dividend",0,TRUE,"")} | H43: {=IF(OR(Table1[[#This Row],[Stock Tickers]]="",Table1[[#This Row],[Action]]="Dividend"), "",IF(Table1[[#This Row],[Action]]="Buy",(SUMIFS($L$2:L43, $C$2:C43,Table1[[#This Row],[Stock Tickers]], $D$2:D43, "Buy") + Table1[[#This Row],[Amount]]) / ((SUMIFS($E$2:E43, $C$2:C43,Table1[[#This Row],[Stock Tickers]], $D$2:D43, "Buy") + Table1[[#This Row],[Lot ]])*100),LOOKUP(2, 1/($C$2:C43=Table1[[#This Row],[Stock Tickers]]), $G$2:G43)))} | J43: 80000000 | L43: =SUM(Table1[[#This Row],[Amount]]:Table1[[#This Row],[Total Fee]]) -> 80000000 | M43: =IF(OR(Table1[[#This Row],[Action]]="Buy",Table1[[#This Row],[Action]]="Withdraw"),-Table1[[#This Row],[Net Amount]],Table1[[#This Row],[Net Amount]]) -> 80000000
A44: 45551 | B44: ="TX"&TEXT(ROW()-1,"0000") -> TX0043 | C44: TLKM | D44: Buy | E44: 17 | F44: {=_xlfn.IFS(Table1[[#This Row],[Action]]="Buy",Table1[[#This Row],[Lot ]],Table1[[#This Row],[Action]]="Sell",-Table1[[#This Row],[Lot ]],Table1[[#This Row],[Action]]="Dividend",0,TRUE,"")} -> 17 | G44: 2480 | H44: {=IF(OR(Table1[[#This Row],[Stock Tickers]]="",Table1[[#This Row],[Action]]="Dividend"), "",IF(Table1[[#This Row],[Action]]="Buy",(SUMIFS($L$2:L44, $C$2:C44,Table1[[#This Row],[Stock Tickers]], $D$2:D44, "Buy") + Table1[[#This Row],[Amount]]) / ((SUMIFS($E$2:E44, $C$2:C44,Table1[[#This Row],[Stock Tickers]], $D$2:D44, "Buy") + Table1[[#This Row],[Lot ]])*100),LOOKUP(2, 1/($C$2:C44=Table1[[#This Row],[Stock Tickers]]), $G$2:G44)))} -> 2975.1385 | J44: =(Table1[[#This Row],[Lot ]]*100)*IF(Table1[[#This Row],[Action]]="Dividend",Table1[[#This Row],[Dividend per Share]],Table1[[#This Row],[Price]]) -> 4216000 | K44: =(exchange_fee+broker_fee)*J44 -> 8149.528 | L44: =SUM(Table1[[#This Row],[Amount]]:Table1[[#This Row],[Total Fee]]) -> 4224149.5 | M44: =IF(OR(Table1[[#This Row],[Action]]="Buy",Table1[[#This Row],[Action]]="Withdraw"),-Table1[[#This Row],[Net Amount]],Table1[[#This Row],[Net Amount]]) -> -4224149.5
A45: 45554 | B45: ="TX"&TEXT(ROW()-1,"0000") -> TX0044 | C45: BBCA | D45: Buy | E45: 15 | F45: {=_xlfn.IFS(Table1[[#This Row],[Action]]="Buy",Table1[[#This Row],[Lot ]],Table1[[#This Row],[Action]]="Sell",-Table1[[#This Row],[Lot ]],Table1[[#This Row],[Action]]="Dividend",0,TRUE,"")} -> 15 | G45: 5980 | H45: {=IF(OR(Table1[[#This Row],[Stock Tickers]]="",Table1[[#This Row],[Action]]="Dividend"), "",IF(Table1[[#This Row],[Action]]="Buy",(SUMIFS($L$2:L45, $C$2:C45,Table1[[#This Row],[Stock Tickers]], $D$2:D45, "Buy") + Table1[[#This Row],[Amount]]) / ((SUMIFS($E$2:E45, $C$2:C45,Table1[[#This Row],[Stock Tickers]], $D$2:D45, "Buy") + Table1[[#This Row],[Lot ]])*100),LOOKUP(2, 1/($C$2:C45=Table1[[#This Row],[Stock Tickers]]), $G$2:G45)))} -> 6406.098 | J45: =(Table1[[#This Row],[Lot ]]*100)*IF(Table1[[#This Row],[Action]]="Dividend",Table1[[#This Row],[Dividend per Share]],Table1[[#This Row],[Price]]) -> 8970000 | K45: =(exchange_fee+broker_fee)*J45 -> 17339.01 | L45: =SUM(Table1[[#This Row],[Amount]]:Table1[[#This Row],[Total Fee]]) -> 8987339 | M45: =IF(OR(Table1[[#This Row],[Action]]="Buy",Table1[[#This Row],[Action]]="Withdraw"),-Table1[[#This Row],[Net Amount]],Table1[[#This Row],[Net Amount]]) -> -8987339
A46: 45560 | B46: ="TX"&TEXT(ROW()-1,"0000") -> TX0045 | C46: ADRO | D46: Buy | E46: 20 | F46: {=_xlfn.IFS(Table1[[#This Row],[Action]]="Buy",Table1[[#This Row],[Lot ]],Table1[[#This Row],[Action]]="Sell",-Table1[[#This Row],[Lot ]],Table1[[#This Row],[Action]]="Dividend",0,TRUE,"")} -> 20 | G46: 1650 | H46: {=IF(OR(Table1[[#This Row],[Stock Tickers]]="",Table1[[#This Row],[Action]]="Dividend"), "",IF(Table1[[#This Row],[Action]]="Buy",(SUMIFS($L$2:L46, $C$2:C46,Table1[[#This Row],[Stock Tickers]], $D$2:D46, "Buy") + Table1[[#This Row],[Amount]]) / ((SUMIFS($E$2:E46, $C$2:C46,Table1[[#This Row],[Stock Tickers]], $D$2:D46, "Buy") + Table1[[#This Row],[Lot ]])*100),LOOKUP(2, 1/($C$2:C46=Table1[[#This Row],[Stock Tickers]]), $G$2:G46)))} -> 2234.2821 | J46: =(Table1[[#This Row],[Lot ]]*100)*IF(Table1[[#This Row],[Action]]="Dividend",Table1[[#This Row],[Dividend per Share]],Table1[[#This Row],[Price]]) -> 3300000 | K46: =(exchange_fee+broker_fee)*J46 -> 6378.9 | L46: =SUM(Table1[[#This Row],[Amount]]:Table1[[#This Row],[Total Fee]]) -> 3306378.9 | M46: =IF(OR(Table1[[#This Row],[Action]]="Buy",Table1[[#This Row],[Action]]="Withdraw"),-Table1[[#This Row],[Net Amount]],Table1[[#This Row],[Net Amount]]) -> -3306378.9
A47: 45563 | B47: ="TX"&TEXT(ROW()-1,"0000") -> TX0046 | C47: BBRI | D47: Buy | E47: 38 | F47: {=_xlfn.IFS(Table1[[#This Row],[Action]]="Buy",Table1[[#This Row],[Lot ]],Table1[[#This Row],[Action]]="Sell",-Table1[[#This Row],[Lot ]],Table1[[#This Row],[Action]]="Dividend",0,TRUE,"")} -> 38 | G47: 3010 | H47: {=IF(OR(Table1[[#This Row],[Stock Tickers]]="",Table1[[#This Row],[Action]]="Dividend"), "",IF(Table1[[#This Row],[Action]]="Buy",(SUMIFS($L$2:L47, $C$2:C47,Table1[[#This Row],[Stock Tickers]], $D$2:D47, "Buy") + Table1[[#This Row],[Amount]]) / ((SUMIFS($E$2:E47, $C$2:C47,Table1[[#This Row],[Stock Tickers]], $D$2:D47, "Buy") + Table1[[#This Row],[Lot ]])*100),LOOKUP(2, 1/($C$2:C47=Table1[[#This Row],[Stock Tickers]]), $G$2:G47)))} -> 3463.2438 | J47: =(Table1[[#This Row],[Lot ]]*100)*IF(Table1[[#This Row],[Action]]="Dividend",Table1[[#This Row],[Dividend per Share]],Table1[[#This Row],[Price]]) -> 11438000 | K47: =(exchange_fee+broker_fee)*J47 -> 22109.654 | L47: =SUM(Table1[[#This Row],[Amount]]:Table1[[#This Row],[Total Fee]]) -> 11460110 | M47: =IF(OR(Table1[[#This Row],[Action]]="Buy",Table1[[#This Row],[Action]]="Withdraw"),-Table1[[#This Row],[Net Amount]],Table1[[#This Row],[Net Amount]]) -> -11460110
A48: 45575 | B48: ="TX"&TEXT(ROW()-1,"0000") -> TX0047 | C48: BBRI | D48: Dividend | E48: 142 | F48: {=_xlfn.IFS(Table1[[#This Row],[Action]]="Buy",Table1[[#This Row],[Lot ]],Table1[[#This Row],[Action]]="Sell",-Table1[[#This Row],[Lot ]],Table1[[#This Row],[Action]]="Dividend",0,TRUE,"")} -> 0 | H48: {=IF(OR(Table1[[#This Row],[Stock Tickers]]="",Table1[[#This Row],[Action]]="Dividend"), "",IF(Table1[[#This Row],[Action]]="Buy",(SUMIFS($L$2:L48, $C$2:C48,Table1[[#This Row],[Stock Tickers]], $D$2:D48, "Buy") + Table1[[#This Row],[Amount]]) / ((SUMIFS($E$2:E48, $C$2:C48,Table1[[#This Row],[Stock Tickers]], $D$2:D48, "Buy") + Table1[[#This Row],[Lot ]])*100),LOOKUP(2, 1/($C$2:C48=Table1[[#This Row],[Stock Tickers]]), $G$2:G48)))} | I48: 370 | J48: =(Table1[[#This Row],[Lot ]]*100)*IF(Table1[[#This Row],[Action]]="Dividend",Table1[[#This Row],[Dividend per Share]],Table1[[#This Row],[Price]]) -> 5254000 | L48: =SUM(Table1[[#This Row],[Amount]]:Table1[[#This Row],[Total Fee]]) -> 5254000 | M48: =IF(OR(Table1[[#This Row],[Action]]="Buy",Table1[[#This Row],[Action]]="Withdraw"),-Table1[[#This Row],[Net Amount]],Table1[[#This Row],[Net Amount]]) -> 5254000
A49: 45578 | B49: ="TX"&TEXT(ROW()-1,"0000") -> TX0048 | C49: ICBP | D49: Buy | E49: 8 | F49: {=_xlfn.IFS(Table1[[#This Row],[Action]]="Buy",Table1[[#This Row],[Lot ]],Table1[[#This Row],[Action]]="Sell",-Table1[[#This Row],[Lot ]],Table1[[#This Row],[Action]]="Dividend",0,TRUE,"")} -> 8 | G49: 1100 | H49: {=IF(OR(Table1[[#This Row],[Stock Tickers]]="",Table1[[#This Row],[Action]]="Dividend"), "",IF(Table1[[#This Row],[Action]]="Buy",(SUMIFS($L$2:L49, $C$2:C49,Table1[[#This Row],[Stock Tickers]], $D$2:D49, "Buy") + Table1[[#This Row],[Amount]]) / ((SUMIFS($E$2:E49, $C$2:C49,Table1[[#This Row],[Stock Tickers]], $D$2:D49, "Buy") + Table1[[#This Row],[Lot ]])*100),LOOKUP(2, 1/($C$2:C49=Table1[[#This Row],[Stock Tickers]]), $G$2:G49)))} -> 1100.4453 | J49: =(Table1[[#This Row],[Lot ]]*100)*IF(Table1[[#This Row],[Action]]="Dividend",Table1[[#This Row],[Dividend per Share]],Table1[[#This Row],[Price]]) -> 880000 | K49: =(exchange_fee+broker_fee)*J49 -> 1701.04 | L49: =SUM(Table1[[#This Row],[Amount]]:Table1[[#This Row],[Total Fee]]) -> 881701.04 | M49: =IF(OR(Table1[[#This Row],[Action]]="Buy",Table1[[#This Row],[Action]]="Withdraw"),-Table1[[#This Row],[Net Amount]],Table1[[#This Row],[Net Amount]]) -> -881701.04
A50: 45583 | B50: ="TX"&TEXT(ROW()-1,"0000") -> TX0049 | C50: GOTO | D50: Buy | E50: 22 | F50: {=_xlfn.IFS(Table1[[#This Row],[Action]]="Buy",Table1[[#This Row],[Lot ]],Table1[[#This Row],[Action]]="Sell",-Table1[[#This Row],[Lot ]],Table1[[#This Row],[Action]]="Dividend",0,TRUE,"")} -> 22 | G50: 89 | H50: {=IF(OR(Table1[[#This Row],[Stock Tickers]]="",Table1[[#This Row],[Action]]="Dividend"), "",IF(Table1[[#This Row],[Action]]="Buy",(SUMIFS($L$2:L50, $C$2:C50,Table1[[#This Row],[Stock Tickers]], $D$2:D50, "Buy") + Table1[[#This Row],[Amount]]) / ((SUMIFS($E$2:E50, $C$2:C50,Table1[[#This Row],[Stock Tickers]], $D$2:D50, "Buy") + Table1[[#This Row],[Lot ]])*100),LOOKUP(2, 1/($C$2:C50=Table1[[#This Row],[Stock Tickers]]), $G$2:G50)))} -> 115.50499 | J50: =(Table1[[#This Row],[Lot ]]*100)*IF(Table1[[#This Row],[Action]]="Dividend",Table1[[#This Row],[Dividend per Share]],Table1[[#This Row],[Price]]) -> 195800 | K50: =(exchange_fee+broker_fee)*J50 -> 378.4814 | L50: =SUM(Table1[[#This Row],[Amount]]:Table1[[#This Row],[Total Fee]]) -> 196178.48 | M50: =IF(OR(Table1[[#This Row],[Action]]="Buy",Table1[[#This Row],[Action]]="Withdraw"),-Table1[[#This Row],[Net Amount]],Table1[[#This Row],[Net Amount]]) -> -196178.48
A51: 45585 | B51: ="TX"&TEXT(ROW()-1,"0000") -> TX0050 | C51: ASII | D51: Sell | E51: 6 | F51: {=_xlfn.IFS(Table1[[#This Row],[Action]]="Buy",Table1[[#This Row],[Lot ]],Table1[[#This Row],[Action]]="Sell",-Table1[[#This Row],[Lot ]],Table1[[#This Row],[Action]]="Dividend",0,TRUE,"")} -> -6 | G51: 6120 | H51: {=IF(OR(Table1[[#This Row],[Stock Tickers]]="",Table1[[#This Row],[Action]]="Dividend"), "",IF(Table1[[#This Row],[Action]]="Buy",(SUMIFS($L$2:L51, $C$2:C51,Table1[[#This Row],[Stock Tickers]], $D$2:D51, "Buy") + Table1[[#This Row],[Amount]]) / ((SUMIFS($E$2:E51, $C$2:C51,Table1[[#This Row],[Stock Tickers]], $D$2:D51, "Buy") + Table1[[#This Row],[Lot ]])*100),LOOKUP(2, 1/($C$2:C51=Table1[[#This Row],[Stock Tickers]]), $G$2:G51)))} -> 6120 | J51: =(Table1[[#This Row],[Lot ]]*100)*IF(Table1[[#This Row],[Action]]="Dividend",Table1[[#This Row],[Dividend per Share]],Table1[[#This Row],[Price]]) -> 3672000 | K51: =(exchange_fee+broker_fee)*J51 -> 7097.976 | L51: =SUM(Table1[[#This Row],[Amount]]:Table1[[#This Row],[Total Fee]]) -> 3679098 | M51: =IF(OR(Table1[[#This Row],[Action]]="Buy",Table1[[#This Row],[Action]]="Withdraw"),-Table1[[#This Row],[Net Amount]],Table1[[#This Row],[Net Amount]]) -> 3679098
A52: 45590 | B52: ="TX"&TEXT(ROW()-1,"0000") -> TX0051 | D52: Withdraw | F52: {=_xlfn.IFS(Table1[[#This Row],[Action]]="Buy",Table1[[#This Row],[Lot ]],Table1[[#This Row],[Action]]="Sell",-Table1[[#This Row],[Lot ]],Table1[[#This Row],[Action]]="Dividend",0,TRUE,"")} | H52: {=IF(OR(Table1[[#This Row],[Stock Tickers]]="",Table1[[#This Row],[Action]]="Dividend"), "",IF(Table1[[#This Row],[Action]]="Buy",(SUMIFS($L$2:L52, $C$2:C52,Table1[[#This Row],[Stock Tickers]], $D$2:D52, "Buy") + Table1[[#This Row],[Amount]]) / ((SUMIFS($E$2:E52, $C$2:C52,Table1[[#This Row],[Stock Tickers]], $D$2:D52, "Buy") + Table1[[#This Row],[Lot ]])*100),LOOKUP(2, 1/($C$2:C52=Table1[[#This Row],[Stock Tickers]]), $G$2:G52)))} | J52: 5000000 | L52: =SUM(Table1[[#This Row],[Amount]]:Table1[[#This Row],[Total Fee]]) -> 5000000 | M52: =IF(OR(Table1[[#This Row],[Action]]="Buy",Table1[[#This Row],[Action]]="Withdraw"),-Table1[[#This Row],[Net Amount]],Table1[[#This Row],[Net Amount]]) -> -5000000
A53: 45600 | B53: ="TX"&TEXT(ROW()-1,"0000") -> TX0052 | C53: TLKM | D53: Buy | E53: 9 | F53: {=_xlfn.IFS(Table1[[#This Row],[Action]]="Buy",Table1[[#This Row],[Lot ]],Table1[[#This Row],[Action]]="Sell",-Table1[[#This Row],[Lot ]],Table1[[#This Row],[Action]]="Dividend",0,TRUE,"")} -> 9 | G53: 2760 | H53: {=IF(OR(Table1[[#This Row],[Stock Tickers]]="",Table1[[#This Row],[Action]]="Dividend"), "",IF(Table1[[#This Row],[Action]]="Buy",(SUMIFS($L$2:L53, $C$2:C53,Table1[[#This Row],[Stock Tickers]], $D$2:D53, "Buy") + Table1[[#This Row],[Amount]]) / ((SUMIFS($E$2:E53, $C$2:C53,Table1[[#This Row],[Stock Tickers]], $D$2:D53, "Buy") + Table1[[#This Row],[Lot ]])*100),LOOKUP(2, 1/($C$2:C53=Table1[[#This Row],[Stock Tickers]]), $G$2:G53)))} -> 3019.7295 | J53: =(Table1[[#This Row],[Lot ]]*100)*IF(Table1[[#This Row],[Action]]="Dividend",Table1[[#This Row],[Dividend per Share]],Table1[[#This Row],[Price]]) -> 2484000 | K53: =(exchange_fee+broker_fee)*J53 -> 4801.572 | L53: =SUM(Table1[[#This Row],[Amount]]:Table1[[#This Row],[Total Fee]]) -> 2488801.6 | M53: =IF(OR(Table1[[#This Row],[Action]]="Buy",Table1[[#This Row],[Action]]="Withdraw"),-Table1[[#This Row],[Net Amount]],Table1[[#This Row],[Net Amount]]) -> -2488801.6
A54: 45601 | B54: ="TX"&TEXT(ROW()-1,"0000") -> TX0053 | C54: BBCA | D54: Buy | E54: 18 | F54: {=_xlfn.IFS(Table1[[#This Row],[Action]]="Buy",Table1[[#This Row],[Lot ]],Table1[[#This Row],[Action]]="Sell",-Table1[[#This Row],[Lot ]],Table1[[#This Row],[Action]]="Dividend",0,TRUE,"")} -> 18 | G54: 7110 | H54: {=IF(OR(Table1[[#This Row],[Stock Tickers]]="",Table1[[#This Row],[Action]]="Dividend"), "",IF(Table1[[#This Row],[Action]]="Buy",(SUMIFS($L$2:L54, $C$2:C54,Table1[[#This Row],[Stock Tickers]], $D$2:D54, "Buy") + Table1[[#This Row],[Amount]]) / ((SUMIFS($E$2:E54, $C$2:C54,Table1[[#This Row],[Stock Tickers]], $D$2:D54, "Buy") + Table1[[#This Row],[Lot ]])*100),LOOKUP(2, 1/($C$2:C54=Table1[[#This Row],[Stock Tickers]]), $G$2:G54)))} -> 6856.5111 | J54: =(Table1[[#This Row],[Lot ]]*100)*IF(Table1[[#This Row],[Action]]="Dividend",Table1[[#This Row],[Dividend per Share]],Table1[[#This Row],[Price]]) -> 12798000 | K54: =(exchange_fee+broker_fee)*J54 -> 24738.534 | L54: =SUM(Table1[[#This Row],[Amount]]:Table1[[#This Row],[Total Fee]]) -> 12822739 | M54: =IF(OR(Table1[[#This Row],[Action]]="Buy",Table1[[#This Row],[Action]]="Withdraw"),-Table1[[#This Row],[Net Amount]],Table1[[#This Row],[Net Amount]]) -> -12822739
A55: 45607 | B55: ="TX"&TEXT(ROW()-1,"0000") -> TX0054 | C55: ADRO | D55: Dividend | E55: 190 | F55: {=_xlfn.IFS(Table1[[#This Row],[Action]]="Buy",Table1[[#This Row],[Lot ]],Table1[[#This Row],[Action]]="Sell",-Table1[[#This Row],[Lot ]],Table1[[#This Row],[Action]]="Dividend",0,TRUE,"")} -> 0 | H55: {=IF(OR(Table1[[#This Row],[Stock Tickers]]="",Table1[[#This Row],[Action]]="Dividend"), "",IF(Table1[[#This Row],[Action]]="Buy",(SUMIFS($L$2:L55, $C$2:C55,Table1[[#This Row],[Stock Tickers]], $D$2:D55, "Buy") + Table1[[#This Row],[Amount]]) / ((SUMIFS($E$2:E55, $C$2:C55,Table1[[#This Row],[Stock Tickers]], $D$2:D55, "Buy") + Table1[[#This Row],[Lot ]])*100),LOOKUP(2, 1/($C$2:C55=Table1[[#This Row],[Stock Tickers]]), $G$2:G55)))} | I55: 1358 | J55: =(Table1[[#This Row],[Lot ]]*100)*IF(Table1[[#This Row],[Action]]="Dividend",Table1[[#This Row],[Dividend per Share]],Table1[[#This Row],[Price]]) -> 25802000 | L55: =SUM(Table1[[#This Row],[Amount]]:Table1[[#This Row],[Total Fee]]) -> 25802000 | M55: =IF(OR(Table1[[#This Row],[Action]]="Buy",Table1[[#This Row],[Action]]="Withdraw"),-Table1[[#This Row],[Net Amount]],Table1[[#This Row],[Net Amount]]) -> 25802000
A56: 45454 | B56: ="TX"&TEXT(ROW()-1,"0000") -> TX0055 | C56: BREN | D56: Buy | E56: 10 | F56: {=_xlfn.IFS(Table1[[#This Row],[Action]]="Buy",Table1[[#This Row],[Lot ]],Table1[[#This Row],[Action]]="Sell",-Table1[[#This Row],[Lot ]],Table1[[#This Row],[Action]]="Dividend",0,TRUE,"")} -> 10 | G56: 6050 | H56: {=IF(OR(Table1[[#This Row],[Stock Tickers]]="",Table1[[#This Row],[Action]]="Dividend"), "",IF(Table1[[#This Row],[Action]]="Buy",(SUMIFS($L$2:L56, $C$2:C56,Table1[[#This Row],[Stock Tickers]], $D$2:D56, "Buy") + Table1[[#This Row],[Amount]]) / ((SUMIFS($E$2:E56, $C$2:C56,Table1[[#This Row],[Stock Tickers]], $D$2:D56, "Buy") + Table1[[#This Row],[Lot ]])*100),LOOKUP(2, 1/($C$2:C56=Table1[[#This Row],[Stock Tickers]]), $G$2:G56)))} -> 6055.8473 | J56: =(Table1[[#This Row],[Lot ]]*100)*IF(Table1[[#This Row],[Action]]="Dividend",Table1[[#This Row],[Dividend per Share]],Table1[[#This Row],[Price]]) -> 6050000 | K56: =(exchange_fee+broker_fee)*J56 -> 11694.65 | L56: =SUM(Table1[[#This Row],[Amount]]:Table1[[#This Row],[Total Fee]]) -> 6061694.7 | M56: =IF(OR(Table1[[#This Row],[Action]]="Buy",Table1[[#This Row],[Action]]="Withdraw"),-Table1[[#This Row],[Net Amount]],Table1[[#This Row],[Net Amount]]) -> -6061694.7
A57: 45610 | B57: ="TX"&TEXT(ROW()-1,"0000") -> TX0056 | C57: BBRI | D57: Buy | E57: 13 | F57: {=_xlfn.IFS(Table1[[#This Row],[Action]]="Buy",Table1[[#This Row],[Lot ]],Table1[[#This Row],[Action]]="Sell",-Table1[[#This Row],[Lot ]],Table1[[#This Row],[Action]]="Dividend",0,TRUE,"")} -> 13 | G57: 3670 | H57: {=IF(OR(Table1[[#This Row],[Stock Tickers]]="",Table1[[#This Row],[Action]]="Dividend"), "",IF(Table1[[#This Row],[Action]]="Buy",(SUMIFS($L$2:L57, $C$2:C57,Table1[[#This Row],[Stock Tickers]], $D$2:D57, "Buy") + Table1[[#This Row],[Amount]]) / ((SUMIFS($E$2:E57, $C$2:C57,Table1[[#This Row],[Stock Tickers]], $D$2:D57, "Buy") + Table1[[#This Row],[Lot ]])*100),LOOKUP(2, 1/($C$2:C57=Table1[[#This Row],[Stock Tickers]]), $G$2:G57)))} -> 3610.5889 | J57: =(Table1[[#This Row],[Lot ]]*100)*IF(Table1[[#This Row],[Action]]="Dividend",Table1[[#This Row],[Dividend per Share]],Table1[[#This Row],[Price]]) -> 4771000 | K57: =(exchange_fee+broker_fee)*J57 -> 9222.343 | L57: =SUM(Table1[[#This Row],[Amount]]:Table1[[#This Row],[Total Fee]]) -> 4780222.3 | M57: =IF(OR(Table1[[#This Row],[Action]]="Buy",Table1[[#This Row],[Action]]="Withdraw"),-Table1[[#This Row],[Net Amount]],Table1[[#This Row],[Net Amount]]) -> -4780222.3
A58: 45619 | B58: ="TX"&TEXT(ROW()-1,"0000") -> TX0057 | C58: GOTO | D58: Buy | E58: 35 | F58: {=_xlfn.IFS(Table1[[#This Row],[Action]]="Buy",Table1[[#This Row],[Lot ]],Table1[[#This Row],[Action]]="Sell",-Table1[[#This Row],[Lot ]],Table1[[#This Row],[Action]]="Dividend",0,TRUE,"")} -> 35 | G58: 76 | H58: {=IF(OR(Table1[[#This Row],[Stock Tickers]]="",Table1[[#This Row],[Action]]="Dividend"), "",IF(Table1[[#This Row],[Action]]="Buy",(SUMIFS($L$2:L58, $C$2:C58,Table1[[#This Row],[Stock Tickers]], $D$2:D58, "Buy") + Table1[[#This Row],[Amount]]) / ((SUMIFS($E$2:E58, $C$2:C58,Table1[[#This Row],[Stock Tickers]], $D$2:D58, "Buy") + Table1[[#This Row],[Lot ]])*100),LOOKUP(2, 1/($C$2:C58=Table1[[#This Row],[Stock Tickers]]), $G$2:G58)))} -> 105.87181 | J58: =(Table1[[#This Row],[Lot ]]*100)*IF(Table1[[#This Row],[Action]]="Dividend",Table1[[#This Row],[Dividend per Share]],Table1[[#This Row],[Price]]) -> 266000 | K58: =(exchange_fee+broker_fee)*J58 -> 514.178 | L58: =SUM(Table1[[#This Row],[Amount]]:Table1[[#This Row],[Total Fee]]) -> 266514.18 | M58: =IF(OR(Table1[[#This Row],[Action]]="Buy",Table1[[#This Row],[Action]]="Withdraw"),-Table1[[#This Row],[Net Amount]],Table1[[#This Row],[Net Amount]]) -> -266514.18
A59: 45623 | B59: ="TX"&TEXT(ROW()-1,"0000") -> TX0058 | C59: ASII | D59: Buy | E59: 11 | F59: {=_xlfn.IFS(Table1[[#This Row],[Action]]="Buy",Table1[[#This Row],[Lot ]],Table1[[#This Row],[Action]]="Sell",-Table1[[#This Row],[Lot ]],Table1[[#This Row],[Action]]="Dividend",0,TRUE,"")} -> 11 | G59: 5680 | H59: {=IF(OR(Table1[[#This Row],[Stock Tickers]]="",Table1[[#This Row],[Action]]="Dividend"), "",IF(Table1[[#This Row],[Action]]="Buy",(SUMIFS($L$2:L59, $C$2:C59,Table1[[#This Row],[Stock Tickers]], $D$2:D59, "Buy") + Table1[[#This Row],[Amount]]) / ((SUMIFS($E$2:E59, $C$2:C59,Table1[[#This Row],[Stock Tickers]], $D$2:D59, "Buy") + Table1[[#This Row],[Lot ]])*100),LOOKUP(2, 1/($C$2:C59=Table1[[#This Row],[Stock Tickers]]), $G$2:G59)))} -> 5110.5273 | J59: =(Table1[[#This Row],[Lot ]]*100)*IF(Table1[[#This Row],[Action]]="Dividend",Table1[[#This Row],[Dividend per Share]],Table1[[#This Row],[Price]]) -> 6248000 | K59: =(exchange_fee+broker_fee)*J59 -> 12077.384 | L59: =SUM(Table1[[#This Row],[Amount]]:Table1[[#This Row],[Total Fee]]) -> 6260077.4 | M59: =IF(OR(Table1[[#This Row],[Action]]="Buy",Table1[[#This Row],[Action]]="Withdraw"),-Table1[[#This Row],[Net Amount]],Table1[[#This Row],[Net Amount]]) -> -6260077.4
A60: 45627 | B60: ="TX"&TEXT(ROW()-1,"0000") -> TX0059 | C60: TLKM | D60: Sell | E60: 4 | F60: {=_xlfn.IFS(Table1[[#This Row],[Action]]="Buy",Table1[[#This Row],[Lot ]],Table1[[#This Row],[Action]]="Sell",-Table1[[#This Row],[Lot ]],Table1[[#This Row],[Action]]="Dividend",0,TRUE,"")} -> -4 | G60: 4190 | H60: {=IF(OR(Table1[[#This Row],[Stock Tickers]]="",Table1[[#This Row],[Action]]="Dividend"), "",IF(Table1[[#This Row],[Action]]="Buy",(SUMIFS($L$2:L60, $C$2:C60,Table1[[#This Row],[Stock Tickers]], $D$2:D60, "Buy") + Table1[[#This Row],[Amount]]) / ((SUMIFS($E$2:E60, $C$2:C60,Table1[[#This Row],[Stock Tickers]], $D$2:D60, "Buy") + Table1[[#This Row],[Lot ]])*100),LOOKUP(2, 1/($C$2:C60=Table1[[#This Row],[Stock Tickers]]), $G$2:G60)))} -> 4190 | J60: =(Table1[[#This Row],[Lot ]]*100)*IF(Table1[[#This Row],[Action]]="Dividend",Table1[[#This Row],[Dividend per Share]],Table1[[#This Row],[Price]]) -> 1676000 | K60: =(exchange_fee+broker_fee)*J60 -> 3239.708 | L60: =SUM(Table1[[#This Row],[Amount]]:Table1[[#This Row],[Total Fee]]) -> 1679239.7 | M60: =IF(OR(Table1[[#This Row],[Action]]="Buy",Table1[[#This Row],[Action]]="Withdraw"),-Table1[[#This Row],[Net Amount]],Table1[[#This Row],[Net Amount]]) -> 1679239.7
A61: 45630 | B61: ="TX"&TEXT(ROW()-1,"0000") -> TX0060 | D61: Deposit | F61: {=_xlfn.IFS(Table1[[#This Row],[Action]]="Buy",Table1[[#This Row],[Lot ]],Table1[[#This Row],[Action]]="Sell",-Table1[[#This Row],[Lot ]],Table1[[#This Row],[Action]]="Dividend",0,TRUE,"")} | H61: {=IF(OR(Table1[[#This Row],[Stock Tickers]]="",Table1[[#This Row],[Action]]="Dividend"), "",IF(Table1[[#This Row],[Action]]="Buy",(SUMIFS($L$2:L61, $C$2:C61,Table1[[#This Row],[Stock Tickers]], $D$2:D61, "Buy") + Table1[[#This Row],[Amount]]) / ((SUMIFS($E$2:E61, $C$2:C61,Table1[[#This Row],[Stock Tickers]], $D$2:D61, "Buy") + Table1[[#This Row],[Lot ]])*100),LOOKUP(2, 1/($C$2:C61=Table1[[#This Row],[Stock Tickers]]), $G$2:G61)))} | J61: 60000000 | L61: =SUM(Table1[[#This Row],[Amount]]:Table1[[#This Row],[Total Fee]]) -> 60000000 | M61: =IF(OR(Table1[[#This Row],[Action]]="Buy",Table1[[#This Row],[Action]]="Withdraw"),-Table1[[#This Row],[Net Amount]],Table1[[#This Row],[Net Amount]]) -> 60000000
A62: 45638 | B62: ="TX"&TEXT(ROW()-1,"0000") -> TX0061 | C62: ICBP | D62: Buy | E62: 36 | F62: {=_xlfn.IFS(Table1[[#This Row],[Action]]="Buy",Table1[[#This Row],[Lot ]],Table1[[#This Row],[Action]]="Sell",-Table1[[#This Row],[Lot ]],Table1[[#This Row],[Action]]="Dividend",0,TRUE,"")} -> 36 | G62: 9840 | H62: {=IF(OR(Table1[[#This Row],[Stock Tickers]]="",Table1[[#This Row],[Action]]="Dividend"), "",IF(Table1[[#This Row],[Action]]="Buy",(SUMIFS($L$2:L62, $C$2:C62,Table1[[#This Row],[Stock Tickers]], $D$2:D62, "Buy") + Table1[[#This Row],[Amount]]) / ((SUMIFS($E$2:E62, $C$2:C62,Table1[[#This Row],[Stock Tickers]], $D$2:D62, "Buy") + Table1[[#This Row],[Lot ]])*100),LOOKUP(2, 1/($C$2:C62=Table1[[#This Row],[Stock Tickers]]), $G$2:G62)))} -> 7947.5784 | J62: =(Table1[[#This Row],[Lot ]]*100)*IF(Table1[[#This Row],[Action]]="Dividend",Table1[[#This Row],[Dividend per Share]],Table1[[#This Row],[Price]]) -> 35424000 | K62: =(exchange_fee+broker_fee)*J62 -> 68474.592 | L62: =SUM(Table1[[#This Row],[Amount]]:Table1[[#This Row],[Total Fee]]) -> 35492475 | M62: =IF(OR(Table1[[#This Row],[Action]]="Buy",Table1[[#This Row],[Action]]="Withdraw"),-Table1[[#This Row],[Net Amount]],Table1[[#This Row],[Net Amount]]) -> -35492475
A63: 45643 | B63: ="TX"&TEXT(ROW()-1,"0000") -> TX0062 | C63: BBCA | D63: Dividend | E63: 58 | F63: {=_xlfn.IFS(Table1[[#This Row],[Action]]="Buy",Table1[[#This Row],[Lot ]],Table1[[#This Row],[Action]]="Sell",-Table1[[#This Row],[Lot ]],Table1[[#This Row],[Action]]="Dividend",0,TRUE,"")} -> 0 | H63: {=IF(OR(Table1[[#This Row],[Stock Tickers]]="",Table1[[#This Row],[Action]]="Dividend"), "",IF(Table1[[#This Row],[Action]]="Buy",(SUMIFS($L$2:L63, $C$2:C63,Table1[[#This Row],[Stock Tickers]], $D$2:D63, "Buy") + Table1[[#This Row],[Amount]]) / ((SUMIFS($E$2:E63, $C$2:C63,Table1[[#This Row],[Stock Tickers]], $D$2:D63, "Buy") + Table1[[#This Row],[Lot ]])*100),LOOKUP(2, 1/($C$2:C63=Table1[[#This Row],[Stock Tickers]]), $G$2:G63)))} | I63: 227 | J63: =(Table1[[#This Row],[Lot ]]*100)*IF(Table1[[#This Row],[Action]]="Dividend",Table1[[#This Row],[Dividend per Share]],Table1[[#This Row],[Price]]) -> 1316600 | L63: =SUM(Table1[[#This Row],[Amount]]:Table1[[#This Row],[Total Fee]]) -> 1316600 | M63: =IF(OR(Table1[[#This Row],[Action]]="Buy",Table1[[#This Row],[Action]]="Withdraw"),-Table1[[#This Row],[Net Amount]],Table1[[#This Row],[Net Amount]]) -> 1316600
A64: 45646 | B64: ="TX"&TEXT(ROW()-1,"0000") -> TX0063 | C64: ADRO | D64: Buy | E64: 37 | F64: {=_xlfn.IFS(Table1[[#This Row],[Action]]="Buy",Table1[[#This Row],[Lot ]],Table1[[#This Row],[Action]]="Sell",-Table1[[#This Row],[Lot ]],Table1[[#This Row],[Action]]="Dividend",0,TRUE,"")} -> 37 | G64: 2120 | H64: {=IF(OR(Table1[[#This Row],[Stock Tickers]]="",Table1[[#This Row],[Action]]="Dividend"), "",IF(Table1[[#This Row],[Action]]="Buy",(SUMIFS($L$2:L64, $C$2:C64,Table1[[#This Row],[Stock Tickers]], $D$2:D64, "Buy") + Table1[[#This Row],[Amount]]) / ((SUMIFS($E$2:E64, $C$2:C64,Table1[[#This Row],[Stock Tickers]], $D$2:D64, "Buy") + Table1[[#This Row],[Lot ]])*100),LOOKUP(2, 1/($C$2:C64=Table1[[#This Row],[Stock Tickers]]), $G$2:G64)))} -> 2252.7542 | J64: =(Table1[[#This Row],[Lot ]]*100)*IF(Table1[[#This Row],[Action]]="Dividend",Table1[[#This Row],[Dividend per Share]],Table1[[#This Row],[Price]]) -> 7844000 | K64: =(exchange_fee+broker_fee)*J64 -> 15162.452 | L64: =SUM(Table1[[#This Row],[Amount]]:Table1[[#This Row],[Total Fee]]) -> 7859162.5 | M64: =IF(OR(Table1[[#This Row],[Action]]="Buy",Table1[[#This Row],[Action]]="Withdraw"),-Table1[[#This Row],[Net Amount]],Table1[[#This Row],[Net Amount]]) -> -7859162.5
A65: 45663 | B65: ="TX"&TEXT(ROW()-1,"0000") -> TX0064 | C65: BREN | D65: Sell | E65: 10 | F65: {=_xlfn.IFS(Table1[[#This Row],[Action]]="Buy",Table1[[#This Row],[Lot ]],Table1[[#This Row],[Action]]="Sell",-Table1[[#This Row],[Lot ]],Table1[[#This Row],[Action]]="Dividend",0,TRUE,"")} -> -10 | G65: 9475 | H65: {=IF(OR(Table1[[#This Row],[Stock Tickers]]="",Table1[[#This Row],[Action]]="Dividend"), "",IF(Table1[[#This Row],[Action]]="Buy",(SUMIFS($L$2:L65, $C$2:C65,Table1[[#This Row],[Stock Tickers]], $D$2:D65, "Buy") + Table1[[#This Row],[Amount]]) / ((SUMIFS($E$2:E65, $C$2:C65,Table1[[#This Row],[Stock Tickers]], $D$2:D65, "Buy") + Table1[[#This Row],[Lot ]])*100),LOOKUP(2, 1/($C$2:C65=Table1[[#This Row],[Stock Tickers]]), $G$2:G65)))} -> 9475 | J65: =(Table1[[#This Row],[Lot ]]*100)*IF(Table1[[#This Row],[Action]]="Dividend",Table1[[#This Row],[Dividend per Share]],Table1[[#This Row],[Price]]) -> 9475000 | K65: =(exchange_fee+broker_fee)*J65 -> 18315.175 | L65: =SUM(Table1[[#This Row],[Amount]]:Table1[[#This Row],[Total Fee]]) -> 9493315.2 | M65: =IF(OR(Table1[[#This Row],[Action]]="Buy",Table1[[#This Row],[Action]]="Withdraw"),-Table1[[#This Row],[Net Amount]],Table1[[#This Row],[Net Amount]]) -> 9493315.2
A66: 45674 | B66: ="TX"&TEXT(ROW()-1,"0000") -> TX0065 | C66: BBRI | D66: Buy | E66: 19 | F66: {=_xlfn.IFS(Table1[[#This Row],[Action]]="Buy",Table1[[#This Row],[Lot ]],Table1[[#This Row],[Action]]="Sell",-Table1[[#This Row],[Lot ]],Table1[[#This Row],[Action]]="Dividend",0,TRUE,"")} -> 19 | G66: 4190 | H66: {=IF(OR(Table1[[#This Row],[Stock Tickers]]="",Table1[[#This Row],[Action]]="Dividend"), "",IF(Table1[[#This Row],[Action]]="Buy",(SUMIFS($L$2:L66, $C$2:C66,Table1[[#This Row],[Stock Tickers]], $D$2:D66, "Buy") + Table1[[#This Row],[Amount]]) / ((SUMIFS($E$2:E66, $C$2:C66,Table1[[#This Row],[Stock Tickers]], $D$2:D66, "Buy") + Table1[[#This Row],[Lot ]])*100),LOOKUP(2, 1/($C$2:C66=Table1[[#This Row],[Stock Tickers]]), $G$2:G66)))} -> 3730.1373 | J66: =(Table1[[#This Row],[Lot ]]*100)*IF(Table1[[#This Row],[Action]]="Dividend",Table1[[#This Row],[Dividend per Share]],Table1[[#This Row],[Price]]) -> 7961000 | K66: =(exchange_fee+broker_fee)*J66 -> 15388.613 | L66: =SUM(Table1[[#This Row],[Amount]]:Table1[[#This Row],[Total Fee]]) -> 7976388.6 | M66: =IF(OR(Table1[[#This Row],[Action]]="Buy",Table1[[#This Row],[Action]]="Withdraw"),-Table1[[#This Row],[Net Amount]],Table1[[#This Row],[Net Amount]]) -> -7976388.6
A67: 45679 | B67: ="TX"&TEXT(ROW()-1,"0000") -> TX0066 | C67: TLKM | D67: Buy | E67: 12 | F67: {=_xlfn.IFS(Table1[[#This Row],[Action]]="Buy",Table1[[#This Row],[Lot ]],Table1[[#This Row],[Action]]="Sell",-Table1[[#This Row],[Lot ]],Table1[[#This Row],[Action]]="Dividend",0,TRUE,"")} -> 12 | G67: 2330 | H67: {=IF(OR(Table1[[#This Row],[Stock Tickers]]="",Table1[[#This Row],[Action]]="Dividend"), "",IF(Table1[[#This Row],[Action]]="Buy",(SUMIFS($L$2:L67, $C$2:C67,Table1[[#This Row],[Stock Tickers]], $D$2:D67, "Buy") + Table1[[#This Row],[Amount]]) / ((SUMIFS($E$2:E67, $C$2:C67,Table1[[#This Row],[Stock Tickers]], $D$2:D67, "Buy") + Table1[[#This Row],[Lot ]])*100),LOOKUP(2, 1/($C$2:C67=Table1[[#This Row],[Stock Tickers]]), $G$2:G67)))} -> 2899.7135 | J67: =(Table1[[#This Row],[Lot ]]*100)*IF(Table1[[#This Row],[Action]]="Dividend",Table1[[#This Row],[Dividend per Share]],Table1[[#This Row],[Price]]) -> 2796000 | K67: =(exchange_fee+broker_fee)*J67 -> 5404.668 | L67: =SUM(Table1[[#This Row],[Amount]]:Table1[[#This Row],[Total Fee]]) -> 2801404.7 | M67: =IF(OR(Table1[[#This Row],[Action]]="Buy",Table1[[#This Row],[Action]]="Withdraw"),-Table1[[#This Row],[Net Amount]],Table1[[#This Row],[Net Amount]]) -> -2801404.7
A68: 45687 | B68: ="TX"&TEXT(ROW()-1,"0000") -> TX0067 | C68: GOTO | D68: Sell | E68: 107 | F68: {=_xlfn.IFS(Table1[[#This Row],[Action]]="Buy",Table1[[#This Row],[Lot ]],Table1[[#This Row],[Action]]="Sell",-Table1[[#This Row],[Lot ]],Table1[[#This Row],[Action]]="Dividend",0,TRUE,"")} -> -107 | G68: 141 | H68: {=IF(OR(Table1[[#This Row],[Stock Tickers]]="",Table1[[#This Row],[Action]]="Dividend"), "",IF(Table1[[#This Row],[Action]]="Buy",(SUMIFS($L$2:L68, $C$2:C68,Table1[[#This Row],[Stock Tickers]], $D$2:D68, "Buy") + Table1[[#This Row],[Amount]]) / ((SUMIFS($E$2:E68, $C$2:C68,Table1[[#This Row],[Stock Tickers]], $D$2:D68, "Buy") + Table1[[#This Row],[Lot ]])*100),LOOKUP(2, 1/($C$2:C68=Table1[[#This Row],[Stock Tickers]]), $G$2:G68)))} -> 141 | J68: =(Table1[[#This Row],[Lot ]]*100)*IF(Table1[[#This Row],[Action]]="Dividend",Table1[[#This Row],[Dividend per Share]],Table1[[#This Row],[Price]]) -> 1508700 | K68: =(exchange_fee+broker_fee)*J68 -> 2916.3171 | L68: =SUM(Table1[[#This Row],[Amount]]:Table1[[#This Row],[Total Fee]]) -> 1511616.3 | M68: =IF(OR(Table1[[#This Row],[Action]]="Buy",Table1[[#This Row],[Action]]="Withdraw"),-Table1[[#This Row],[Net Amount]],Table1[[#This Row],[Net Amount]]) -> 1511616.3
A69: 45691 | B69: ="TX"&TEXT(ROW()-1,"0000") -> TX0068 | C69: ASII | D69: Buy | E69: 9 | F69: {=_xlfn.IFS(Table1[[#This Row],[Action]]="Buy",Table1[[#This Row],[Lot ]],Table1[[#This Row],[Action]]="Sell",-Table1[[#This Row],[Lot ]],Table1[[#This Row],[Action]]="Dividend",0,TRUE,"")} -> 9 | G69: 4720 | H69: {=IF(OR(Table1[[#This Row],[Stock Tickers]]="",Table1[[#This Row],[Action]]="Dividend"), "",IF(Table1[[#This Row],[Action]]="Buy",(SUMIFS($L$2:L69, $C$2:C69,Table1[[#This Row],[Stock Tickers]], $D$2:D69, "Buy") + Table1[[#This Row],[Amount]]) / ((SUMIFS($E$2:E69, $C$2:C69,Table1[[#This Row],[Stock Tickers]], $D$2:D69, "Buy") + Table1[[#This Row],[Lot ]])*100),LOOKUP(2, 1/($C$2:C69=Table1[[#This Row],[Stock Tickers]]), $G$2:G69)))} -> 5005.6735 | J69: =(Table1[[#This Row],[Lot ]]*100)*IF(Table1[[#This Row],[Action]]="Dividend",Table1[[#This Row],[Dividend per Share]],Table1[[#This Row],[Price]]) -> 4248000 | K69: =(exchange_fee+broker_fee)*J69 -> 8211.384 | L69: =SUM(Table1[[#This Row],[Amount]]:Table1[[#This Row],[Total Fee]]) -> 4256211.4 | M69: =IF(OR(Table1[[#This Row],[Action]]="Buy",Table1[[#This Row],[Action]]="Withdraw"),-Table1[[#This Row],[Net Amount]],Table1[[#This Row],[Net Amount]]) -> -4256211.4
A70: 45702 | B70: ="TX"&TEXT(ROW()-1,"0000") -> TX0069 | D70: Deposit | F70: {=_xlfn.IFS(Table1[[#This Row],[Action]]="Buy",Table1[[#This Row],[Lot ]],Table1[[#This Row],[Action]]="Sell",-Table1[[#This Row],[Lot ]],Table1[[#This Row],[Action]]="Dividend",0,TRUE,"")} | H70: {=IF(OR(Table1[[#This Row],[Stock Tickers]]="",Table1[[#This Row],[Action]]="Dividend"), "",IF(Table1[[#This Row],[Action]]="Buy",(SUMIFS($L$2:L70, $C$2:C70,Table1[[#This Row],[Stock Tickers]], $D$2:D70, "Buy") + Table1[[#This Row],[Amount]]) / ((SUMIFS($E$2:E70, $C$2:C70,Table1[[#This Row],[Stock Tickers]], $D$2:D70, "Buy") + Table1[[#This Row],[Lot ]])*100),LOOKUP(2, 1/($C$2:C70=Table1[[#This Row],[Stock Tickers]]), $G$2:G70)))} | J70: 15000000 | L70: =SUM(Table1[[#This Row],[Amount]]:Table1[[#This Row],[Total Fee]]) -> 15000000 | M70: =IF(OR(Table1[[#This Row],[Action]]="Buy",Table1[[#This Row],[Action]]="Withdraw"),-Table1[[#This Row],[Net Amount]],Table1[[#This Row],[Net Amount]]) -> 15000000
A71: 45705 | B71: ="TX"&TEXT(ROW()-1,"0000") -> TX0070 | C71: BBCA | D71: Buy | E71: 15 | F71: {=_xlfn.IFS(Table1[[#This Row],[Action]]="Buy",Table1[[#This Row],[Lot ]],Table1[[#This Row],[Action]]="Sell",-Table1[[#This Row],[Lot ]],Table1[[#This Row],[Action]]="Dividend",0,TRUE,"")} -> 15 | G71: 5770 | H71: {=IF(OR(Table1[[#This Row],[Stock Tickers]]="",Table1[[#This Row],[Action]]="Dividend"), "",IF(Table1[[#This Row],[Action]]="Buy",(SUMIFS($L$2:L71, $C$2:C71,Table1[[#This Row],[Stock Tickers]], $D$2:D71, "Buy") + Table1[[#This Row],[Amount]]) / ((SUMIFS($E$2:E71, $C$2:C71,Table1[[#This Row],[Stock Tickers]], $D$2:D71, "Buy") + Table1[[#This Row],[Lot ]])*100),LOOKUP(2, 1/($C$2:C71=Table1[[#This Row],[Stock Tickers]]), $G$2:G71)))} -> 6410.8384 | J71: =(Table1[[#This Row],[Lot ]]*100)*IF(Table1[[#This Row],[Action]]="Dividend",Table1[[#This Row],[Dividend per Share]],Table1[[#This Row],[Price]]) -> 8655000 | K71: =(exchange_fee+broker_fee)*J71 -> 16730.115 | L71: =SUM(Table1[[#This Row],[Amount]]:Table1[[#This Row],[Total Fee]]) -> 8671730.1 | M71: =IF(OR(Table1[[#This Row],[Action]]="Buy",Table1[[#This Row],[Action]]="Withdraw"),-Table1[[#This Row],[Net Amount]],Table1[[#This Row],[Net Amount]]) -> -8671730.1
A72: 45712 | B72: ="TX"&TEXT(ROW()-1,"0000") -> TX0071 | C72: ITMG | D72: Dividend | E72: 29 | F72: {=_xlfn.IFS(Table1[[#This Row],[Action]]="Buy",Table1[[#This Row],[Lot ]],Table1[[#This Row],[Action]]="Sell",-Table1[[#This Row],[Lot ]],Table1[[#This Row],[Action]]="Dividend",0,TRUE,"")} -> 0 | H72: {=IF(OR(Table1[[#This Row],[Stock Tickers]]="",Table1[[#This Row],[Action]]="Dividend"), "",IF(Table1[[#This Row],[Action]]="Buy",(SUMIFS($L$2:L72, $C$2:C72,Table1[[#This Row],[Stock Tickers]], $D$2:D72, "Buy") + Table1[[#This Row],[Amount]]) / ((SUMIFS($E$2:E72, $C$2:C72,Table1[[#This Row],[Stock Tickers]], $D$2:D72, "Buy") + Table1[[#This Row],[Lot ]])*100),LOOKUP(2, 1/($C$2:C72=Table1[[#This Row],[Stock Tickers]]), $G$2:G72)))} | I72: 738 | J72: =(Table1[[#This Row],[Lot ]]*100)*IF(Table1[[#This Row],[Action]]="Dividend",Table1[[#This Row],[Dividend per Share]],Table1[[#This Row],[Price]]) -> 2140200 | L72: =SUM(Table1[[#This Row],[Amount]]:Table1[[#This Row],[Total Fee]]) -> 2140200 | M72: =IF(OR(Table1[[#This Row],[Action]]="Buy",Table1[[#This Row],[Action]]="Withdraw"),-Table1[[#This Row],[Net Amount]],Table1[[#This Row],[Net Amount]]) -> 2140200
A73: 45716 | B73: ="TX"&TEXT(ROW()-1,"0000") -> TX0072 | C73: ICBP | D73: Buy | E73: 7 | F73: {=_xlfn.IFS(Table1[[#This Row],[Action]]="Buy",Table1[[#This Row],[Lot ]],Table1[[#This Row],[Action]]="Sell",-Table1[[#This Row],[Lot ]],Table1[[#This Row],[Action]]="Dividend",0,TRUE,"")} -> 7 | G73: 8330 | H73: {=IF(OR(Table1[[#This Row],[Stock Tickers]]="",Table1[[#This Row],[Action]]="Dividend"), "",IF(Table1[[#This Row],[Action]]="Buy",(SUMIFS($L$2:L73, $C$2:C73,Table1[[#This Row],[Stock Tickers]], $D$2:D73, "Buy") + Table1[[#This Row],[Amount]]) / ((SUMIFS($E$2:E73, $C$2:C73,Table1[[#This Row],[Stock Tickers]], $D$2:D73, "Buy") + Table1[[#This Row],[Lot ]])*100),LOOKUP(2, 1/($C$2:C73=Table1[[#This Row],[Stock Tickers]]), $G$2:G73)))} -> 7052.4275 | J73: =(Table1[[#This Row],[Lot ]]*100)*IF(Table1[[#This Row],[Action]]="Dividend",Table1[[#This Row],[Dividend per Share]],Table1[[#This Row],[Price]]) -> 5831000 | K73: =(exchange_fee+broker_fee)*J73 -> 11271.323 | L73: =SUM(Table1[[#This Row],[Amount]]:Table1[[#This Row],[Total Fee]]) -> 5842271.3 | M73: =IF(OR(Table1[[#This Row],[Action]]="Buy",Table1[[#This Row],[Action]]="Withdraw"),-Table1[[#This Row],[Net Amount]],Table1[[#This Row],[Net Amount]]) -> -5842271.3
A74: 45717 | B74: ="TX"&TEXT(ROW()-1,"0000") -> TX0073 | C74: INDF | D74: Buy | E74: 5 | F74: {=_xlfn.IFS(Table1[[#This Row],[Action]]="Buy",Table1[[#This Row],[Lot ]],Table1[[#This Row],[Action]]="Sell",-Table1[[#This Row],[Lot ]],Table1[[#This Row],[Action]]="Dividend",0,TRUE,"")} -> 5 | G74: 7375 | H74: {=IF(OR(Table1[[#This Row],[Stock Tickers]]="",Table1[[#This Row],[Action]]="Dividend"), "",IF(Table1[[#This Row],[Action]]="Buy",(SUMIFS($L$2:L74, $C$2:C74,Table1[[#This Row],[Stock Tickers]], $D$2:D74, "Buy") + Table1[[#This Row],[Amount]]) / ((SUMIFS($E$2:E74, $C$2:C74,Table1[[#This Row],[Stock Tickers]], $D$2:D74, "Buy") + Table1[[#This Row],[Lot ]])*100),LOOKUP(2, 1/($C$2:C74=Table1[[#This Row],[Stock Tickers]]), $G$2:G74)))} -> 7382.1279 | J74: =(Table1[[#This Row],[Lot ]]*100)*IF(Table1[[#This Row],[Action]]="Dividend",Table1[[#This Row],[Dividend per Share]],Table1[[#This Row],[Price]]) -> 3687500 | K74: =(exchange_fee+broker_fee)*J74 -> 7127.9375 | L74: =SUM(Table1[[#This Row],[Amount]]:Table1[[#This Row],[Total Fee]]) -> 3694627.9 | M74: =IF(OR(Table1[[#This Row],[Action]]="Buy",Table1[[#This Row],[Action]]="Withdraw"),-Table1[[#This Row],[Net Amount]],Table1[[#This Row],[Net Amount]]) -> -3694627.9
A75: 45721 | B75: ="TX"&TEXT(ROW()-1,"0000") -> TX0074 | C75: BBRI | D75: Sell | E75: 25 | F75: {=_xlfn.IFS(Table1[[#This Row],[Action]]="Buy",Table1[[#This Row],[Lot ]],Table1[[#This Row],[Action]]="Sell",-Table1[[#This Row],[Lot ]],Table1[[#This Row],[Action]]="Dividend",0,TRUE,"")} -> -25 | G75: 5910 | H75: {=IF(OR(Table1[[#This Row],[Stock Tickers]]="",Table1[[#This Row],[Action]]="Dividend"), "",IF(Table1[[#This Row],[Action]]="Buy",(SUMIFS($L$2:L75, $C$2:C75,Table1[[#This Row],[Stock Tickers]], $D$2:D75, "Buy") + Table1[[#This Row],[Amount]]) / ((SUMIFS($E$2:E75, $C$2:C75,Table1[[#This Row],[Stock Tickers]], $D$2:D75, "Buy") + Table1[[#This Row],[Lot ]])*100),LOOKUP(2, 1/($C$2:C75=Table1[[#This Row],[Stock Tickers]]), $G$2:G75)))} -> 5910 | J75: =(Table1[[#This Row],[Lot ]]*100)*IF(Table1[[#This Row],[Action]]="Dividend",Table1[[#This Row],[Dividend per Share]],Table1[[#This Row],[Price]]) -> 14775000 | K75: =(exchange_fee+broker_fee)*J75 -> 28560.075 | L75: =SUM(Table1[[#This Row],[Amount]]:Table1[[#This Row],[Total Fee]]) -> 14803560 | M75: =IF(OR(Table1[[#This Row],[Action]]="Buy",Table1[[#This Row],[Action]]="Withdraw"),-Table1[[#This Row],[Net Amount]],Table1[[#This Row],[Net Amount]]) -> 14803560
A76: 45734 | B76: ="TX"&TEXT(ROW()-1,"0000") -> TX0075 | C76: GOTO | D76: Buy | E76: 15 | F76: {=_xlfn.IFS(Table1[[#This Row],[Action]]="Buy",Table1[[#This Row],[Lot ]],Table1[[#This Row],[Action]]="Sell",-Table1[[#This Row],[Lot ]],Table1[[#This Row],[Action]]="Dividend",0,TRUE,"")} -> 15 | G76: 95 | H76: {=IF(OR(Table1[[#This Row],[Stock Tickers]]="",Table1[[#This Row],[Action]]="Dividend"), "",IF(Table1[[#This Row],[Action]]="Buy",(SUMIFS($L$2:L76, $C$2:C76,Table1[[#This Row],[Stock Tickers]], $D$2:D76, "Buy") + Table1[[#This Row],[Amount]]) / ((SUMIFS($E$2:E76, $C$2:C76,Table1[[#This Row],[Stock Tickers]], $D$2:D76, "Buy") + Table1[[#This Row],[Lot ]])*100),LOOKUP(2, 1/($C$2:C76=Table1[[#This Row],[Stock Tickers]]), $G$2:G76)))} -> 109.1393 | J76: =(Table1[[#This Row],[Lot ]]*100)*IF(Table1[[#This Row],[Action]]="Dividend",Table1[[#This Row],[Dividend per Share]],Table1[[#This Row],[Price]]) -> 142500 | K76: =(exchange_fee+broker_fee)*J76 -> 275.4525 | L76: =SUM(Table1[[#This Row],[Amount]]:Table1[[#This Row],[Total Fee]]) -> 142775.45 | M76: =IF(OR(Table1[[#This Row],[Action]]="Buy",Table1[[#This Row],[Action]]="Withdraw"),-Table1[[#This Row],[Net Amount]],Table1[[#This Row],[Net Amount]]) -> -142775.45
A77: 45736 | B77: ="TX"&TEXT(ROW()-1,"0000") -> TX0076 | C77: 0 | D77: Buy | E77: 10 | F77: {=_xlfn.IFS(Table1[[#This Row],[Action]]="Buy",Table1[[#This Row],[Lot ]],Table1[[#This Row],[Action]]="Sell",-Table1[[#This Row],[Lot ]],Table1[[#This Row],[Action]]="Dividend",0,TRUE,"")} -> 10 | G77: 2410 | H77: {=IF(OR(Table1[[#This Row],[Stock Tickers]]="",Table1[[#This Row],[Action]]="Dividend"), "",IF(Table1[[#This Row],[Action]]="Buy",(SUMIFS($L$2:L77, $C$2:C77,Table1[[#This Row],[Stock Tickers]], $D$2:D77, "Buy") + Table1[[#This Row],[Amount]]) / ((SUMIFS($E$2:E77, $C$2:C77,Table1[[#This Row],[Stock Tickers]], $D$2:D77, "Buy") + Table1[[#This Row],[Lot ]])*100),LOOKUP(2, 1/($C$2:C77=Table1[[#This Row],[Stock Tickers]]), $G$2:G77)))} -> 2412.3293 | J77: =(Table1[[#This Row],[Lot ]]*100)*IF(Table1[[#This Row],[Action]]="Dividend",Table1[[#This Row],[Dividend per Share]],Table1[[#This Row],[Price]]) -> 2410000 | K77: =(exchange_fee+broker_fee)*J77 -> 4658.53 | L77: =SUM(Table1[[#This Row],[Amount]]:Table1[[#This Row],[Total Fee]]) -> 2414658.5 | M77: =IF(OR(Table1[[#This Row],[Action]]="Buy",Table1[[#This Row],[Action]]="Withdraw"),-Table1[[#This Row],[Net Amount]],Table1[[#This Row],[Net Amount]]) -> -2414658.5
A78: 45745 | B78: ="TX"&TEXT(ROW()-1,"0000") -> TX0077 | C78: BREN | D78: Buy | E78: 15 | F78: {=_xlfn.IFS(Table1[[#This Row],[Action]]="Buy",Table1[[#This Row],[Lot ]],Table1[[#This Row],[Action]]="Sell",-Table1[[#This Row],[Lot ]],Table1[[#This Row],[Action]]="Dividend",0,TRUE,"")} -> 15 | G78: 5300 | H78: {=IF(OR(Table1[[#This Row],[Stock Tickers]]="",Table1[[#This Row],[Action]]="Dividend"), "",IF(Table1[[#This Row],[Action]]="Buy",(SUMIFS($L$2:L78, $C$2:C78,Table1[[#This Row],[Stock Tickers]], $D$2:D78, "Buy") + Table1[[#This Row],[Amount]]) / ((SUMIFS($E$2:E78, $C$2:C78,Table1[[#This Row],[Stock Tickers]], $D$2:D78, "Buy") + Table1[[#This Row],[Lot ]])*100),LOOKUP(2, 1/($C$2:C78=Table1[[#This Row],[Stock Tickers]]), $G$2:G78)))} -> 5494.2655 | J78: =(Table1[[#This Row],[Lot ]]*100)*IF(Table1[[#This Row],[Action]]="Dividend",Table1[[#This Row],[Dividend per Share]],Table1[[#This Row],[Price]]) -> 7950000 | K78: =(exchange_fee+broker_fee)*J78 -> 15367.35 | L78: =SUM(Table1[[#This Row],[Amount]]:Table1[[#This Row],[Total Fee]]) -> 7965367.3 | M78: =IF(OR(Table1[[#This Row],[Action]]="Buy",Table1[[#This Row],[Action]]="Withdraw"),-Table1[[#This Row],[Net Amount]],Table1[[#This Row],[Net Amount]]) -> -7965367.3
A79: 45748 | B79: ="TX"&TEXT(ROW()-1,"0000") -> TX0078 | C79: ASII | D79: Dividend | E79: 123 | F79: {=_xlfn.IFS(Table1[[#This Row],[Action]]="Buy",Table1[[#This Row],[Lot ]],Table1[[#This Row],[Action]]="Sell",-Table1[[#This Row],[Lot ]],Table1[[#This Row],[Action]]="Dividend",0,TRUE,"")} -> 0 | H79: {=IF(OR(Table1[[#This Row],[Stock Tickers]]="",Table1[[#This Row],[Action]]="Dividend"), "",IF(Table1[[#This Row],[Action]]="Buy",(SUMIFS($L$2:L79, $C$2:C79,Table1[[#This Row],[Stock Tickers]], $D$2:D79, "Buy") + Table1[[#This Row],[Amount]]) / ((SUMIFS($E$2:E79, $C$2:C79,Table1[[#This Row],[Stock Tickers]], $D$2:D79, "Buy") + Table1[[#This Row],[Lot ]])*100),LOOKUP(2, 1/($C$2:C79=Table1[[#This Row],[Stock Tickers]]), $G$2:G79)))} | I79: 308 | J79: =(Table1[[#This Row],[Lot ]]*100)*IF(Table1[[#This Row],[Action]]="Dividend",Table1[[#This Row],[Dividend per Share]],Table1[[#This Row],[Price]]) -> 3788400 | L79: =SUM(Table1[[#This Row],[Amount]]:Table1[[#This Row],[Total Fee]]) -> 3788400 | M79: =IF(OR(Table1[[#This Row],[Action]]="Buy",Table1[[#This Row],[Action]]="Withdraw"),-Table1[[#This Row],[Net Amount]],Table1[[#This Row],[Net Amount]]) -> 3788400
A80: 45751 | B80: ="TX"&TEXT(ROW()-1,"0000") -> TX0079 | C80: BBCA | D80: Buy | E80: 8 | F80: {=_xlfn.IFS(Table1[[#This Row],[Action]]="Buy",Table1[[#This Row],[Lot ]],Table1[[#This Row],[Action]]="Sell",-Table1[[#This Row],[Lot ]],Table1[[#This Row],[Action]]="Dividend",0,TRUE,"")} -> 8 | G80: 6850 | H80: {=IF(OR(Table1[[#This Row],[Stock Tickers]]="",Table1[[#This Row],[Action]]="Dividend"), "",IF(Table1[[#This Row],[Action]]="Buy",(SUMIFS($L$2:L80, $C$2:C80,Table1[[#This Row],[Stock Tickers]], $D$2:D80, "Buy") + Table1[[#This Row],[Amount]]) / ((SUMIFS($E$2:E80, $C$2:C80,Table1[[#This Row],[Stock Tickers]], $D$2:D80, "Buy") + Table1[[#This Row],[Lot ]])*100),LOOKUP(2, 1/($C$2:C80=Table1[[#This Row],[Stock Tickers]]), $G$2:G80)))} -> 6610.1847 | J80: =(Table1[[#This Row],[Lot ]]*100)*IF(Table1[[#This Row],[Action]]="Dividend",Table1[[#This Row],[Dividend per Share]],Table1[[#This Row],[Price]]) -> 5480000 | K80: =(exchange_fee+broker_fee)*J80 -> 10592.84 | L80: =SUM(Table1[[#This Row],[Amount]]:Table1[[#This Row],[Total Fee]]) -> 5490592.8 | M80: =IF(OR(Table1[[#This Row],[Action]]="Buy",Table1[[#This Row],[Action]]="Withdraw"),-Table1[[#This Row],[Net Amount]],Table1[[#This Row],[Net Amount]]) -> -5490592.8
A81: 45758 | B81: ="TX"&TEXT(ROW()-1,"0000") -> TX0080 | C81: ADRO | D81: Buy | E81: 19 | F81: {=_xlfn.IFS(Table1[[#This Row],[Action]]="Buy",Table1[[#This Row],[Lot ]],Table1[[#This Row],[Action]]="Sell",-Table1[[#This Row],[Lot ]],Table1[[#This Row],[Action]]="Dividend",0,TRUE,"")} -> 19 | G81: 2770 | H81: {=IF(OR(Table1[[#This Row],[Stock Tickers]]="",Table1[[#This Row],[Action]]="Dividend"), "",IF(Table1[[#This Row],[Action]]="Buy",(SUMIFS($L$2:L81, $C$2:C81,Table1[[#This Row],[Stock Tickers]], $D$2:D81, "Buy") + Table1[[#This Row],[Amount]]) / ((SUMIFS($E$2:E81, $C$2:C81,Table1[[#This Row],[Stock Tickers]], $D$2:D81, "Buy") + Table1[[#This Row],[Lot ]])*100),LOOKUP(2, 1/($C$2:C81=Table1[[#This Row],[Stock Tickers]]), $G$2:G81)))} -> 2386.8247 | J81: =(Table1[[#This Row],[Lot ]]*100)*IF(Table1[[#This Row],[Action]]="Dividend",Table1[[#This Row],[Dividend per Share]],Table1[[#This Row],[Price]]) -> 5263000 | K81: =(exchange_fee+broker_fee)*J81 -> 10173.379 | L81: =SUM(Table1[[#This Row],[Amount]]:Table1[[#This Row],[Total Fee]]) -> 5273173.4 | M81: =IF(OR(Table1[[#This Row],[Action]]="Buy",Table1[[#This Row],[Action]]="Withdraw"),-Table1[[#This Row],[Net Amount]],Table1[[#This Row],[Net Amount]]) -> -5273173.4
A82: 45760 | B82: ="TX"&TEXT(ROW()-1,"0000") -> TX0081 | D82: Deposit | F82: {=_xlfn.IFS(Table1[[#This Row],[Action]]="Buy",Table1[[#This Row],[Lot ]],Table1[[#This Row],[Action]]="Sell",-Table1[[#This Row],[Lot ]],Table1[[#This Row],[Action]]="Dividend",0,TRUE,"")} | H82: {=IF(OR(Table1[[#This Row],[Stock Tickers]]="",Table1[[#This Row],[Action]]="Dividend"), "",IF(Table1[[#This Row],[Action]]="Buy",(SUMIFS($L$2:L82, $C$2:C82,Table1[[#This Row],[Stock Tickers]], $D$2:D82, "Buy") + Table1[[#This Row],[Amount]]) / ((SUMIFS($E$2:E82, $C$2:C82,Table1[[#This Row],[Stock Tickers]], $D$2:D82, "Buy") + Table1[[#This Row],[Lot ]])*100),LOOKUP(2, 1/($C$2:C82=Table1[[#This Row],[Stock Tickers]]), $G$2:G82)))} | J82: 150000000 | L82: =SUM(Table1[[#This Row],[Amount]]:Table1[[#This Row],[Total Fee]]) -> 150000000 | M82: =IF(OR(Table1[[#This Row],[Action]]="Buy",Table1[[#This Row],[Action]]="Withdraw"),-Table1[[#This Row],[Net Amount]],Table1[[#This Row],[Net Amount]]) -> 150000000
A83: 45774 | B83: ="TX"&TEXT(ROW()-1,"0000") -> TX0082 | C83: ICBP | D83: Buy | E83: 6 | F83: {=_xlfn.IFS(Table1[[#This Row],[Action]]="Buy",Table1[[#This Row],[Lot ]],Table1[[#This Row],[Action]]="Sell",-Table1[[#This Row],[Lot ]],Table1[[#This Row],[Action]]="Dividend",0,TRUE,"")} -> 6 | G83: 9100 | H83: {=IF(OR(Table1[[#This Row],[Stock Tickers]]="",Table1[[#This Row],[Action]]="Dividend"), "",IF(Table1[[#This Row],[Action]]="Buy",(SUMIFS($L$2:L83, $C$2:C83,Table1[[#This Row],[Stock Tickers]], $D$2:D83, "Buy") + Table1[[#This Row],[Amount]]) / ((SUMIFS($E$2:E83, $C$2:C83,Table1[[#This Row],[Stock Tickers]], $D$2:D83, "Buy") + Table1[[#This Row],[Lot ]])*100),LOOKUP(2, 1/($C$2:C83=Table1[[#This Row],[Stock Tickers]]), $G$2:G83)))} -> 7262.2063 | J83: =(Table1[[#This Row],[Lot ]]*100)*IF(Table1[[#This Row],[Action]]="Dividend",Table1[[#This Row],[Dividend per Share]],Table1[[#This Row],[Price]]) -> 5460000 | K83: =(exchange_fee+broker_fee)*J83 -> 10554.18 | L83: =SUM(Table1[[#This Row],[Amount]]:Table1[[#This Row],[Total Fee]]) -> 5470554.2 | M83: =IF(OR(Table1[[#This Row],[Action]]="Buy",Table1[[#This Row],[Action]]="Withdraw"),-Table1[[#This Row],[Net Amount]],Table1[[#This Row],[Net Amount]]) -> -5470554.2
A84: 45775 | B84: ="TX"&TEXT(ROW()-1,"0000") -> TX0083 | C84: BBRI | D84: Buy | E84: 14 | F84: {=_xlfn.IFS(Table1[[#This Row],[Action]]="Buy",Table1[[#This Row],[Lot ]],Table1[[#This Row],[Action]]="Sell",-Table1[[#This Row],[Lot ]],Table1[[#This Row],[Action]]="Dividend",0,TRUE,"")} -> 14 | G84: 3120 | H84: {=IF(OR(Table1[[#This Row],[Stock Tickers]]="",Table1[[#This Row],[Action]]="Dividend"), "",IF(Table1[[#This Row],[Action]]="Buy",(SUMIFS($L$2:L84, $C$2:C84,Table1[[#This Row],[Stock Tickers]], $D$2:D84, "Buy") + Table1[[#This Row],[Amount]]) / ((SUMIFS($E$2:E84, $C$2:C84,Table1[[#This Row],[Stock Tickers]], $D$2:D84, "Buy") + Table1[[#This Row],[Lot ]])*100),LOOKUP(2, 1/($C$2:C84=Table1[[#This Row],[Stock Tickers]]), $G$2:G84)))} -> 3593.2394 | J84: =(Table1[[#This Row],[Lot ]]*100)*IF(Table1[[#This Row],[Action]]="Dividend",Table1[[#This Row],[Dividend per Share]],Table1[[#This Row],[Price]]) -> 4368000 | K84: =(exchange_fee+broker_fee)*J84 -> 8443.344 | L84: =SUM(Table1[[#This Row],[Amount]]:Table1[[#This Row],[Total Fee]]) -> 4376443.3 | M84: =IF(OR(Table1[[#This Row],[Action]]="Buy",Table1[[#This Row],[Action]]="Withdraw"),-Table1[[#This Row],[Net Amount]],Table1[[#This Row],[Net Amount]]) -> -4376443.3
A85: 45782 | B85: ="TX"&TEXT(ROW()-1,"0000") -> TX0084 | C85: TLKM | D85: Sell | E85: 5 | F85: {=_xlfn.IFS(Table1[[#This Row],[Action]]="Buy",Table1[[#This Row],[Lot ]],Table1[[#This Row],[Action]]="Sell",-Table1[[#This Row],[Lot ]],Table1[[#This Row],[Action]]="Dividend",0,TRUE,"")} -> -5 | G85: 3920 | H85: {=IF(OR(Table1[[#This Row],[Stock Tickers]]="",Table1[[#This Row],[Action]]="Dividend"), "",IF(Table1[[#This Row],[Action]]="Buy",(SUMIFS($L$2:L85, $C$2:C85,Table1[[#This Row],[Stock Tickers]], $D$2:D85, "Buy") + Table1[[#This Row],[Amount]]) / ((SUMIFS($E$2:E85, $C$2:C85,Table1[[#This Row],[Stock Tickers]], $D$2:D85, "Buy") + Table1[[#This Row],[Lot ]])*100),LOOKUP(2, 1/($C$2:C85=Table1[[#This Row],[Stock Tickers]]), $G$2:G85)))} -> 3920 | J85: =(Table1[[#This Row],[Lot ]]*100)*IF(Table1[[#This Row],[Action]]="Dividend",Table1[[#This Row],[Dividend per Share]],Table1[[#This Row],[Price]]) -> 1960000 | K85: =(exchange_fee+broker_fee)*J85 -> 3788.68 | L85: =SUM(Table1[[#This Row],[Amount]]:Table1[[#This Row],[Total Fee]]) -> 1963788.7 | M85: =IF(OR(Table1[[#This Row],[Action]]="Buy",Table1[[#This Row],[Action]]="Withdraw"),-Table1[[#This Row],[Net Amount]],Table1[[#This Row],[Net Amount]]) -> 1963788.7
A86: 45782 | B86: ="TX"&TEXT(ROW()-1,"0000") -> TX0085 | C86: GOTO | D86: Sell | E86: 35 | F86: {=_xlfn.IFS(Table1[[#This Row],[Action]]="Buy",Table1[[#This Row],[Lot ]],Table1[[#This Row],[Action]]="Sell",-Table1[[#This Row],[Lot ]],Table1[[#This Row],[Action]]="Dividend",0,TRUE,"")} -> -35 | G86: 78 | H86: {=IF(OR(Table1[[#This Row],[Stock Tickers]]="",Table1[[#This Row],[Action]]="Dividend"), "",IF(Table1[[#This Row],[Action]]="Buy",(SUMIFS($L$2:L86, $C$2:C86,Table1[[#This Row],[Stock Tickers]], $D$2:D86, "Buy") + Table1[[#This Row],[Amount]]) / ((SUMIFS($E$2:E86, $C$2:C86,Table1[[#This Row],[Stock Tickers]], $D$2:D86, "Buy") + Table1[[#This Row],[Lot ]])*100),LOOKUP(2, 1/($C$2:C86=Table1[[#This Row],[Stock Tickers]]), $G$2:G86)))} -> 78 | J86: =(Table1[[#This Row],[Lot ]]*100)*IF(Table1[[#This Row],[Action]]="Dividend",Table1[[#This Row],[Dividend per Share]],Table1[[#This Row],[Price]]) -> 273000 | K86: =(exchange_fee+broker_fee)*J86 -> 527.709 | L86: =SUM(Table1[[#This Row],[Amount]]:Table1[[#This Row],[Total Fee]]) -> 273527.71 | M86: =IF(OR(Table1[[#This Row],[Action]]="Buy",Table1[[#This Row],[Action]]="Withdraw"),-Table1[[#This Row],[Net Amount]],Table1[[#This Row],[Net Amount]]) -> 273527.71
A87: 45792 | B87: ="TX"&TEXT(ROW()-1,"0000") -> TX0086 | C87: GOTO | D87: Buy | E87: 32 | F87: {=_xlfn.IFS(Table1[[#This Row],[Action]]="Buy",Table1[[#This Row],[Lot ]],Table1[[#This Row],[Action]]="Sell",-Table1[[#This Row],[Lot ]],Table1[[#This Row],[Action]]="Dividend",0,TRUE,"")} -> 32 | G87: 64 | H87: {=IF(OR(Table1[[#This Row],[Stock Tickers]]="",Table1[[#This Row],[Action]]="Dividend"), "",IF(Table1[[#This Row],[Action]]="Buy",(SUMIFS($L$2:L87, $C$2:C87,Table1[[#This Row],[Stock Tickers]], $D$2:D87, "Buy") + Table1[[#This Row],[Amount]]) / ((SUMIFS($E$2:E87, $C$2:C87,Table1[[#This Row],[Stock Tickers]], $D$2:D87, "Buy") + Table1[[#This Row],[Lot ]])*100),LOOKUP(2, 1/($C$2:C87=Table1[[#This Row],[Stock Tickers]]), $G$2:G87)))} -> 99.23979 | J87: =(Table1[[#This Row],[Lot ]]*100)*IF(Table1[[#This Row],[Action]]="Dividend",Table1[[#This Row],[Dividend per Share]],Table1[[#This Row],[Price]]) -> 204800 | K87: =(exchange_fee+broker_fee)*J87 -> 395.8784 | L87: =SUM(Table1[[#This Row],[Amount]]:Table1[[#This Row],[Total Fee]]) -> 205195.88 | M87: =IF(OR(Table1[[#This Row],[Action]]="Buy",Table1[[#This Row],[Action]]="Withdraw"),-Table1[[#This Row],[Net Amount]],Table1[[#This Row],[Net Amount]]) -> -205195.88
A88: 45799 | B88: ="TX"&TEXT(ROW()-1,"0000") -> TX0087 | C88: ASII | D88: Buy | E88: 11 | F88: {=_xlfn.IFS(Table1[[#This Row],[Action]]="Buy",Table1[[#This Row],[Lot ]],Table1[[#This Row],[Action]]="Sell",-Table1[[#This Row],[Lot ]],Table1[[#This Row],[Action]]="Dividend",0,TRUE,"")} -> 11 | G88: 5810 | H88: {=IF(OR(Table1[[#This Row],[Stock Tickers]]="",Table1[[#This Row],[Action]]="Dividend"), "",IF(Table1[[#This Row],[Action]]="Buy",(SUMIFS($L$2:L88, $C$2:C88,Table1[[#This Row],[Stock Tickers]], $D$2:D88, "Buy") + Table1[[#This Row],[Amount]]) / ((SUMIFS($E$2:E88, $C$2:C88,Table1[[#This Row],[Stock Tickers]], $D$2:D88, "Buy") + Table1[[#This Row],[Lot ]])*100),LOOKUP(2, 1/($C$2:C88=Table1[[#This Row],[Stock Tickers]]), $G$2:G88)))} -> 5152.3626 | J88: =(Table1[[#This Row],[Lot ]]*100)*IF(Table1[[#This Row],[Action]]="Dividend",Table1[[#This Row],[Dividend per Share]],Table1[[#This Row],[Price]]) -> 6391000 | K88: =(exchange_fee+broker_fee)*J88 -> 12353.803 | L88: =SUM(Table1[[#This Row],[Amount]]:Table1[[#This Row],[Total Fee]]) -> 6403353.8 | M88: =IF(OR(Table1[[#This Row],[Action]]="Buy",Table1[[#This Row],[Action]]="Withdraw"),-Table1[[#This Row],[Net Amount]],Table1[[#This Row],[Net Amount]]) -> -6403353.8
A89: 45806 | B89: ="TX"&TEXT(ROW()-1,"0000") -> TX0088 | C89: BBCA | D89: Dividend | E89: 81 | F89: {=_xlfn.IFS(Table1[[#This Row],[Action]]="Buy",Table1[[#This Row],[Lot ]],Table1[[#This Row],[Action]]="Sell",-Table1[[#This Row],[Lot ]],Table1[[#This Row],[Action]]="Dividend",0,TRUE,"")} -> 0 | H89: {=IF(OR(Table1[[#This Row],[Stock Tickers]]="",Table1[[#This Row],[Action]]="Dividend"), "",IF(Table1[[#This Row],[Action]]="Buy",(SUMIFS($L$2:L89, $C$2:C89,Table1[[#This Row],[Stock Tickers]], $D$2:D89, "Buy") + Table1[[#This Row],[Amount]]) / ((SUMIFS($E$2:E89, $C$2:C89,Table1[[#This Row],[Stock Tickers]], $D$2:D89, "Buy") + Table1[[#This Row],[Lot ]])*100),LOOKUP(2, 1/($C$2:C89=Table1[[#This Row],[Stock Tickers]]), $G$2:G89)))} | I89: 305 | J89: =(Table1[[#This Row],[Lot ]]*100)*IF(Table1[[#This Row],[Action]]="Dividend",Table1[[#This Row],[Dividend per Share]],Table1[[#This Row],[Price]]) -> 2470500 | L89: =SUM(Table1[[#This Row],[Amount]]:Table1[[#This Row],[Total Fee]]) -> 2470500 | M89: =IF(OR(Table1[[#This Row],[Action]]="Buy",Table1[[#This Row],[Action]]="Withdraw"),-Table1[[#This Row],[Net Amount]],Table1[[#This Row],[Net Amount]]) -> 2470500
A90: 45810 | B90: ="TX"&TEXT(ROW()-1,"0000") -> TX0089 | C90: BBRI | D90: Dividend | E90: 213 | F90: {=_xlfn.IFS(Table1[[#This Row],[Action]]="Buy",Table1[[#This Row],[Lot ]],Table1[[#This Row],[Action]]="Sell",-Table1[[#This Row],[Lot ]],Table1[[#This Row],[Action]]="Dividend",0,TRUE,"")} -> 0 | H90: {=IF(OR(Table1[[#This Row],[Stock Tickers]]="",Table1[[#This Row],[Action]]="Dividend"), "",IF(Table1[[#This Row],[Action]]="Buy",(SUMIFS($L$2:L90, $C$2:C90,Table1[[#This Row],[Stock Tickers]], $D$2:D90, "Buy") + Table1[[#This Row],[Amount]]) / ((SUMIFS($E$2:E90, $C$2:C90,Table1[[#This Row],[Stock Tickers]], $D$2:D90, "Buy") + Table1[[#This Row],[Lot ]])*100),LOOKUP(2, 1/($C$2:C90=Table1[[#This Row],[Stock Tickers]]), $G$2:G90)))} | I90: 50 | J90: =(Table1[[#This Row],[Lot ]]*100)*IF(Table1[[#This Row],[Action]]="Dividend",Table1[[#This Row],[Dividend per Share]],Table1[[#This Row],[Price]]) -> 1065000 | L90: =SUM(Table1[[#This Row],[Amount]]:Table1[[#This Row],[Total Fee]]) -> 1065000 | M90: =IF(OR(Table1[[#This Row],[Action]]="Buy",Table1[[#This Row],[Action]]="Withdraw"),-Table1[[#This Row],[Net Amount]],Table1[[#This Row],[Net Amount]]) -> 1065000
A91: 45812 | B91: ="TX"&TEXT(ROW()-1,"0000") -> TX0090 | C91: ADRO | D91: Buy | E91: 15 | F91: {=_xlfn.IFS(Table1[[#This Row],[Action]]="Buy",Table1[[#This Row],[Lot ]],Table1[[#This Row],[Action]]="Sell",-Table1[[#This Row],[Lot ]],Table1[[#This Row],[Action]]="Dividend",0,TRUE,"")} -> 15 | G91: 2340 | H91: {=IF(OR(Table1[[#This Row],[Stock Tickers]]="",Table1[[#This Row],[Action]]="Dividend"), "",IF(Table1[[#This Row],[Action]]="Buy",(SUMIFS($L$2:L91, $C$2:C91,Table1[[#This Row],[Stock Tickers]], $D$2:D91, "Buy") + Table1[[#This Row],[Amount]]) / ((SUMIFS($E$2:E91, $C$2:C91,Table1[[#This Row],[Stock Tickers]], $D$2:D91, "Buy") + Table1[[#This Row],[Lot ]])*100),LOOKUP(2, 1/($C$2:C91=Table1[[#This Row],[Stock Tickers]]), $G$2:G91)))} -> 2342.6338 | J91: =(Table1[[#This Row],[Lot ]]*100)*IF(Table1[[#This Row],[Action]]="Dividend",Table1[[#This Row],[Dividend per Share]],Table1[[#This Row],[Price]]) -> 3510000 | K91: =(exchange_fee+broker_fee)*J91 -> 6784.83 | L91: =SUM(Table1[[#This Row],[Amount]]:Table1[[#This Row],[Total Fee]]) -> 3516784.8 | M91: =IF(OR(Table1[[#This Row],[Action]]="Buy",Table1[[#This Row],[Action]]="Withdraw"),-Table1[[#This Row],[Net Amount]],Table1[[#This Row],[Net Amount]]) -> -3516784.8
A92: 45824 | B92: ="TX"&TEXT(ROW()-1,"0000") -> TX0091 | C92: ICBP | D92: Sell | E92: 13 | F92: {=_xlfn.IFS(Table1[[#This Row],[Action]]="Buy",Table1[[#This Row],[Lot ]],Table1[[#This Row],[Action]]="Sell",-Table1[[#This Row],[Lot ]],Table1[[#This Row],[Action]]="Dividend",0,TRUE,"")} -> -13 | G92: 1240 | H92: {=IF(OR(Table1[[#This Row],[Stock Tickers]]="",Table1[[#This Row],[Action]]="Dividend"), "",IF(Table1[[#This Row],[Action]]="Buy",(SUMIFS($L$2:L92, $C$2:C92,Table1[[#This Row],[Stock Tickers]], $D$2:D92, "Buy") + Table1[[#This Row],[Amount]]) / ((SUMIFS($E$2:E92, $C$2:C92,Table1[[#This Row],[Stock Tickers]], $D$2:D92, "Buy") + Table1[[#This Row],[Lot ]])*100),LOOKUP(2, 1/($C$2:C92=Table1[[#This Row],[Stock Tickers]]), $G$2:G92)))} -> 1240 | J92: =(Table1[[#This Row],[Lot ]]*100)*IF(Table1[[#This Row],[Action]]="Dividend",Table1[[#This Row],[Dividend per Share]],Table1[[#This Row],[Price]]) -> 1612000 | K92: =(exchange_fee+broker_fee)*J92 -> 3115.996 | L92: =SUM(Table1[[#This Row],[Amount]]:Table1[[#This Row],[Total Fee]]) -> 1615116 | M92: =IF(OR(Table1[[#This Row],[Action]]="Buy",Table1[[#This Row],[Action]]="Withdraw"),-Table1[[#This Row],[Net Amount]],Table1[[#This Row],[Net Amount]]) -> 1615116
A93: 45830 | B93: ="TX"&TEXT(ROW()-1,"0000") -> TX0092 | C93: BBRI | D93: Buy | E93: 19 | F93: {=_xlfn.IFS(Table1[[#This Row],[Action]]="Buy",Table1[[#This Row],[Lot ]],Table1[[#This Row],[Action]]="Sell",-Table1[[#This Row],[Lot ]],Table1[[#This Row],[Action]]="Dividend",0,TRUE,"")} -> 19 | G93: 4190 | H93: {=IF(OR(Table1[[#This Row],[Stock Tickers]]="",Table1[[#This Row],[Action]]="Dividend"), "",IF(Table1[[#This Row],[Action]]="Buy",(SUMIFS($L$2:L93, $C$2:C93,Table1[[#This Row],[Stock Tickers]], $D$2:D93, "Buy") + Table1[[#This Row],[Amount]]) / ((SUMIFS($E$2:E93, $C$2:C93,Table1[[#This Row],[Stock Tickers]], $D$2:D93, "Buy") + Table1[[#This Row],[Lot ]])*100),LOOKUP(2, 1/($C$2:C93=Table1[[#This Row],[Stock Tickers]]), $G$2:G93)))} -> 3732.1835 | J93: =(Table1[[#This Row],[Lot ]]*100)*IF(Table1[[#This Row],[Action]]="Dividend",Table1[[#This Row],[Dividend per Share]],Table1[[#This Row],[Price]]) -> 7961000 | K93: =(exchange_fee+broker_fee)*J93 -> 15388.613 | L93: =SUM(Table1[[#This Row],[Amount]]:Table1[[#This Row],[Total Fee]]) -> 7976388.6 | M93: =IF(OR(Table1[[#This Row],[Action]]="Buy",Table1[[#This Row],[Action]]="Withdraw"),-Table1[[#This Row],[Net Amount]],Table1[[#This Row],[Net Amount]]) -> -7976388.6
A94: 45847 | B94: ="TX"&TEXT(ROW()-1,"0000") -> TX0093 | D94: Withdraw | F94: {=_xlfn.IFS(Table1[[#This Row],[Action]]="Buy",Table1[[#This Row],[Lot ]],Table1[[#This Row],[Action]]="Sell",-Table1[[#This Row],[Lot ]],Table1[[#This Row],[Action]]="Dividend",0,TRUE,"")} | H94: {=IF(OR(Table1[[#This Row],[Stock Tickers]]="",Table1[[#This Row],[Action]]="Dividend"), "",IF(Table1[[#This Row],[Action]]="Buy",(SUMIFS($L$2:L94, $C$2:C94,Table1[[#This Row],[Stock Tickers]], $D$2:D94, "Buy") + Table1[[#This Row],[Amount]]) / ((SUMIFS($E$2:E94, $C$2:C94,Table1[[#This Row],[Stock Tickers]], $D$2:D94, "Buy") + Table1[[#This Row],[Lot ]])*100),LOOKUP(2, 1/($C$2:C94=Table1[[#This Row],[Stock Tickers]]), $G$2:G94)))} | J94: 30000000 | L94: =SUM(Table1[[#This Row],[Amount]]:Table1[[#This Row],[Total Fee]]) -> 30000000 | M94: =IF(OR(Table1[[#This Row],[Action]]="Buy",Table1[[#This Row],[Action]]="Withdraw"),-Table1[[#This Row],[Net Amount]],Table1[[#This Row],[Net Amount]]) -> -30000000
A95: 45856 | B95: ="TX"&TEXT(ROW()-1,"0000") -> TX0094 | C95: TLKM | D95: Buy | E95: 7 | F95: {=_xlfn.IFS(Table1[[#This Row],[Action]]="Buy",Table1[[#This Row],[Lot ]],Table1[[#This Row],[Action]]="Sell",-Table1[[#This Row],[Lot ]],Table1[[#This Row],[Action]]="Dividend",0,TRUE,"")} -> 7 | G95: 2540 | H95: {=IF(OR(Table1[[#This Row],[Stock Tickers]]="",Table1[[#This Row],[Action]]="Dividend"), "",IF(Table1[[#This Row],[Action]]="Buy",(SUMIFS($L$2:L95, $C$2:C95,Table1[[#This Row],[Stock Tickers]], $D$2:D95, "Buy") + Table1[[#This Row],[Amount]]) / ((SUMIFS($E$2:E95, $C$2:C95,Table1[[#This Row],[Stock Tickers]], $D$2:D95, "Buy") + Table1[[#This Row],[Lot ]])*100),LOOKUP(2, 1/($C$2:C95=Table1[[#This Row],[Stock Tickers]]), $G$2:G95)))} -> 2915.0046 | J95: =(Table1[[#This Row],[Lot ]]*100)*IF(Table1[[#This Row],[Action]]="Dividend",Table1[[#This Row],[Dividend per Share]],Table1[[#This Row],[Price]]) -> 1778000 | K95: =(exchange_fee+broker_fee)*J95 -> 3436.874 | L95: =SUM(Table1[[#This Row],[Amount]]:Table1[[#This Row],[Total Fee]]) -> 1781436.9 | M95: =IF(OR(Table1[[#This Row],[Action]]="Buy",Table1[[#This Row],[Action]]="Withdraw"),-Table1[[#This Row],[Net Amount]],Table1[[#This Row],[Net Amount]]) -> -1781436.9
A96: 45865 | B96: ="TX"&TEXT(ROW()-1,"0000") -> TX0095 | C96: ITMG | D96: Dividend | E96: 29 | F96: {=_xlfn.IFS(Table1[[#This Row],[Action]]="Buy",Table1[[#This Row],[Lot ]],Table1[[#This Row],[Action]]="Sell",-Table1[[#This Row],[Lot ]],Table1[[#This Row],[Action]]="Dividend",0,TRUE,"")} -> 0 | H96: {=IF(OR(Table1[[#This Row],[Stock Tickers]]="",Table1[[#This Row],[Action]]="Dividend"), "",IF(Table1[[#This Row],[Action]]="Buy",(SUMIFS($L$2:L96, $C$2:C96,Table1[[#This Row],[Stock Tickers]], $D$2:D96, "Buy") + Table1[[#This Row],[Amount]]) / ((SUMIFS($E$2:E96, $C$2:C96,Table1[[#This Row],[Stock Tickers]], $D$2:D96, "Buy") + Table1[[#This Row],[Lot ]])*100),LOOKUP(2, 1/($C$2:C96=Table1[[#This Row],[Stock Tickers]]), $G$2:G96)))} | I96: 2245 | J96: =(Table1[[#This Row],[Lot ]]*100)*IF(Table1[[#This Row],[Action]]="Dividend",Table1[[#This Row],[Dividend per Share]],Table1[[#This Row],[Price]]) -> 6510500 | L96: =SUM(Table1[[#This Row],[Amount]]:Table1[[#This Row],[Total Fee]]) -> 6510500 | M96: =IF(OR(Table1[[#This Row],[Action]]="Buy",Table1[[#This Row],[Action]]="Withdraw"),-Table1[[#This Row],[Net Amount]],Table1[[#This Row],[Net Amount]]) -> 6510500
A97: 45872 | B97: ="TX"&TEXT(ROW()-1,"0000") -> TX0096 | C97: ASII | D97: Buy | E97: 13 | F97: {=_xlfn.IFS(Table1[[#This Row],[Action]]="Buy",Table1[[#This Row],[Lot ]],Table1[[#This Row],[Action]]="Sell",-Table1[[#This Row],[Lot ]],Table1[[#This Row],[Action]]="Dividend",0,TRUE,"")} -> 13 | G97: 6540 | H97: {=IF(OR(Table1[[#This Row],[Stock Tickers]]="",Table1[[#This Row],[Action]]="Dividend"), "",IF(Table1[[#This Row],[Action]]="Buy",(SUMIFS($L$2:L97, $C$2:C97,Table1[[#This Row],[Stock Tickers]], $D$2:D97, "Buy") + Table1[[#This Row],[Amount]]) / ((SUMIFS($E$2:E97, $C$2:C97,Table1[[#This Row],[Stock Tickers]], $D$2:D97, "Buy") + Table1[[#This Row],[Lot ]])*100),LOOKUP(2, 1/($C$2:C97=Table1[[#This Row],[Stock Tickers]]), $G$2:G97)))} -> 5340.7321 | J97: =(Table1[[#This Row],[Lot ]]*100)*IF(Table1[[#This Row],[Action]]="Dividend",Table1[[#This Row],[Dividend per Share]],Table1[[#This Row],[Price]]) -> 8502000 | K97: =(exchange_fee+broker_fee)*J97 -> 16434.366 | L97: =SUM(Table1[[#This Row],[Amount]]:Table1[[#This Row],[Total Fee]]) -> 8518434.4 | M97: =IF(OR(Table1[[#This Row],[Action]]="Buy",Table1[[#This Row],[Action]]="Withdraw"),-Table1[[#This Row],[Net Amount]],Table1[[#This Row],[Net Amount]]) -> -8518434.4
A98: 45873 | B98: ="TX"&TEXT(ROW()-1,"0000") -> TX0097 | D98: Deposit | F98: {=_xlfn.IFS(Table1[[#This Row],[Action]]="Buy",Table1[[#This Row],[Lot ]],Table1[[#This Row],[Action]]="Sell",-Table1[[#This Row],[Lot ]],Table1[[#This Row],[Action]]="Dividend",0,TRUE,"")} | H98: {=IF(OR(Table1[[#This Row],[Stock Tickers]]="",Table1[[#This Row],[Action]]="Dividend"), "",IF(Table1[[#This Row],[Action]]="Buy",(SUMIFS($L$2:L98, $C$2:C98,Table1[[#This Row],[Stock Tickers]], $D$2:D98, "Buy") + Table1[[#This Row],[Amount]]) / ((SUMIFS($E$2:E98, $C$2:C98,Table1[[#This Row],[Stock Tickers]], $D$2:D98, "Buy") + Table1[[#This Row],[Lot ]])*100),LOOKUP(2, 1/($C$2:C98=Table1[[#This Row],[Stock Tickers]]), $G$2:G98)))} | J98: 10000000 | L98: =SUM(Table1[[#This Row],[Amount]]:Table1[[#This Row],[Total Fee]]) -> 10000000 | M98: =IF(OR(Table1[[#This Row],[Action]]="Buy",Table1[[#This Row],[Action]]="Withdraw"),-Table1[[#This Row],[Net Amount]],Table1[[#This Row],[Net Amount]]) -> 10000000
A99: 45885 | B99: ="TX"&TEXT(ROW()-1,"0000") -> TX0098 | C99: BBCA | D99: Buy | E99: 36 | F99: {=_xlfn.IFS(Table1[[#This Row],[Action]]="Buy",Table1[[#This Row],[Lot ]],Table1[[#This Row],[Action]]="Sell",-Table1[[#This Row],[Lot ]],Table1[[#This Row],[Action]]="Dividend",0,TRUE,"")} -> 36 | G99: 7730 | H99: {=IF(OR(Table1[[#This Row],[Stock Tickers]]="",Table1[[#This Row],[Action]]="Dividend"), "",IF(Table1[[#This Row],[Action]]="Buy",(SUMIFS($L$2:L99, $C$2:C99,Table1[[#This Row],[Stock Tickers]], $D$2:D99, "Buy") + Table1[[#This Row],[Amount]]) / ((SUMIFS($E$2:E99, $C$2:C99,Table1[[#This Row],[Stock Tickers]], $D$2:D99, "Buy") + Table1[[#This Row],[Lot ]])*100),LOOKUP(2, 1/($C$2:C99=Table1[[#This Row],[Stock Tickers]]), $G$2:G99)))} -> 7145.6313 | J99: =(Table1[[#This Row],[Lot ]]*100)*IF(Table1[[#This Row],[Action]]="Dividend",Table1[[#This Row],[Dividend per Share]],Table1[[#This Row],[Price]]) -> 27828000 | K99: =(exchange_fee+broker_fee)*J99 -> 53791.524 | L99: =SUM(Table1[[#This Row],[Amount]]:Table1[[#This Row],[Total Fee]]) -> 27881792 | M99: =IF(OR(Table1[[#This Row],[Action]]="Buy",Table1[[#This Row],[Action]]="Withdraw"),-Table1[[#This Row],[Net Amount]],Table1[[#This Row],[Net Amount]]) -> -27881792
A100: 45885 | B100: ="TX"&TEXT(ROW()-1,"0000") -> TX0099 | C100: ADRO | D100: Sell | E100: 8 | F100: {=_xlfn.IFS(Table1[[#This Row],[Action]]="Buy",Table1[[#This Row],[Lot ]],Table1[[#This Row],[Action]]="Sell",-Table1[[#This Row],[Lot ]],Table1[[#This Row],[Action]]="Dividend",0,TRUE,"")} -> -8 | G100: 3460 | H100: {=IF(OR(Table1[[#This Row],[Stock Tickers]]="",Table1[[#This Row],[Action]]="Dividend"), "",IF(Table1[[#This Row],[Action]]="Buy",(SUMIFS($L$2:L100, $C$2:C100,Table1[[#This Row],[Stock Tickers]], $D$2:D100, "Buy") + Table1[[#This Row],[Amount]]) / ((SUMIFS($E$2:E100, $C$2:C100,Table1[[#This Row],[Stock Tickers]], $D$2:D100, "Buy") + Table1[[#This Row],[Lot ]])*100),LOOKUP(2, 1/($C$2:C100=Table1[[#This Row],[Stock Tickers]]), $G$2:G100)))} -> 3460 | J100: =(Table1[[#This Row],[Lot ]]*100)*IF(Table1[[#This Row],[Action]]="Dividend",Table1[[#This Row],[Dividend per Share]],Table1[[#This Row],[Price]]) -> 2768000 | K100: =(exchange_fee+broker_fee)*J100 -> 5350.544 | L100: =SUM(Table1[[#This Row],[Amount]]:Table1[[#This Row],[Total Fee]]) -> 2773350.5 | M100: =IF(OR(Table1[[#This Row],[Action]]="Buy",Table1[[#This Row],[Action]]="Withdraw"),-Table1[[#This Row],[Net Amount]],Table1[[#This Row],[Net Amount]]) -> 2773350.5
...

Sheet Simulation
A1: Stock Ticker | B1: Growth Percentage | C1: 2027 | D1: 2028 | E1: 2029 | F1: 2030 | G1: 2031 | H1: 2032 | I1: 2033 | J1: 2034 | K1: 2035 | L1: 2036
A2: ='Database '!$A$11 -> ADRO | B2: ='Database '!B28 -> 0.06 | C2: =SUMIF('Database '!$A$11:$A$22,A2,'Database '!$G$11:$G$22)*(1+Table2[[#This Row],[Growth Percentage]])^(Table2[[#Headers],[2027]]-YEAR(TODAY())) -> 65010142 | D2: =SUMIF('Database '!$A$11:$A$22,A2,'Database '!$G$11:$G$22)*(1+Table2[[#This Row],[Growth Percentage]])^(Table2[[#Headers],[2028]]-YEAR(TODAY())) -> 68910751 | E2: =SUMIF('Database '!$A$11:$A$22,A2,'Database '!$G$11:$G$22)*(1+Table2[[#This Row],[Growth Percentage]])^(Table2[[#Headers],[2029]]-YEAR(TODAY())) -> 73045396 | F2: =SUMIF('Database '!$A$11:$A$22,A2,'Database '!$G$11:$G$22)*(1+Table2[[#This Row],[Growth Percentage]])^(Table2[[#Headers],[2030]]-YEAR(TODAY())) -> 77428119 | G2: =SUMIF('Database '!$A$11:$A$22,A2,'Database '!$G$11:$G$22)*(1+Table2[[#This Row],[Growth Percentage]])^(Table2[[#Headers],[2031]]-YEAR(TODAY())) -> 82073807 | H2: =SUMIF('Database '!$A$11:$A$22,A2,'Database '!$G$11:$G$22)*(1+Table2[[#This Row],[Growth Percentage]])^(Table2[[#Headers],[2032]]-YEAR(TODAY())) -> 86998235 | I2: =SUMIF('Database '!$A$11:$A$22,A2,'Database '!$G$11:$G$22)*(1+Table2[[#This Row],[Growth Percentage]])^(Table2[[#Headers],[2033]]-YEAR(TODAY())) -> 92218129 | J2: =SUMIF('Database '!$A$11:$A$22,A2,'Database '!$G$11:$G$22)*(1+Table2[[#This Row],[Growth Percentage]])^(Table2[[#Headers],[2034]]-YEAR(TODAY())) -> 97751217 | K2: =SUMIF('Database '!$A$11:$A$22,A2,'Database '!$G$11:$G$22)*(1+Table2[[#This Row],[Growth Percentage]])^(Table2[[#Headers],[2035]]-YEAR(TODAY())) -> 1.0361629e+08 | L2: =SUMIF('Database '!$A$11:$A$22,A2,'Database '!$G$11:$G$22)*(1+Table2[[#This Row],[Growth Percentage]])^(Table2[[#Headers],[2036]]-YEAR(TODAY())) -> 1.0983327e+08
A3: ='Database '!$A$11 -> ADRO | B3: ='Database '!C28 -> 0.07 | C3: =SUMIF('Database '!$A$11:$A$22,A3,'Database '!$G$11:$G$22)*(1+Table2[[#This Row],[Growth Percentage]])^(Table2[[#Headers],[2027]]-YEAR(TODAY())) -> 65623445 | D3: =SUMIF('Database '!$A$11:$A$22,A3,'Database '!$G$11:$G$22)*(1+Table2[[#This Row],[Growth Percentage]])^(Table2[[#Headers],[2028]]-YEAR(TODAY())) -> 70217087 | E3: =SUMIF('Database '!$A$11:$A$22,A3,'Database '!$G$11:$G$22)*(1+Table2[[#This Row],[Growth Percentage]])^(Table2[[#Headers],[2029]]-YEAR(TODAY())) -> 75132283 | F3: =SUMIF('Database '!$A$11:$A$22,A3,'Database '!$G$11:$G$22)*(1+Table2[[#This Row],[Growth Percentage]])^(Table2[[#Headers],[2030]]-YEAR(TODAY())) -> 80391542 | G3: =SUMIF('Database '!$A$11:$A$22,A3,'Database '!$G$11:$G$22)*(1+Table2[[#This Row],[Growth Percentage]])^(Table2[[#Headers],[2031]]-YEAR(TODAY())) -> 86018950 | H3: =SUMIF('Database '!$A$11:$A$22,A3,'Database '!$G$11:$G$22)*(1+Table2[[#This Row],[Growth Percentage]])^(Table2[[#Headers],[2032]]-YEAR(TODAY())) -> 92040277 | I3: =SUMIF('Database '!$A$11:$A$22,A3,'Database '!$G$11:$G$22)*(1+Table2[[#This Row],[Growth Percentage]])^(Table2[[#Headers],[2033]]-YEAR(TODAY())) -> 98483096 | J3: =SUMIF('Database '!$A$11:$A$22,A3,'Database '!$G$11:$G$22)*(1+Table2[[#This Row],[Growth Percentage]])^(Table2[[#Headers],[2034]]-YEAR(TODAY())) -> 1.0537691e+08 | K3: =SUMIF('Database '!$A$11:$A$22,A3,'Database '!$G$11:$G$22)*(1+Table2[[#This Row],[Growth Percentage]])^(Table2[[#Headers],[2035]]-YEAR(TODAY())) -> 1.127533e+08 | L3: =SUMIF('Database '!$A$11:$A$22,A3,'Database '!$G$11:$G$22)*(1+Table2[[#This Row],[Growth Percentage]])^(Table2[[#Headers],[2036]]-YEAR(TODAY())) -> 1.2064603e+08
A4: ='Database '!$A$11 -> ADRO | B4: ='Database '!D28 -> 0.08 | C4: =SUMIF('Database '!$A$11:$A$22,A4,'Database '!$G$11:$G$22)*(1+Table2[[#This Row],[Growth Percentage]])^(Table2[[#Headers],[2027]]-YEAR(TODAY())) -> 66236749 | D4: =SUMIF('Database '!$A$11:$A$22,A4,'Database '!$G$11:$G$22)*(1+Table2[[#This Row],[Growth Percentage]])^(Table2[[#Headers],[2028]]-YEAR(TODAY())) -> 71535689 | E4: =SUMIF('Database '!$A$11:$A$22,A4,'Database '!$G$11:$G$22)*(1+Table2[[#This Row],[Growth Percentage]])^(Table2[[#Headers],[2029]]-YEAR(TODAY())) -> 77258544 | F4: =SUMIF('Database '!$A$11:$A$22,A4,'Database '!$G$11:$G$22)*(1+Table2[[#This Row],[Growth Percentage]])^(Table2[[#Headers],[2030]]-YEAR(TODAY())) -> 83439227 | G4: =SUMIF('Database '!$A$11:$A$22,A4,'Database '!$G$11:$G$22)*(1+Table2[[#This Row],[Growth Percentage]])^(Table2[[#Headers],[2031]]-YEAR(TODAY())) -> 90114365 | H4: =SUMIF('Database '!$A$11:$A$22,A4,'Database '!$G$11:$G$22)*(1+Table2[[#This Row],[Growth Percentage]])^(Table2[[#Headers],[2032]]-YEAR(TODAY())) -> 97323514 | I4: =SUMIF('Database '!$A$11:$A$22,A4,'Database '!$G$11:$G$22)*(1+Table2[[#This Row],[Growth Percentage]])^(Table2[[#Headers],[2033]]-YEAR(TODAY())) -> 1.051094e+08 | J4: =SUMIF('Database '!$A$11:$A$22,A4,'Database '!$G$11:$G$22)*(1+Table2[[#This Row],[Growth Percentage]])^(Table2[[#Headers],[2034]]-YEAR(TODAY())) -> 1.1351815e+08 | K4: =SUMIF('Database '!$A$11:$A$22,A4,'Database '!$G$11:$G$22)*(1+Table2[[#This Row],[Growth Percentage]])^(Table2[[#Headers],[2035]]-YEAR(TODAY())) -> 1.225996e+08 | L4: =SUMIF('Database '!$A$11:$A$22,A4,'Database '!$G$11:$G$22)*(1+Table2[[#This Row],[Growth Percentage]])^(Table2[[#Headers],[2036]]-YEAR(TODAY())) -> 1.3240757e+08
A5: ='Database '!$A$11 -> ADRO | B5: ='Database '!E28 -> 0.09 | C5: =SUMIF('Database '!$A$11:$A$22,A5,'Database '!$G$11:$G$22)*(1+Table2[[#This Row],[Growth Percentage]])^(Table2[[#Headers],[2027]]-YEAR(TODAY())) -> 66850052 | D5: =SUMIF('Database '!$A$11:$A$22,A5,'Database '!$G$11:$G$22)*(1+Table2[[#This Row],[Growth Percentage]])^(Table2[[#Headers],[2028]]-YEAR(TODAY())) -> 72866557 | E5: =SUMIF('Database '!$A$11:$A$22,A5,'Database '!$G$11:$G$22)*(1+Table2[[#This Row],[Growth Percentage]])^(Table2[[#Headers],[2029]]-YEAR(TODAY())) -> 79424547 | F5: =SUMIF('Database '!$A$11:$A$22,A5,'Database '!$G$11:$G$22)*(1+Table2[[#This Row],[Growth Percentage]])^(Table2[[#Headers],[2030]]-YEAR(TODAY())) -> 86572756 | G5: =SUMIF('Database '!$A$11:$A$22,A5,'Database '!$G$11:$G$22)*(1+Table2[[#This Row],[Growth Percentage]])^(Table2[[#Headers],[2031]]-YEAR(TODAY())) -> 94364304 | H5: =SUMIF('Database '!$A$11:$A$22,A5,'Database '!$G$11:$G$22)*(1+Table2[[#This Row],[Growth Percentage]])^(Table2[[#Headers],[2032]]-YEAR(TODAY())) -> 1.0285709e+08 | I5: =SUMIF('Database '!$A$11:$A$22,A5,'Database '!$G$11:$G$22)*(1+Table2[[#This Row],[Growth Percentage]])^(Table2[[#Headers],[2033]]-YEAR(TODAY())) -> 1.1211423e+08 | J5: =SUMIF('Database '!$A$11:$A$22,A5,'Database '!$G$11:$G$22)*(1+Table2[[#This Row],[Growth Percentage]])^(Table2[[#Headers],[2034]]-YEAR(TODAY())) -> 1.2220451e+08 | K5: =SUMIF('Database '!$A$11:$A$22,A5,'Database '!$G$11:$G$22)*(1+Table2[[#This Row],[Growth Percentage]])^(Table2[[#Headers],[2035]]-YEAR(TODAY())) -> 1.3320292e+08 | L5: =SUMIF('Database '!$A$11:$A$22,A5,'Database '!$G$11:$G$22)*(1+Table2[[#This Row],[Growth Percentage]])^(Table2[[#Headers],[2036]]-YEAR(TODAY())) -> 1.4519118e+08
A6: ='Database '!$A$11 -> ADRO | B6: ='Database '!F28 -> 0.095 | C6: =SUMIF('Database '!$A$11:$A$22,A6,'Database '!$G$11:$G$22)*(1+Table2[[#This Row],[Growth Percentage]])^(Table2[[#Headers],[2027]]-YEAR(TODAY())) -> 67156703 | D6: =SUMIF('Database '!$A$11:$A$22,A6,'Database '!$G$11:$G$22)*(1+Table2[[#This Row],[Growth Percentage]])^(Table2[[#Headers],[2028]]-YEAR(TODAY())) -> 73536590 | E6: =SUMIF('Database '!$A$11:$A$22,A6,'Database '!$G$11:$G$22)*(1+Table2[[#This Row],[Growth Percentage]])^(Table2[[#Headers],[2029]]-YEAR(TODAY())) -> 80522566 | F6: =SUMIF('Database '!$A$11:$A$22,A6,'Database '!$G$11:$G$22)*(1+Table2[[#This Row],[Growth Percentage]])^(Table2[[#Headers],[2030]]-YEAR(TODAY())) -> 88172210 | G6: =SUMIF('Database '!$A$11:$A$22,A6,'Database '!$G$11:$G$22)*(1+Table2[[#This Row],[Growth Percentage]])^(Table2[[#Headers],[2031]]-YEAR(TODAY())) -> 96548570 | H6: =SUMIF('Database '!$A$11:$A$22,A6,'Database '!$G$11:$G$22)*(1+Table2[[#This Row],[Growth Percentage]])^(Table2[[#Headers],[2032]]-YEAR(TODAY())) -> 1.0572068e+08 | I6: =SUMIF('Database '!$A$11:$A$22,A6,'Database '!$G$11:$G$22)*(1+Table2[[#This Row],[Growth Percentage]])^(Table2[[#Headers],[2033]]-YEAR(TODAY())) -> 1.1576415e+08 | J6: =SUMIF('Database '!$A$11:$A$22,A6,'Database '!$G$11:$G$22)*(1+Table2[[#This Row],[Growth Percentage]])^(Table2[[#Headers],[2034]]-YEAR(TODAY())) -> 1.2676174e+08 | K6: =SUMIF('Database '!$A$11:$A$22,A6,'Database '!$G$11:$G$22)*(1+Table2[[#This Row],[Growth Percentage]])^(Table2[[#Headers],[2035]]-YEAR(TODAY())) -> 1.3880411e+08 | L6: =SUMIF('Database '!$A$11:$A$22,A6,'Database '!$G$11:$G$22)*(1+Table2[[#This Row],[Growth Percentage]])^(Table2[[#Headers],[2036]]-YEAR(TODAY())) -> 1.519905e+08
A7: ='Database '!$A$11 -> ADRO | B7: ='Database '!G28 -> 0.1 | C7: =SUMIF('Database '!$A$11:$A$22,A7,'Database '!$G$11:$G$22)*(1+Table2[[#This Row],[Growth Percentage]])^(Table2[[#Headers],[2027]]-YEAR(TODAY())) -> 67463355 | D7: =SUMIF('Database '!$A$11:$A$22,A7,'Database '!$G$11:$G$22)*(1+Table2[[#This Row],[Growth Percentage]])^(Table2[[#Headers],[2028]]-YEAR(TODAY())) -> 74209691 | E7: =SUMIF('Database '!$A$11:$A$22,A7,'Database '!$G$11:$G$22)*(1+Table2[[#This Row],[Growth Percentage]])^(Table2[[#Headers],[2029]]-YEAR(TODAY())) -> 81630660 | F7: =SUMIF('Database '!$A$11:$A$22,A7,'Database '!$G$11:$G$22)*(1+Table2[[#This Row],[Growth Percentage]])^(Table2[[#Headers],[2030]]-YEAR(TODAY())) -> 89793726 | G7: =SUMIF('Database '!$A$11:$A$22,A7,'Database '!$G$11:$G$22)*(1+Table2[[#This Row],[Growth Percentage]])^(Table2[[#Headers],[2031]]-YEAR(TODAY())) -> 98773098 | H7: =SUMIF('Database '!$A$11:$A$22,A7,'Database '!$G$11:$G$22)*(1+Table2[[#This Row],[Growth Percentage]])^(Table2[[#Headers],[2032]]-YEAR(TODAY())) -> 1.0865041e+08 | I7: =SUMIF('Database '!$A$11:$A$22,A7,'Database '!$G$11:$G$22)*(1+Table2[[#This Row],[Growth Percentage]])^(Table2[[#Headers],[2033]]-YEAR(TODAY())) -> 1.1951545e+08 | J7: =SUMIF('Database '!$A$11:$A$22,A7,'Database '!$G$11:$G$22)*(1+Table2[[#This Row],[Growth Percentage]])^(Table2[[#Headers],[2034]]-YEAR(TODAY())) -> 1.3146699e+08 | K7: =SUMIF('Database '!$A$11:$A$22,A7,'Database '!$G$11:$G$22)*(1+Table2[[#This Row],[Growth Percentage]])^(Table2[[#Headers],[2035]]-YEAR(TODAY())) -> 1.4461369e+08 | L7: =SUMIF('Database '!$A$11:$A$22,A7,'Database '!$G$11:$G$22)*(1+Table2[[#This Row],[Growth Percentage]])^(Table2[[#Headers],[2036]]-YEAR(TODAY())) -> 1.5907506e+08
A8: ='Database '!$A$11 -> ADRO | B8: ='Database '!H28 -> 0.11 | C8: =SUMIF('Database '!$A$11:$A$22,A8,'Database '!$G$11:$G$22)*(1+Table2[[#This Row],[Growth Percentage]])^(Table2[[#Headers],[2027]]-YEAR(TODAY())) -> 68076658 | D8: =SUMIF('Database '!$A$11:$A$22,A8,'Database '!$G$11:$G$22)*(1+Table2[[#This Row],[Growth Percentage]])^(Table2[[#Headers],[2028]]-YEAR(TODAY())) -> 75565091 | E8: =SUMIF('Database '!$A$11:$A$22,A8,'Database '!$G$11:$G$22)*(1+Table2[[#This Row],[Growth Percentage]])^(Table2[[#Headers],[2029]]-YEAR(TODAY())) -> 83877251 | F8: =SUMIF('Database '!$A$11:$A$22,A8,'Database '!$G$11:$G$22)*(1+Table2[[#This Row],[Growth Percentage]])^(Table2[[#Headers],[2030]]-YEAR(TODAY())) -> 93103748 | G8: =SUMIF('Database '!$A$11:$A$22,A8,'Database '!$G$11:$G$22)*(1+Table2[[#This Row],[Growth Percentage]])^(Table2[[#Headers],[2031]]-YEAR(TODAY())) -> 1.0334516e+08 | H8: =SUMIF('Database '!$A$11:$A$22,A8,'Database '!$G$11:$G$22)*(1+Table2[[#This Row],[Growth Percentage]])^(Table2[[#Headers],[2032]]-YEAR(TODAY())) -> 1.1471313e+08 | I8: =SUMIF('Database '!$A$11:$A$22,A8,'Database '!$G$11:$G$22)*(1+Table2[[#This Row],[Growth Percentage]])^(Table2[[#Headers],[2033]]-YEAR(TODAY())) -> 1.2733157e+08 | J8: =SUMIF('Database '!$A$11:$A$22,A8,'Database '!$G$11:$G$22)*(1+Table2[[#This Row],[Growth Percentage]])^(Table2[[#Headers],[2034]]-YEAR(TODAY())) -> 1.4133805e+08 | K8: =SUMIF('Database '!$A$11:$A$22,A8,'Database '!$G$11:$G$22)*(1+Table2[[#This Row],[Growth Percentage]])^(Table2[[#Headers],[2035]]-YEAR(TODAY())) -> 1.5688523e+08 | L8: =SUMIF('Database '!$A$11:$A$22,A8,'Database '!$G$11:$G$22)*(1+Table2[[#This Row],[Growth Percentage]])^(Table2[[#Headers],[2036]]-YEAR(TODAY())) -> 1.7414261e+08
A9: ='Database '!$A$11 -> ADRO | B9: ='Database '!I28 -> 0.12 | C9: =SUMIF('Database '!$A$11:$A$22,A9,'Database '!$G$11:$G$22)*(1+Table2[[#This Row],[Growth Percentage]])^(Table2[[#Headers],[2027]]-YEAR(TODAY())) -> 68689962 | D9: =SUMIF('Database '!$A$11:$A$22,A9,'Database '!$G$11:$G$22)*(1+Table2[[#This Row],[Growth Percentage]])^(Table2[[#Headers],[2028]]-YEAR(TODAY())) -> 76932757 | E9: =SUMIF('Database '!$A$11:$A$22,A9,'Database '!$G$11:$G$22)*(1+Table2[[#This Row],[Growth Percentage]])^(Table2[[#Headers],[2029]]-YEAR(TODAY())) -> 86164688 | F9: =SUMIF('Database '!$A$11:$A$22,A9,'Database '!$G$11:$G$22)*(1+Table2[[#This Row],[Growth Percentage]])^(Table2[[#Headers],[2030]]-YEAR(TODAY())) -> 96504450 | G9: =SUMIF('Database '!$A$11:$A$22,A9,'Database '!$G$11:$G$22)*(1+Table2[[#This Row],[Growth Percentage]])^(Table2[[#Headers],[2031]]-YEAR(TODAY())) -> 1.0808498e+08 | H9: =SUMIF('Database '!$A$11:$A$22,A9,'Database '!$G$11:$G$22)*(1+Table2[[#This Row],[Growth Percentage]])^(Table2[[#Headers],[2032]]-YEAR(TODAY())) -> 1.2105518e+08 | I9: =SUMIF('Database '!$A$11:$A$22,A9,'Database '!$G$11:$G$22)*(1+Table2[[#This Row],[Growth Percentage]])^(Table2[[#Headers],[2033]]-YEAR(TODAY())) -> 1.355818e+08 | J9: =SUMIF('Database '!$A$11:$A$22,A9,'Database '!$G$11:$G$22)*(1+Table2[[#This Row],[Growth Percentage]])^(Table2[[#Headers],[2034]]-YEAR(TODAY())) -> 1.5185162e+08 | K9: =SUMIF('Database '!$A$11:$A$22,A9,'Database '!$G$11:$G$22)*(1+Table2[[#This Row],[Growth Percentage]])^(Table2[[#Headers],[2035]]-YEAR(TODAY())) -> 1.7007382e+08 | L9: =SUMIF('Database '!$A$11:$A$22,A9,'Database '!$G$11:$G$22)*(1+Table2[[#This Row],[Growth Percentage]])^(Table2[[#Headers],[2036]]-YEAR(TODAY())) -> 1.9048267e+08
A10: ='Database '!$A$12 -> ASII | B10: ='Database '!B28 -> 0.06 | C10: =SUMIF('Database '!$A$11:$A$22,A10,'Database '!$G$11:$G$22)*(1+Table2[[#This Row],[Growth Percentage]])^(Table2[[#Headers],[2027]]-YEAR(TODAY())) -> 97053222 | D10: =SUMIF('Database '!$A$11:$A$22,A10,'Database '!$G$11:$G$22)*(1+Table2[[#This Row],[Growth Percentage]])^(Table2[[#Headers],[2028]]-YEAR(TODAY())) -> 1.0287642e+08 | E10: =SUMIF('Database '!$A$11:$A$22,A10,'Database '!$G$11:$G$22)*(1+Table2[[#This Row],[Growth Percentage]])^(Table2[[#Headers],[2029]]-YEAR(TODAY())) -> 1.09049e+08 | F10: =SUMIF('Database '!$A$11:$A$22,A10,'Database '!$G$11:$G$22)*(1+Table2[[#This Row],[Growth Percentage]])^(Table2[[#Headers],[2030]]-YEAR(TODAY())) -> 1.1559194e+08 | G10: =SUMIF('Database '!$A$11:$A$22,A10,'Database '!$G$11:$G$22)*(1+Table2[[#This Row],[Growth Percentage]])^(Table2[[#Headers],[2031]]-YEAR(TODAY())) -> 1.2252746e+08 | H10: =SUMIF('Database '!$A$11:$A$22,A10,'Database '!$G$11:$G$22)*(1+Table2[[#This Row],[Growth Percentage]])^(Table2[[#Headers],[2032]]-YEAR(TODAY())) -> 1.298791e+08 | I10: =SUMIF('Database '!$A$11:$A$22,A10,'Database '!$G$11:$G$22)*(1+Table2[[#This Row],[Growth Percentage]])^(Table2[[#Headers],[2033]]-YEAR(TODAY())) -> 1.3767185e+08 | J10: =SUMIF('Database '!$A$11:$A$22,A10,'Database '!$G$11:$G$22)*(1+Table2[[#This Row],[Growth Percentage]])^(Table2[[#Headers],[2034]]-YEAR(TODAY())) -> 1.4593216e+08 | K10: =SUMIF('Database '!$A$11:$A$22,A10,'Database '!$G$11:$G$22)*(1+Table2[[#This Row],[Growth Percentage]])^(Table2[[#Headers],[2035]]-YEAR(TODAY())) -> 1.5468809e+08 | L10: =SUMIF('Database '!$A$11:$A$22,A10,'Database '!$G$11:$G$22)*(1+Table2[[#This Row],[Growth Percentage]])^(Table2[[#Headers],[2036]]-YEAR(TODAY())) -> 1.6396938e+08
A11: ='Database '!$A$12 -> ASII | B11: ='Database '!C28 -> 0.07 | C11: =SUMIF('Database '!$A$11:$A$22,A11,'Database '!$G$11:$G$22)*(1+Table2[[#This Row],[Growth Percentage]])^(Table2[[#Headers],[2027]]-YEAR(TODAY())) -> 97968818 | D11: =SUMIF('Database '!$A$11:$A$22,A11,'Database '!$G$11:$G$22)*(1+Table2[[#This Row],[Growth Percentage]])^(Table2[[#Headers],[2028]]-YEAR(TODAY())) -> 1.0482664e+08 | E11: =SUMIF('Database '!$A$11:$A$22,A11,'Database '!$G$11:$G$22)*(1+Table2[[#This Row],[Growth Percentage]])^(Table2[[#Headers],[2029]]-YEAR(TODAY())) -> 1.121645e+08 | F11: =SUMIF('Database '!$A$11:$A$22,A11,'Database '!$G$11:$G$22)*(1+Table2[[#This Row],[Growth Percentage]])^(Table2[[#Headers],[2030]]-YEAR(TODAY())) -> 1.2001602e+08 | G11: =SUMIF('Database '!$A$11:$A$22,A11,'Database '!$G$11:$G$22)*(1+Table2[[#This Row],[Growth Percentage]])^(Table2[[#Headers],[2031]]-YEAR(TODAY())) -> 1.2841714e+08 | H11: =SUMIF('Database '!$A$11:$A$22,A11,'Database '!$G$11:$G$22)*(1+Table2[[#This Row],[Growth Percentage]])^(Table2[[#Headers],[2032]]-YEAR(TODAY())) -> 1.3740634e+08 | I11: =SUMIF('Database '!$A$11:$A$22,A11,'Database '!$G$11:$G$22)*(1+Table2[[#This Row],[Growth Percentage]])^(Table2[[#Headers],[2033]]-YEAR(TODAY())) -> 1.4702478e+08 | J11: =SUMIF('Database '!$A$11:$A$22,A11,'Database '!$G$11:$G$22)*(1+Table2[[#This Row],[Growth Percentage]])^(Table2[[#Headers],[2034]]-YEAR(TODAY())) -> 1.5731651e+08 | K11: =SUMIF('Database '!$A$11:$A$22,A11,'Database '!$G$11:$G$22)*(1+Table2[[#This Row],[Growth Percentage]])^(Table2[[#Headers],[2035]]-YEAR(TODAY())) -> 1.6832867e+08 | L11: =SUMIF('Database '!$A$11:$A$22,A11,'Database '!$G$11:$G$22)*(1+Table2[[#This Row],[Growth Percentage]])^(Table2[[#Headers],[2036]]-YEAR(TODAY())) -> 1.8011168e+08
A12: ='Database '!$A$12 -> ASII | B12: ='Database '!D28 -> 0.08 | C12: =SUMIF('Database '!$A$11:$A$22,A12,'Database '!$G$11:$G$22)*(1+Table2[[#This Row],[Growth Percentage]])^(Table2[[#Headers],[2027]]-YEAR(TODAY())) -> 98884415 | D12: =SUMIF('Database '!$A$11:$A$22,A12,'Database '!$G$11:$G$22)*(1+Table2[[#This Row],[Growth Percentage]])^(Table2[[#Headers],[2028]]-YEAR(TODAY())) -> 1.0679517e+08 | E12: =SUMIF('Database '!$A$11:$A$22,A12,'Database '!$G$11:$G$22)*(1+Table2[[#This Row],[Growth Percentage]])^(Table2[[#Headers],[2029]]-YEAR(TODAY())) -> 1.1533878e+08 | F12: =SUMIF('Database '!$A$11:$A$22,A12,'Database '!$G$11:$G$22)*(1+Table2[[#This Row],[Growth Percentage]])^(Table2[[#Headers],[2030]]-YEAR(TODAY())) -> 1.2456588e+08 | G12: =SUMIF('Database '!$A$11:$A$22,A12,'Database '!$G$11:$G$22)*(1+Table2[[#This Row],[Growth Percentage]])^(Table2[[#Headers],[2031]]-YEAR(TODAY())) -> 1.3453115e+08 | H12: =SUMIF('Database '!$A$11:$A$22,A12,'Database '!$G$11:$G$22)*(1+Table2[[#This Row],[Growth Percentage]])^(Table2[[#Headers],[2032]]-YEAR(TODAY())) -> 1.4529365e+08 | I12: =SUMIF('Database '!$A$11:$A$22,A12,'Database '!$G$11:$G$22)*(1+Table2[[#This Row],[Growth Percentage]])^(Table2[[#Headers],[2033]]-YEAR(TODAY())) -> 1.5691714e+08 | J12: =SUMIF('Database '!$A$11:$A$22,A12,'Database '!$G$11:$G$22)*(1+Table2[[#This Row],[Growth Percentage]])^(Table2[[#Headers],[2034]]-YEAR(TODAY())) -> 1.6947051e+08 | K12: =SUMIF('Database '!$A$11:$A$22,A12,'Database '!$G$11:$G$22)*(1+Table2[[#This Row],[Growth Percentage]])^(Table2[[#Headers],[2035]]-YEAR(TODAY())) -> 1.8302815e+08 | L12: =SUMIF('Database '!$A$11:$A$22,A12,'Database '!$G$11:$G$22)*(1+Table2[[#This Row],[Growth Percentage]])^(Table2[[#Headers],[2036]]-YEAR(TODAY())) -> 1.976704e+08
A13: ='Database '!$A$12 -> ASII | B13: ='Database '!E28 -> 0.09 | C13: =SUMIF('Database '!$A$11:$A$22,A13,'Database '!$G$11:$G$22)*(1+Table2[[#This Row],[Growth Percentage]])^(Table2[[#Headers],[2027]]-YEAR(TODAY())) -> 99800011 | D13: =SUMIF('Database '!$A$11:$A$22,A13,'Database '!$G$11:$G$22)*(1+Table2[[#This Row],[Growth Percentage]])^(Table2[[#Headers],[2028]]-YEAR(TODAY())) -> 1.0878201e+08 | E13: =SUMIF('Database '!$A$11:$A$22,A13,'Database '!$G$11:$G$22)*(1+Table2[[#This Row],[Growth Percentage]])^(Table2[[#Headers],[2029]]-YEAR(TODAY())) -> 1.1857239e+08 | F13: =SUMIF('Database '!$A$11:$A$22,A13,'Database '!$G$11:$G$22)*(1+Table2[[#This Row],[Growth Percentage]])^(Table2[[#Headers],[2030]]-YEAR(TODAY())) -> 1.2924391e+08 | G13: =SUMIF('Database '!$A$11:$A$22,A13,'Database '!$G$11:$G$22)*(1+Table2[[#This Row],[Growth Percentage]])^(Table2[[#Headers],[2031]]-YEAR(TODAY())) -> 1.4087586e+08 | H13: =SUMIF('Database '!$A$11:$A$22,A13,'Database '!$G$11:$G$22)*(1+Table2[[#This Row],[Growth Percentage]])^(Table2[[#Headers],[2032]]-YEAR(TODAY())) -> 1.5355469e+08 | I13: =SUMIF('Database '!$A$11:$A$22,A13,'Database '!$G$11:$G$22)*(1+Table2[[#This Row],[Growth Percentage]])^(Table2[[#Headers],[2033]]-YEAR(TODAY())) -> 1.6737461e+08 | J13: =SUMIF('Database '!$A$11:$A$22,A13,'Database '!$G$11:$G$22)*(1+Table2[[#This Row],[Growth Percentage]])^(Table2[[#Headers],[2034]]-YEAR(TODAY())) -> 1.8243832e+08 | K13: =SUMIF('Database '!$A$11:$A$22,A13,'Database '!$G$11:$G$22)*(1+Table2[[#This Row],[Growth Percentage]])^(Table2[[#Headers],[2035]]-YEAR(TODAY())) -> 1.9885777e+08 | L13: =SUMIF('Database '!$A$11:$A$22,A13,'Database '!$G$11:$G$22)*(1+Table2[[#This Row],[Growth Percentage]])^(Table2[[#Headers],[2036]]-YEAR(TODAY())) -> 2.1675497e+08
A14: ='Database '!$A$12 -> ASII | B14: ='Database '!F28 -> 0.095 | C14: =SUMIF('Database '!$A$11:$A$22,A14,'Database '!$G$11:$G$22)*(1+Table2[[#This Row],[Growth Percentage]])^(Table2[[#Headers],[2027]]-YEAR(TODAY())) -> 1.0025781e+08 | D14: =SUMIF('Database '!$A$11:$A$22,A14,'Database '!$G$11:$G$22)*(1+Table2[[#This Row],[Growth Percentage]])^(Table2[[#Headers],[2028]]-YEAR(TODAY())) -> 1.097823e+08 | E14: =SUMIF('Database '!$A$11:$A$22,A14,'Database '!$G$11:$G$22)*(1+Table2[[#This Row],[Growth Percentage]])^(Table2[[#Headers],[2029]]-YEAR(TODAY())) -> 1.2021162e+08 | F14: =SUMIF('Database '!$A$11:$A$22,A14,'Database '!$G$11:$G$22)*(1+Table2[[#This Row],[Growth Percentage]])^(Table2[[#Headers],[2030]]-YEAR(TODAY())) -> 1.3163172e+08 | G14: =SUMIF('Database '!$A$11:$A$22,A14,'Database '!$G$11:$G$22)*(1+Table2[[#This Row],[Growth Percentage]])^(Table2[[#Headers],[2031]]-YEAR(TODAY())) -> 1.4413674e+08 | H14: =SUMIF('Database '!$A$11:$A$22,A14,'Database '!$G$11:$G$22)*(1+Table2[[#This Row],[Growth Percentage]])^(Table2[[#Headers],[2032]]-YEAR(TODAY())) -> 1.5782973e+08 | I14: =SUMIF('Database '!$A$11:$A$22,A14,'Database '!$G$11:$G$22)*(1+Table2[[#This Row],[Growth Percentage]])^(Table2[[#Headers],[2033]]-YEAR(TODAY())) -> 1.7282355e+08 | J14: =SUMIF('Database '!$A$11:$A$22,A14,'Database '!$G$11:$G$22)*(1+Table2[[#This Row],[Growth Percentage]])^(Table2[[#Headers],[2034]]-YEAR(TODAY())) -> 1.8924179e+08 | K14: =SUMIF('Database '!$A$11:$A$22,A14,'Database '!$G$11:$G$22)*(1+Table2[[#This Row],[Growth Percentage]])^(Table2[[#Headers],[2035]]-YEAR(TODAY())) -> 2.0721976e+08 | L14: =SUMIF('Database '!$A$11:$A$22,A14,'Database '!$G$11:$G$22)*(1+Table2[[#This Row],[Growth Percentage]])^(Table2[[#Headers],[2036]]-YEAR(TODAY())) -> 2.2690564e+08
A15: ='Database '!$A$12 -> ASII | B15: ='Database '!G28 -> 0.1 | C15: =SUMIF('Database '!$A$11:$A$22,A15,'Database '!$G$11:$G$22)*(1+Table2[[#This Row],[Growth Percentage]])^(Table2[[#Headers],[2027]]-YEAR(TODAY())) -> 1.0071561e+08 | D15: =SUMIF('Database '!$A$11:$A$22,A15,'Database '!$G$11:$G$22)*(1+Table2[[#This Row],[Growth Percentage]])^(Table2[[#Headers],[2028]]-YEAR(TODAY())) -> 1.1078717e+08 | E15: =SUMIF('Database '!$A$11:$A$22,A15,'Database '!$G$11:$G$22)*(1+Table2[[#This Row],[Growth Percentage]])^(Table2[[#Headers],[2029]]-YEAR(TODAY())) -> 1.2186589e+08 | F15: =SUMIF('Database '!$A$11:$A$22,A15,'Database '!$G$11:$G$22)*(1+Table2[[#This Row],[Growth Percentage]])^(Table2[[#Headers],[2030]]-YEAR(TODAY())) -> 1.3405247e+08 | G15: =SUMIF('Database '!$A$11:$A$22,A15,'Database '!$G$11:$G$22)*(1+Table2[[#This Row],[Growth Percentage]])^(Table2[[#Headers],[2031]]-YEAR(TODAY())) -> 1.4745772e+08 | H15: =SUMIF('Database '!$A$11:$A$22,A15,'Database '!$G$11:$G$22)*(1+Table2[[#This Row],[Growth Percentage]])^(Table2[[#Headers],[2032]]-YEAR(TODAY())) -> 1.6220349e+08 | I15: =SUMIF('Database '!$A$11:$A$22,A15,'Database '!$G$11:$G$22)*(1+Table2[[#This Row],[Growth Percentage]])^(Table2[[#Headers],[2033]]-YEAR(TODAY())) -> 1.7842384e+08 | J15: =SUMIF('Database '!$A$11:$A$22,A15,'Database '!$G$11:$G$22)*(1+Table2[[#This Row],[Growth Percentage]])^(Table2[[#Headers],[2034]]-YEAR(TODAY())) -> 1.9626623e+08 | K15: =SUMIF('Database '!$A$11:$A$22,A15,'Database '!$G$11:$G$22)*(1+Table2[[#This Row],[Growth Percentage]])^(Table2[[#Headers],[2035]]-YEAR(TODAY())) -> 2.1589285e+08 | L15: =SUMIF('Database '!$A$11:$A$22,A15,'Database '!$G$11:$G$22)*(1+Table2[[#This Row],[Growth Percentage]])^(Table2[[#Headers],[2036]]-YEAR(TODAY())) -> 2.3748213e+08
A16: ='Database '!$A$12 -> ASII | B16: ='Database '!H28 -> 0.11 | C16: =SUMIF('Database '!$A$11:$A$22,A16,'Database '!$G$11:$G$22)*(1+Table2[[#This Row],[Growth Percentage]])^(Table2[[#Headers],[2027]]-YEAR(TODAY())) -> 1.016312e+08 | D16: =SUMIF('Database '!$A$11:$A$22,A16,'Database '!$G$11:$G$22)*(1+Table2[[#This Row],[Growth Percentage]])^(Table2[[#Headers],[2028]]-YEAR(TODAY())) -> 1.1281064e+08 | E16: =SUMIF('Database '!$A$11:$A$22,A16,'Database '!$G$11:$G$22)*(1+Table2[[#This Row],[Growth Percentage]])^(Table2[[#Headers],[2029]]-YEAR(TODAY())) -> 1.2521981e+08 | F16: =SUMIF('Database '!$A$11:$A$22,A16,'Database '!$G$11:$G$22)*(1+Table2[[#This Row],[Growth Percentage]])^(Table2[[#Headers],[2030]]-YEAR(TODAY())) -> 1.3899399e+08 | G16: =SUMIF('Database '!$A$11:$A$22,A16,'Database '!$G$11:$G$22)*(1+Table2[[#This Row],[Growth Percentage]])^(Table2[[#Headers],[2031]]-YEAR(TODAY())) -> 1.5428332e+08 | H16: =SUMIF('Database '!$A$11:$A$22,A16,'Database '!$G$11:$G$22)*(1+Table2[[#This Row],[Growth Percentage]])^(Table2[[#Headers],[2032]]-YEAR(TODAY())) -> 1.7125449e+08 | I16: =SUMIF('Database '!$A$11:$A$22,A16,'Database '!$G$11:$G$22)*(1+Table2[[#This Row],[Growth Percentage]])^(Table2[[#Headers],[2033]]-YEAR(TODAY())) -> 1.9009248e+08 | J16: =SUMIF('Database '!$A$11:$A$22,A16,'Database '!$G$11:$G$22)*(1+Table2[[#This Row],[Growth Percentage]])^(Table2[[#Headers],[2034]]-YEAR(TODAY())) -> 2.1100266e+08 | K16: =SUMIF('Database '!$A$11:$A$22,A16,'Database '!$G$11:$G$22)*(1+Table2[[#This Row],[Growth Percentage]])^(Table2[[#Headers],[2035]]-YEAR(TODAY())) -> 2.3421295e+08 | L16: =SUMIF('Database '!$A$11:$A$22,A16,'Database '!$G$11:$G$22)*(1+Table2[[#This Row],[Growth Percentage]])^(Table2[[#Headers],[2036]]-YEAR(TODAY())) -> 2.5997637e+08
A17: ='Database '!$A$12 -> ASII | B17: ='Database '!I28 -> 0.12 | C17: =SUMIF('Database '!$A$11:$A$22,A17,'Database '!$G$11:$G$22)*(1+Table2[[#This Row],[Growth Percentage]])^(Table2[[#Headers],[2027]]-YEAR(TODAY())) -> 1.025468e+08 | D17: =SUMIF('Database '!$A$11:$A$22,A17,'Database '!$G$11:$G$22)*(1+Table2[[#This Row],[Growth Percentage]])^(Table2[[#Headers],[2028]]-YEAR(TODAY())) -> 1.1485242e+08 | E17: =SUMIF('Database '!$A$11:$A$22,A17,'Database '!$G$11:$G$22)*(1+Table2[[#This Row],[Growth Percentage]])^(Table2[[#Headers],[2029]]-YEAR(TODAY())) -> 1.2863471e+08 | F17: =SUMIF('Database '!$A$11:$A$22,A17,'Database '!$G$11:$G$22)*(1+Table2[[#This Row],[Growth Percentage]])^(Table2[[#Headers],[2030]]-YEAR(TODAY())) -> 1.4407087e+08 | G17: =SUMIF('Database '!$A$11:$A$22,A17,'Database '!$G$11:$G$22)*(1+Table2[[#This Row],[Growth Percentage]])^(Table2[[#Headers],[2031]]-YEAR(TODAY())) -> 1.6135938e+08 | H17: =SUMIF('Database '!$A$11:$A$22,A17,'Database '!$G$11:$G$22)*(1+Table2[[#This Row],[Growth Percentage]])^(Table2[[#Headers],[2032]]-YEAR(TODAY())) -> 1.807225e+08 | I17: =SUMIF('Database '!$A$11:$A$22,A17,'Database '!$G$11:$G$22)*(1+Table2[[#This Row],[Growth Percentage]])^(Table2[[#Headers],[2033]]-YEAR(TODAY())) -> 2.024092e+08 | J17: =SUMIF('Database '!$A$11:$A$22,A17,'Database '!$G$11:$G$22)*(1+Table2[[#This Row],[Growth Percentage]])^(Table2[[#Headers],[2034]]-YEAR(TODAY())) -> 2.2669831e+08 | K17: =SUMIF('Database '!$A$11:$A$22,A17,'Database '!$G$11:$G$22)*(1+Table2[[#This Row],[Growth Percentage]])^(Table2[[#Headers],[2035]]-YEAR(TODAY())) -> 2.539021e+08 | L17: =SUMIF('Database '!$A$11:$A$22,A17,'Database '!$G$11:$G$22)*(1+Table2[[#This Row],[Growth Percentage]])^(Table2[[#Headers],[2036]]-YEAR(TODAY())) -> 2.8437035e+08
A18: ='Database '!$A$13 -> BBCA | B18: ='Database '!B28 -> 0.06 | C18: =SUMIF('Database '!$A$11:$A$22,A18,'Database '!$G$11:$G$22)*(1+Table2[[#This Row],[Growth Percentage]])^(Table2[[#Headers],[2027]]-YEAR(TODAY())) -> 1.3303119e+08 | D18: =SUMIF('Database '!$A$11:$A$22,A18,'Database '!$G$11:$G$22)*(1+Table2[[#This Row],[Growth Percentage]])^(Table2[[#Headers],[2028]]-YEAR(TODAY())) -> 1.4101306e+08 | E18: =SUMIF('Database '!$A$11:$A$22,A18,'Database '!$G$11:$G$22)*(1+Table2[[#This Row],[Growth Percentage]])^(Table2[[#Headers],[2029]]-YEAR(TODAY())) -> 1.4947385e+08 | F18: =SUMIF('Database '!$A$11:$A$22,A18,'Database '!$G$11:$G$22)*(1+Table2[[#This Row],[Growth Percentage]])^(Table2[[#Headers],[2030]]-YEAR(TODAY())) -> 1.5844228e+08 | G18: =SUMIF('Database '!$A$11:$A$22,A18,'Database '!$G$11:$G$22)*(1+Table2[[#This Row],[Growth Percentage]])^(Table2[[#Headers],[2031]]-YEAR(TODAY())) -> 1.6794882e+08 | H18: =SUMIF('Database '!$A$11:$A$22,A18,'Database '!$G$11:$G$22)*(1+Table2[[#This Row],[Growth Percentage]])^(Table2[[#Headers],[2032]]-YEAR(TODAY())) -> 1.7802575e+08 | I18: =SUMIF('Database '!$A$11:$A$22,A18,'Database '!$G$11:$G$22)*(1+Table2[[#This Row],[Growth Percentage]])^(Table2[[#Headers],[2033]]-YEAR(TODAY())) -> 1.8870729e+08 | J18: =SUMIF('Database '!$A$11:$A$22,A18,'Database '!$G$11:$G$22)*(1+Table2[[#This Row],[Growth Percentage]])^(Table2[[#Headers],[2034]]-YEAR(TODAY())) -> 2.0002973e+08 | K18: =SUMIF('Database '!$A$11:$A$22,A18,'Database '!$G$11:$G$22)*(1+Table2[[#This Row],[Growth Percentage]])^(Table2[[#Headers],[2035]]-YEAR(TODAY())) -> 2.1203151e+08 | L18: =SUMIF('Database '!$A$11:$A$22,A18,'Database '!$G$11:$G$22)*(1+Table2[[#This Row],[Growth Percentage]])^(Table2[[#Headers],[2036]]-YEAR(TODAY())) -> 2.247534e+08
A19: ='Database '!$A$13 -> BBCA | B19: ='Database '!C28 -> 0.07 | C19: =SUMIF('Database '!$A$11:$A$22,A19,'Database '!$G$11:$G$22)*(1+Table2[[#This Row],[Growth Percentage]])^(Table2[[#Headers],[2027]]-YEAR(TODAY())) -> 1.342862e+08 | D19: =SUMIF('Database '!$A$11:$A$22,A19,'Database '!$G$11:$G$22)*(1+Table2[[#This Row],[Growth Percentage]])^(Table2[[#Headers],[2028]]-YEAR(TODAY())) -> 1.4368624e+08 | E19: =SUMIF('Database '!$A$11:$A$22,A19,'Database '!$G$11:$G$22)*(1+Table2[[#This Row],[Growth Percentage]])^(Table2[[#Headers],[2029]]-YEAR(TODAY())) -> 1.5374428e+08 | F19: =SUMIF('Database '!$A$11:$A$22,A19,'Database '!$G$11:$G$22)*(1+Table2[[#This Row],[Growth Percentage]])^(Table2[[#Headers],[2030]]-YEAR(TODAY())) -> 1.6450637e+08 | G19: =SUMIF('Database '!$A$11:$A$22,A19,'Database '!$G$11:$G$22)*(1+Table2[[#This Row],[Growth Percentage]])^(Table2[[#Headers],[2031]]-YEAR(TODAY())) -> 1.7602182e+08 | H19: =SUMIF('Database '!$A$11:$A$22,A19,'Database '!$G$11:$G$22)*(1+Table2[[#This Row],[Growth Percentage]])^(Table2[[#Headers],[2032]]-YEAR(TODAY())) -> 1.8834335e+08 | I19: =SUMIF('Database '!$A$11:$A$22,A19,'Database '!$G$11:$G$22)*(1+Table2[[#This Row],[Growth Percentage]])^(Table2[[#Headers],[2033]]-YEAR(TODAY())) -> 2.0152738e+08 | J19: =SUMIF('Database '!$A$11:$A$22,A19,'Database '!$G$11:$G$22)*(1+Table2[[#This Row],[Growth Percentage]])^(Table2[[#Headers],[2034]]-YEAR(TODAY())) -> 2.156343e+08 | K19: =SUMIF('Database '!$A$11:$A$22,A19,'Database '!$G$11:$G$22)*(1+Table2[[#This Row],[Growth Percentage]])^(Table2[[#Headers],[2035]]-YEAR(TODAY())) -> 2.307287e+08 | L19: =SUMIF('Database '!$A$11:$A$22,A19,'Database '!$G$11:$G$22)*(1+Table2[[#This Row],[Growth Percentage]])^(Table2[[#Headers],[2036]]-YEAR(TODAY())) -> 2.4687971e+08
A20: ='Database '!$A$13 -> BBCA | B20: ='Database '!D28 -> 0.08 | C20: =SUMIF('Database '!$A$11:$A$22,A20,'Database '!$G$11:$G$22)*(1+Table2[[#This Row],[Growth Percentage]])^(Table2[[#Headers],[2027]]-YEAR(TODAY())) -> 1.3554122e+08 | D20: =SUMIF('Database '!$A$11:$A$22,A20,'Database '!$G$11:$G$22)*(1+Table2[[#This Row],[Growth Percentage]])^(Table2[[#Headers],[2028]]-YEAR(TODAY())) -> 1.4638451e+08 | E20: =SUMIF('Database '!$A$11:$A$22,A20,'Database '!$G$11:$G$22)*(1+Table2[[#This Row],[Growth Percentage]])^(Table2[[#Headers],[2029]]-YEAR(TODAY())) -> 1.5809527e+08 | F20: =SUMIF('Database '!$A$11:$A$22,A20,'Database '!$G$11:$G$22)*(1+Table2[[#This Row],[Growth Percentage]])^(Table2[[#Headers],[2030]]-YEAR(TODAY())) -> 1.707429e+08 | G20: =SUMIF('Database '!$A$11:$A$22,A20,'Database '!$G$11:$G$22)*(1+Table2[[#This Row],[Growth Percentage]])^(Table2[[#Headers],[2031]]-YEAR(TODAY())) -> 1.8440233e+08 | H20: =SUMIF('Database '!$A$11:$A$22,A20,'Database '!$G$11:$G$22)*(1+Table2[[#This Row],[Growth Percentage]])^(Table2[[#Headers],[2032]]-YEAR(TODAY())) -> 1.9915451e+08 | I20: =SUMIF('Database '!$A$11:$A$22,A20,'Database '!$G$11:$G$22)*(1+Table2[[#This Row],[Growth Percentage]])^(Table2[[#Headers],[2033]]-YEAR(TODAY())) -> 2.1508687e+08 | J20: =SUMIF('Database '!$A$11:$A$22,A20,'Database '!$G$11:$G$22)*(1+Table2[[#This Row],[Growth Percentage]])^(Table2[[#Headers],[2034]]-YEAR(TODAY())) -> 2.3229382e+08 | K20: =SUMIF('Database '!$A$11:$A$22,A20,'Database '!$G$11:$G$22)*(1+Table2[[#This Row],[Growth Percentage]])^(Table2[[#Headers],[2035]]-YEAR(TODAY())) -> 2.5087733e+08 | L20: =SUMIF('Database '!$A$11:$A$22,A20,'Database '!$G$11:$G$22)*(1+Table2[[#This Row],[Growth Percentage]])^(Table2[[#Headers],[2036]]-YEAR(TODAY())) -> 2.7094752e+08
A21: ='Database '!$A$13 -> BBCA | B21: ='Database '!E28 -> 0.09 | C21: =SUMIF('Database '!$A$11:$A$22,A21,'Database '!$G$11:$G$22)*(1+Table2[[#This Row],[Growth Percentage]])^(Table2[[#Headers],[2027]]-YEAR(TODAY())) -> 1.3679623e+08 | D21: =SUMIF('Database '!$A$11:$A$22,A21,'Database '!$G$11:$G$22)*(1+Table2[[#This Row],[Growth Percentage]])^(Table2[[#Headers],[2028]]-YEAR(TODAY())) -> 1.4910789e+08 | E21: =SUMIF('Database '!$A$11:$A$22,A21,'Database '!$G$11:$G$22)*(1+Table2[[#This Row],[Growth Percentage]])^(Table2[[#Headers],[2029]]-YEAR(TODAY())) -> 1.625276e+08 | F21: =SUMIF('Database '!$A$11:$A$22,A21,'Database '!$G$11:$G$22)*(1+Table2[[#This Row],[Growth Percentage]])^(Table2[[#Headers],[2030]]-YEAR(TODAY())) -> 1.7715508e+08 | G21: =SUMIF('Database '!$A$11:$A$22,A21,'Database '!$G$11:$G$22)*(1+Table2[[#This Row],[Growth Percentage]])^(Table2[[#Headers],[2031]]-YEAR(TODAY())) -> 1.9309904e+08 | H21: =SUMIF('Database '!$A$11:$A$22,A21,'Database '!$G$11:$G$22)*(1+Table2[[#This Row],[Growth Percentage]])^(Table2[[#Headers],[2032]]-YEAR(TODAY())) -> 2.1047795e+08 | I21: =SUMIF('Database '!$A$11:$A$22,A21,'Database '!$G$11:$G$22)*(1+Table2[[#This Row],[Growth Percentage]])^(Table2[[#Headers],[2033]]-YEAR(TODAY())) -> 2.2942097e+08 | J21: =SUMIF('Database '!$A$11:$A$22,A21,'Database '!$G$11:$G$22)*(1+Table2[[#This Row],[Growth Percentage]])^(Table2[[#Headers],[2034]]-YEAR(TODAY())) -> 2.5006885e+08 | K21: =SUMIF('Database '!$A$11:$A$22,A21,'Database '!$G$11:$G$22)*(1+Table2[[#This Row],[Growth Percentage]])^(Table2[[#Headers],[2035]]-YEAR(TODAY())) -> 2.7257505e+08 | L21: =SUMIF('Database '!$A$11:$A$22,A21,'Database '!$G$11:$G$22)*(1+Table2[[#This Row],[Growth Percentage]])^(Table2[[#Headers],[2036]]-YEAR(TODAY())) -> 2.9710681e+08
A22: ='Database '!$A$13 -> BBCA | B22: ='Database '!F28 -> 0.095 | C22: =SUMIF('Database '!$A$11:$A$22,A22,'Database '!$G$11:$G$22)*(1+Table2[[#This Row],[Growth Percentage]])^(Table2[[#Headers],[2027]]-YEAR(TODAY())) -> 1.3742373e+08 | D22: =SUMIF('Database '!$A$11:$A$22,A22,'Database '!$G$11:$G$22)*(1+Table2[[#This Row],[Growth Percentage]])^(Table2[[#Headers],[2028]]-YEAR(TODAY())) -> 1.5047899e+08 | E22: =SUMIF('Database '!$A$11:$A$22,A22,'Database '!$G$11:$G$22)*(1+Table2[[#This Row],[Growth Percentage]])^(Table2[[#Headers],[2029]]-YEAR(TODAY())) -> 1.6477449e+08 | F22: =SUMIF('Database '!$A$11:$A$22,A22,'Database '!$G$11:$G$22)*(1+Table2[[#This Row],[Growth Percentage]])^(Table2[[#Headers],[2030]]-YEAR(TODAY())) -> 1.8042807e+08 | G22: =SUMIF('Database '!$A$11:$A$22,A22,'Database '!$G$11:$G$22)*(1+Table2[[#This Row],[Growth Percentage]])^(Table2[[#Headers],[2031]]-YEAR(TODAY())) -> 1.9756873e+08 | H22: =SUMIF('Database '!$A$11:$A$22,A22,'Database '!$G$11:$G$22)*(1+Table2[[#This Row],[Growth Percentage]])^(Table2[[#Headers],[2032]]-YEAR(TODAY())) -> 2.1633776e+08 | I22: =SUMIF('Database '!$A$11:$A$22,A22,'Database '!$G$11:$G$22)*(1+Table2[[#This Row],[Growth Percentage]])^(Table2[[#Headers],[2033]]-YEAR(TODAY())) -> 2.3688985e+08 | J22: =SUMIF('Database '!$A$11:$A$22,A22,'Database '!$G$11:$G$22)*(1+Table2[[#This Row],[Growth Percentage]])^(Table2[[#Headers],[2034]]-YEAR(TODAY())) -> 2.5939439e+08 | K22: =SUMIF('Database '!$A$11:$A$22,A22,'Database '!$G$11:$G$22)*(1+Table2[[#This Row],[Growth Percentage]])^(Table2[[#Headers],[2035]]-YEAR(TODAY())) -> 2.8403685e+08 | L22: =SUMIF('Database '!$A$11:$A$22,A22,'Database '!$G$11:$G$22)*(1+Table2[[#This Row],[Growth Percentage]])^(Table2[[#Headers],[2036]]-YEAR(TODAY())) -> 3.1102036e+08
A23: ='Database '!$A$13 -> BBCA | B23: ='Database '!G28 -> 0.1 | C23: =SUMIF('Database '!$A$11:$A$22,A23,'Database '!$G$11:$G$22)*(1+Table2[[#This Row],[Growth Percentage]])^(Table2[[#Headers],[2027]]-YEAR(TODAY())) -> 1.3805124e+08 | D23: =SUMIF('Database '!$A$11:$A$22,A23,'Database '!$G$11:$G$22)*(1+Table2[[#This Row],[Growth Percentage]])^(Table2[[#Headers],[2028]]-YEAR(TODAY())) -> 1.5185636e+08 | E23: =SUMIF('Database '!$A$11:$A$22,A23,'Database '!$G$11:$G$22)*(1+Table2[[#This Row],[Growth Percentage]])^(Table2[[#Headers],[2029]]-YEAR(TODAY())) -> 1.67042e+08 | F23: =SUMIF('Database '!$A$11:$A$22,A23,'Database '!$G$11:$G$22)*(1+Table2[[#This Row],[Growth Percentage]])^(Table2[[#Headers],[2030]]-YEAR(TODAY())) -> 1.837462e+08 | G23: =SUMIF('Database '!$A$11:$A$22,A23,'Database '!$G$11:$G$22)*(1+Table2[[#This Row],[Growth Percentage]])^(Table2[[#Headers],[2031]]-YEAR(TODAY())) -> 2.0212082e+08 | H23: =SUMIF('Database '!$A$11:$A$22,A23,'Database '!$G$11:$G$22)*(1+Table2[[#This Row],[Growth Percentage]])^(Table2[[#Headers],[2032]]-YEAR(TODAY())) -> 2.223329e+08 | I23: =SUMIF('Database '!$A$11:$A$22,A23,'Database '!$G$11:$G$22)*(1+Table2[[#This Row],[Growth Percentage]])^(Table2[[#Headers],[2033]]-YEAR(TODAY())) -> 2.4456619e+08 | J23: =SUMIF('Database '!$A$11:$A$22,A23,'Database '!$G$11:$G$22)*(1+Table2[[#This Row],[Growth Percentage]])^(Table2[[#Headers],[2034]]-YEAR(TODAY())) -> 2.6902281e+08 | K23: =SUMIF('Database '!$A$11:$A$22,A23,'Database '!$G$11:$G$22)*(1+Table2[[#This Row],[Growth Percentage]])^(Table2[[#Headers],[2035]]-YEAR(TODAY())) -> 2.9592509e+08 | L23: =SUMIF('Database '!$A$11:$A$22,A23,'Database '!$G$11:$G$22)*(1+Table2[[#This Row],[Growth Percentage]])^(Table2[[#Headers],[2036]]-YEAR(TODAY())) -> 3.255176e+08
A24: ='Database '!$A$13 -> BBCA | B24: ='Database '!H28 -> 0.11 | C24: =SUMIF('Database '!$A$11:$A$22,A24,'Database '!$G$11:$G$22)*(1+Table2[[#This Row],[Growth Percentage]])^(Table2[[#Headers],[2027]]-YEAR(TODAY())) -> 1.3930625e+08 | D24: =SUMIF('Database '!$A$11:$A$22,A24,'Database '!$G$11:$G$22)*(1+Table2[[#This Row],[Growth Percentage]])^(Table2[[#Headers],[2028]]-YEAR(TODAY())) -> 1.5462994e+08 | E24: =SUMIF('Database '!$A$11:$A$22,A24,'Database '!$G$11:$G$22)*(1+Table2[[#This Row],[Growth Percentage]])^(Table2[[#Headers],[2029]]-YEAR(TODAY())) -> 1.7163923e+08 | F24: =SUMIF('Database '!$A$11:$A$22,A24,'Database '!$G$11:$G$22)*(1+Table2[[#This Row],[Growth Percentage]])^(Table2[[#Headers],[2030]]-YEAR(TODAY())) -> 1.9051955e+08 | G24: =SUMIF('Database '!$A$11:$A$22,A24,'Database '!$G$11:$G$22)*(1+Table2[[#This Row],[Growth Percentage]])^(Table2[[#Headers],[2031]]-YEAR(TODAY())) -> 2.114767e+08 | H24: =SUMIF('Database '!$A$11:$A$22,A24,'Database '!$G$11:$G$22)*(1+Table2[[#This Row],[Growth Percentage]])^(Table2[[#Headers],[2032]]-YEAR(TODAY())) -> 2.3473913e+08 | I24: =SUMIF('Database '!$A$11:$A$22,A24,'Database '!$G$11:$G$22)*(1+Table2[[#This Row],[Growth Percentage]])^(Table2[[#Headers],[2033]]-YEAR(TODAY())) -> 2.6056044e+08 | J24: =SUMIF('Database '!$A$11:$A$22,A24,'Database '!$G$11:$G$22)*(1+Table2[[#This Row],[Growth Percentage]])^(Table2[[#Headers],[2034]]-YEAR(TODAY())) -> 2.8922208e+08 | K24: =SUMIF('Database '!$A$11:$A$22,A24,'Database '!$G$11:$G$22)*(1+Table2[[#This Row],[Growth Percentage]])^(Table2[[#Headers],[2035]]-YEAR(TODAY())) -> 3.2103651e+08 | L24: =SUMIF('Database '!$A$11:$A$22,A24,'Database '!$G$11:$G$22)*(1+Table2[[#This Row],[Growth Percentage]])^(Table2[[#Headers],[2036]]-YEAR(TODAY())) -> 3.5635053e+08
A25: ='Database '!$A$13 -> BBCA | B25: ='Database '!I28 -> 0.12 | C25: =SUMIF('Database '!$A$11:$A$22,A25,'Database '!$G$11:$G$22)*(1+Table2[[#This Row],[Growth Percentage]])^(Table2[[#Headers],[2027]]-YEAR(TODAY())) -> 1.4056126e+08 | D25: =SUMIF('Database '!$A$11:$A$22,A25,'Database '!$G$11:$G$22)*(1+Table2[[#This Row],[Growth Percentage]])^(Table2[[#Headers],[2028]]-YEAR(TODAY())) -> 1.5742861e+08 | E25: =SUMIF('Database '!$A$11:$A$22,A25,'Database '!$G$11:$G$22)*(1+Table2[[#This Row],[Growth Percentage]])^(Table2[[#Headers],[2029]]-YEAR(TODAY())) -> 1.7632005e+08 | F25: =SUMIF('Database '!$A$11:$A$22,A25,'Database '!$G$11:$G$22)*(1+Table2[[#This Row],[Growth Percentage]])^(Table2[[#Headers],[2030]]-YEAR(TODAY())) -> 1.9747845e+08 | G25: =SUMIF('Database '!$A$11:$A$22,A25,'Database '!$G$11:$G$22)*(1+Table2[[#This Row],[Growth Percentage]])^(Table2[[#Headers],[2031]]-YEAR(TODAY())) -> 2.2117587e+08 | H25: =SUMIF('Database '!$A$11:$A$22,A25,'Database '!$G$11:$G$22)*(1+Table2[[#This Row],[Growth Percentage]])^(Table2[[#Headers],[2032]]-YEAR(TODAY())) -> 2.4771697e+08 | I25: =SUMIF('Database '!$A$11:$A$22,A25,'Database '!$G$11:$G$22)*(1+Table2[[#This Row],[Growth Percentage]])^(Table2[[#Headers],[2033]]-YEAR(TODAY())) -> 2.7744301e+08 | J25: =SUMIF('Database '!$A$11:$A$22,A25,'Database '!$G$11:$G$22)*(1+Table2[[#This Row],[Growth Percentage]])^(Table2[[#Headers],[2034]]-YEAR(TODAY())) -> 3.1073617e+08 | K25: =SUMIF('Database '!$A$11:$A$22,A25,'Database '!$G$11:$G$22)*(1+Table2[[#This Row],[Growth Percentage]])^(Table2[[#Headers],[2035]]-YEAR(TODAY())) -> 3.4802451e+08 | L25: =SUMIF('Database '!$A$11:$A$22,A25,'Database '!$G$11:$G$22)*(1+Table2[[#This Row],[Growth Percentage]])^(Table2[[#Headers],[2036]]-YEAR(TODAY())) -> 3.8978745e+08
A26: ='Database '!$A$14 -> BBRI | B26: ='Database '!B28 -> 0.06 | C26: =SUMIF('Database '!$A$11:$A$22,A26,'Database '!$G$11:$G$22)*(1+Table2[[#This Row],[Growth Percentage]])^(Table2[[#Headers],[2027]]-YEAR(TODAY())) -> 1.1678503e+08 | D26: =SUMIF('Database '!$A$11:$A$22,A26,'Database '!$G$11:$G$22)*(1+Table2[[#This Row],[Growth Percentage]])^(Table2[[#Headers],[2028]]-YEAR(TODAY())) -> 1.2379213e+08 | E26: =SUMIF('Database '!$A$11:$A$22,A26,'Database '!$G$11:$G$22)*(1+Table2[[#This Row],[Growth Percentage]])^(Table2[[#Headers],[2029]]-YEAR(TODAY())) -> 1.3121966e+08 | F26: =SUMIF('Database '!$A$11:$A$22,A26,'Database '!$G$11:$G$22)*(1+Table2[[#This Row],[Growth Percentage]])^(Table2[[#Headers],[2030]]-YEAR(TODAY())) -> 1.3909284e+08 | G26: =SUMIF('Database '!$A$11:$A$22,A26,'Database '!$G$11:$G$22)*(1+Table2[[#This Row],[Growth Percentage]])^(Table2[[#Headers],[2031]]-YEAR(TODAY())) -> 1.4743841e+08 | H26: =SUMIF('Database '!$A$11:$A$22,A26,'Database '!$G$11:$G$22)*(1+Table2[[#This Row],[Growth Percentage]])^(Table2[[#Headers],[2032]]-YEAR(TODAY())) -> 1.5628471e+08 | I26: =SUMIF('Database '!$A$11:$A$22,A26,'Database '!$G$11:$G$22)*(1+Table2[[#This Row],[Growth Percentage]])^(Table2[[#Headers],[2033]]-YEAR(TODAY())) -> 1.656618e+08 | J26: =SUMIF('Database '!$A$11:$A$22,A26,'Database '!$G$11:$G$22)*(1+Table2[[#This Row],[Growth Percentage]])^(Table2[[#Headers],[2034]]-YEAR(TODAY())) -> 1.756015e+08 | K26: =SUMIF('Database '!$A$11:$A$22,A26,'Database '!$G$11:$G$22)*(1+Table2[[#This Row],[Growth Percentage]])^(Table2[[#Headers],[2035]]-YEAR(TODAY())) -> 1.861376e+08 | L26: =SUMIF('Database '!$A$11:$A$22,A26,'Database '!$G$11:$G$22)*(1+Table2[[#This Row],[Growth Percentage]])^(Table2[[#Headers],[2036]]-YEAR(TODAY())) -> 1.9730585e+08
A27: ='Database '!$A$14 -> BBRI | B27: ='Database '!C28 -> 0.07 | C27: =SUMIF('Database '!$A$11:$A$22,A27,'Database '!$G$11:$G$22)*(1+Table2[[#This Row],[Growth Percentage]])^(Table2[[#Headers],[2027]]-YEAR(TODAY())) -> 1.1788678e+08 | D27: =SUMIF('Database '!$A$11:$A$22,A27,'Database '!$G$11:$G$22)*(1+Table2[[#This Row],[Growth Percentage]])^(Table2[[#Headers],[2028]]-YEAR(TODAY())) -> 1.2613885e+08 | E27: =SUMIF('Database '!$A$11:$A$22,A27,'Database '!$G$11:$G$22)*(1+Table2[[#This Row],[Growth Percentage]])^(Table2[[#Headers],[2029]]-YEAR(TODAY())) -> 1.3496857e+08 | F27: =SUMIF('Database '!$A$11:$A$22,A27,'Database '!$G$11:$G$22)*(1+Table2[[#This Row],[Growth Percentage]])^(Table2[[#Headers],[2030]]-YEAR(TODAY())) -> 1.4441637e+08 | G27: =SUMIF('Database '!$A$11:$A$22,A27,'Database '!$G$11:$G$22)*(1+Table2[[#This Row],[Growth Percentage]])^(Table2[[#Headers],[2031]]-YEAR(TODAY())) -> 1.5452551e+08 | H27: =SUMIF('Database '!$A$11:$A$22,A27,'Database '!$G$11:$G$22)*(1+Table2[[#This Row],[Growth Percentage]])^(Table2[[#Headers],[2032]]-YEAR(TODAY())) -> 1.653423e+08 | I27: =SUMIF('Database '!$A$11:$A$22,A27,'Database '!$G$11:$G$22)*(1+Table2[[#This Row],[Growth Percentage]])^(Table2[[#Headers],[2033]]-YEAR(TODAY())) -> 1.7691626e+08 | J27: =SUMIF('Database '!$A$11:$A$22,A27,'Database '!$G$11:$G$22)*(1+Table2[[#This Row],[Growth Percentage]])^(Table2[[#Headers],[2034]]-YEAR(TODAY())) -> 1.893004e+08 | K27: =SUMIF('Database '!$A$11:$A$22,A27,'Database '!$G$11:$G$22)*(1+Table2[[#This Row],[Growth Percentage]])^(Table2[[#Headers],[2035]]-YEAR(TODAY())) -> 2.0255143e+08 | L27: =SUMIF('Database '!$A$11:$A$22,A27,'Database '!$G$11:$G$22)*(1+Table2[[#This Row],[Growth Percentage]])^(Table2[[#Headers],[2036]]-YEAR(TODAY())) -> 2.1673003e+08
A28: ='Database '!$A$14 -> BBRI | B28: ='Database '!D28 -> 0.08 | C28: =SUMIF('Database '!$A$11:$A$22,A28,'Database '!$G$11:$G$22)*(1+Table2[[#This Row],[Growth Percentage]])^(Table2[[#Headers],[2027]]-YEAR(TODAY())) -> 1.1898852e+08 | D28: =SUMIF('Database '!$A$11:$A$22,A28,'Database '!$G$11:$G$22)*(1+Table2[[#This Row],[Growth Percentage]])^(Table2[[#Headers],[2028]]-YEAR(TODAY())) -> 1.285076e+08 | E28: =SUMIF('Database '!$A$11:$A$22,A28,'Database '!$G$11:$G$22)*(1+Table2[[#This Row],[Growth Percentage]])^(Table2[[#Headers],[2029]]-YEAR(TODAY())) -> 1.3878821e+08 | F28: =SUMIF('Database '!$A$11:$A$22,A28,'Database '!$G$11:$G$22)*(1+Table2[[#This Row],[Growth Percentage]])^(Table2[[#Headers],[2030]]-YEAR(TODAY())) -> 1.4989127e+08 | G28: =SUMIF('Database '!$A$11:$A$22,A28,'Database '!$G$11:$G$22)*(1+Table2[[#This Row],[Growth Percentage]])^(Table2[[#Headers],[2031]]-YEAR(TODAY())) -> 1.6188257e+08 | H28: =SUMIF('Database '!$A$11:$A$22,A28,'Database '!$G$11:$G$22)*(1+Table2[[#This Row],[Growth Percentage]])^(Table2[[#Headers],[2032]]-YEAR(TODAY())) -> 1.7483317e+08 | I28: =SUMIF('Database '!$A$11:$A$22,A28,'Database '!$G$11:$G$22)*(1+Table2[[#This Row],[Growth Percentage]])^(Table2[[#Headers],[2033]]-YEAR(TODAY())) -> 1.8881983e+08 | J28: =SUMIF('Database '!$A$11:$A$22,A28,'Database '!$G$11:$G$22)*(1+Table2[[#This Row],[Growth Percentage]])^(Table2[[#Headers],[2034]]-YEAR(TODAY())) -> 2.0392542e+08 | K28: =SUMIF('Database '!$A$11:$A$22,A28,'Database '!$G$11:$G$22)*(1+Table2[[#This Row],[Growth Percentage]])^(Table2[[#Headers],[2035]]-YEAR(TODAY())) -> 2.2023945e+08 | L28: =SUMIF('Database '!$A$11:$A$22,A28,'Database '!$G$11:$G$22)*(1+Table2[[#This Row],[Growth Percentage]])^(Table2[[#Headers],[2036]]-YEAR(TODAY())) -> 2.378586e+08
A29: ='Database '!$A$14 -> BBRI | B29: ='Database '!E28 -> 0.09 | C29: =SUMIF('Database '!$A$11:$A$22,A29,'Database '!$G$11:$G$22)*(1+Table2[[#This Row],[Growth Percentage]])^(Table2[[#Headers],[2027]]-YEAR(TODAY())) -> 1.2009027e+08 | D29: =SUMIF('Database '!$A$11:$A$22,A29,'Database '!$G$11:$G$22)*(1+Table2[[#This Row],[Growth Percentage]])^(Table2[[#Headers],[2028]]-YEAR(TODAY())) -> 1.3089839e+08 | E29: =SUMIF('Database '!$A$11:$A$22,A29,'Database '!$G$11:$G$22)*(1+Table2[[#This Row],[Growth Percentage]])^(Table2[[#Headers],[2029]]-YEAR(TODAY())) -> 1.4267925e+08 | F29: =SUMIF('Database '!$A$11:$A$22,A29,'Database '!$G$11:$G$22)*(1+Table2[[#This Row],[Growth Percentage]])^(Table2[[#Headers],[2030]]-YEAR(TODAY())) -> 1.5552038e+08 | G29: =SUMIF('Database '!$A$11:$A$22,A29,'Database '!$G$11:$G$22)*(1+Table2[[#This Row],[Growth Percentage]])^(Table2[[#Headers],[2031]]-YEAR(TODAY())) -> 1.6951721e+08 | H29: =SUMIF('Database '!$A$11:$A$22,A29,'Database '!$G$11:$G$22)*(1+Table2[[#This Row],[Growth Percentage]])^(Table2[[#Headers],[2032]]-YEAR(TODAY())) -> 1.8477376e+08 | I29: =SUMIF('Database '!$A$11:$A$22,A29,'Database '!$G$11:$G$22)*(1+Table2[[#This Row],[Growth Percentage]])^(Table2[[#Headers],[2033]]-YEAR(TODAY())) -> 2.014034e+08 | J29: =SUMIF('Database '!$A$11:$A$22,A29,'Database '!$G$11:$G$22)*(1+Table2[[#This Row],[Growth Percentage]])^(Table2[[#Headers],[2034]]-YEAR(TODAY())) -> 2.1952971e+08 | K29: =SUMIF('Database '!$A$11:$A$22,A29,'Database '!$G$11:$G$22)*(1+Table2[[#This Row],[Growth Percentage]])^(Table2[[#Headers],[2035]]-YEAR(TODAY())) -> 2.3928738e+08 | L29: =SUMIF('Database '!$A$11:$A$22,A29,'Database '!$G$11:$G$22)*(1+Table2[[#This Row],[Growth Percentage]])^(Table2[[#Headers],[2036]]-YEAR(TODAY())) -> 2.6082324e+08
A30: ='Database '!$A$14 -> BBRI | B30: ='Database '!F28 -> 0.095 | C30: =SUMIF('Database '!$A$11:$A$22,A30,'Database '!$G$11:$G$22)*(1+Table2[[#This Row],[Growth Percentage]])^(Table2[[#Headers],[2027]]-YEAR(TODAY())) -> 1.2064114e+08 | D30: =SUMIF('Database '!$A$11:$A$22,A30,'Database '!$G$11:$G$22)*(1+Table2[[#This Row],[Growth Percentage]])^(Table2[[#Headers],[2028]]-YEAR(TODAY())) -> 1.3210205e+08 | E30: =SUMIF('Database '!$A$11:$A$22,A30,'Database '!$G$11:$G$22)*(1+Table2[[#This Row],[Growth Percentage]])^(Table2[[#Headers],[2029]]-YEAR(TODAY())) -> 1.4465174e+08 | F30: =SUMIF('Database '!$A$11:$A$22,A30,'Database '!$G$11:$G$22)*(1+Table2[[#This Row],[Growth Percentage]])^(Table2[[#Headers],[2030]]-YEAR(TODAY())) -> 1.5839366e+08 | G30: =SUMIF('Database '!$A$11:$A$22,A30,'Database '!$G$11:$G$22)*(1+Table2[[#This Row],[Growth Percentage]])^(Table2[[#Headers],[2031]]-YEAR(TODAY())) -> 1.7344106e+08 | H30: =SUMIF('Database '!$A$11:$A$22,A30,'Database '!$G$11:$G$22)*(1+Table2[[#This Row],[Growth Percentage]])^(Table2[[#Headers],[2032]]-YEAR(TODAY())) -> 1.8991796e+08 | I30: =SUMIF('Database '!$A$11:$A$22,A30,'Database '!$G$11:$G$22)*(1+Table2[[#This Row],[Growth Percentage]])^(Table2[[#Headers],[2033]]-YEAR(TODAY())) -> 2.0796016e+08 | J30: =SUMIF('Database '!$A$11:$A$22,A30,'Database '!$G$11:$G$22)*(1+Table2[[#This Row],[Growth Percentage]])^(Table2[[#Headers],[2034]]-YEAR(TODAY())) -> 2.2771638e+08 | K30: =SUMIF('Database '!$A$11:$A$22,A30,'Database '!$G$11:$G$22)*(1+Table2[[#This Row],[Growth Percentage]])^(Table2[[#Headers],[2035]]-YEAR(TODAY())) -> 2.4934943e+08 | L30: =SUMIF('Database '!$A$11:$A$22,A30,'Database '!$G$11:$G$22)*(1+Table2[[#This Row],[Growth Percentage]])^(Table2[[#Headers],[2036]]-YEAR(TODAY())) -> 2.7303763e+08
A31: ='Database '!$A$14 -> BBRI | B31: ='Database '!G28 -> 0.1 | C31: =SUMIF('Database '!$A$11:$A$22,A31,'Database '!$G$11:$G$22)*(1+Table2[[#This Row],[Growth Percentage]])^(Table2[[#Headers],[2027]]-YEAR(TODAY())) -> 1.2119201e+08 | D31: =SUMIF('Database '!$A$11:$A$22,A31,'Database '!$G$11:$G$22)*(1+Table2[[#This Row],[Growth Percentage]])^(Table2[[#Headers],[2028]]-YEAR(TODAY())) -> 1.3331121e+08 | E31: =SUMIF('Database '!$A$11:$A$22,A31,'Database '!$G$11:$G$22)*(1+Table2[[#This Row],[Growth Percentage]])^(Table2[[#Headers],[2029]]-YEAR(TODAY())) -> 1.4664233e+08 | F31: =SUMIF('Database '!$A$11:$A$22,A31,'Database '!$G$11:$G$22)*(1+Table2[[#This Row],[Growth Percentage]])^(Table2[[#Headers],[2030]]-YEAR(TODAY())) -> 1.6130657e+08 | G31: =SUMIF('Database '!$A$11:$A$22,A31,'Database '!$G$11:$G$22)*(1+Table2[[#This Row],[Growth Percentage]])^(Table2[[#Headers],[2031]]-YEAR(TODAY())) -> 1.7743723e+08 | H31: =SUMIF('Database '!$A$11:$A$22,A31,'Database '!$G$11:$G$22)*(1+Table2[[#This Row],[Growth Percentage]])^(Table2[[#Headers],[2032]]-YEAR(TODAY())) -> 1.9518095e+08 | I31: =SUMIF('Database '!$A$11:$A$22,A31,'Database '!$G$11:$G$22)*(1+Table2[[#This Row],[Growth Percentage]])^(Table2[[#Headers],[2033]]-YEAR(TODAY())) -> 2.1469904e+08 | J31: =SUMIF('Database '!$A$11:$A$22,A31,'Database '!$G$11:$G$22)*(1+Table2[[#This Row],[Growth Percentage]])^(Table2[[#Headers],[2034]]-YEAR(TODAY())) -> 2.3616895e+08 | K31: =SUMIF('Database '!$A$11:$A$22,A31,'Database '!$G$11:$G$22)*(1+Table2[[#This Row],[Growth Percentage]])^(Table2[[#Headers],[2035]]-YEAR(TODAY())) -> 2.5978584e+08 | L31: =SUMIF('Database '!$A$11:$A$22,A31,'Database '!$G$11:$G$22)*(1+Table2[[#This Row],[Growth Percentage]])^(Table2[[#Headers],[2036]]-YEAR(TODAY())) -> 2.8576443e+08
A32: ='Database '!$A$14 -> BBRI | B32: ='Database '!H28 -> 0.11 | C32: =SUMIF('Database '!$A$11:$A$22,A32,'Database '!$G$11:$G$22)*(1+Table2[[#This Row],[Growth Percentage]])^(Table2[[#Headers],[2027]]-YEAR(TODAY())) -> 1.2229376e+08 | D32: =SUMIF('Database '!$A$11:$A$22,A32,'Database '!$G$11:$G$22)*(1+Table2[[#This Row],[Growth Percentage]])^(Table2[[#Headers],[2028]]-YEAR(TODAY())) -> 1.3574607e+08 | E32: =SUMIF('Database '!$A$11:$A$22,A32,'Database '!$G$11:$G$22)*(1+Table2[[#This Row],[Growth Percentage]])^(Table2[[#Headers],[2029]]-YEAR(TODAY())) -> 1.5067814e+08 | F32: =SUMIF('Database '!$A$11:$A$22,A32,'Database '!$G$11:$G$22)*(1+Table2[[#This Row],[Growth Percentage]])^(Table2[[#Headers],[2030]]-YEAR(TODAY())) -> 1.6725273e+08 | G32: =SUMIF('Database '!$A$11:$A$22,A32,'Database '!$G$11:$G$22)*(1+Table2[[#This Row],[Growth Percentage]])^(Table2[[#Headers],[2031]]-YEAR(TODAY())) -> 1.8565053e+08 | H32: =SUMIF('Database '!$A$11:$A$22,A32,'Database '!$G$11:$G$22)*(1+Table2[[#This Row],[Growth Percentage]])^(Table2[[#Headers],[2032]]-YEAR(TODAY())) -> 2.0607209e+08 | I32: =SUMIF('Database '!$A$11:$A$22,A32,'Database '!$G$11:$G$22)*(1+Table2[[#This Row],[Growth Percentage]])^(Table2[[#Headers],[2033]]-YEAR(TODAY())) -> 2.2874002e+08 | J32: =SUMIF('Database '!$A$11:$A$22,A32,'Database '!$G$11:$G$22)*(1+Table2[[#This Row],[Growth Percentage]])^(Table2[[#Headers],[2034]]-YEAR(TODAY())) -> 2.5390143e+08 | K32: =SUMIF('Database '!$A$11:$A$22,A32,'Database '!$G$11:$G$22)*(1+Table2[[#This Row],[Growth Percentage]])^(Table2[[#Headers],[2035]]-YEAR(TODAY())) -> 2.8183058e+08 | L32: =SUMIF('Database '!$A$11:$A$22,A32,'Database '!$G$11:$G$22)*(1+Table2[[#This Row],[Growth Percentage]])^(Table2[[#Headers],[2036]]-YEAR(TODAY())) -> 3.1283195e+08
A33: ='Database '!$A$14 -> BBRI | B33: ='Database '!I28 -> 0.12 | C33: =SUMIF('Database '!$A$11:$A$22,A33,'Database '!$G$11:$G$22)*(1+Table2[[#This Row],[Growth Percentage]])^(Table2[[#Headers],[2027]]-YEAR(TODAY())) -> 1.233955e+08 | D33: =SUMIF('Database '!$A$11:$A$22,A33,'Database '!$G$11:$G$22)*(1+Table2[[#This Row],[Growth Percentage]])^(Table2[[#Headers],[2028]]-YEAR(TODAY())) -> 1.3820296e+08 | E33: =SUMIF('Database '!$A$11:$A$22,A33,'Database '!$G$11:$G$22)*(1+Table2[[#This Row],[Growth Percentage]])^(Table2[[#Headers],[2029]]-YEAR(TODAY())) -> 1.5478732e+08 | F33: =SUMIF('Database '!$A$11:$A$22,A33,'Database '!$G$11:$G$22)*(1+Table2[[#This Row],[Growth Percentage]])^(Table2[[#Headers],[2030]]-YEAR(TODAY())) -> 1.733618e+08 | G33: =SUMIF('Database '!$A$11:$A$22,A33,'Database '!$G$11:$G$22)*(1+Table2[[#This Row],[Growth Percentage]])^(Table2[[#Headers],[2031]]-YEAR(TODAY())) -> 1.9416521e+08 | H33: =SUMIF('Database '!$A$11:$A$22,A33,'Database '!$G$11:$G$22)*(1+Table2[[#This Row],[Growth Percentage]])^(Table2[[#Headers],[2032]]-YEAR(TODAY())) -> 2.1746504e+08 | I33: =SUMIF('Database '!$A$11:$A$22,A33,'Database '!$G$11:$G$22)*(1+Table2[[#This Row],[Growth Percentage]])^(Table2[[#Headers],[2033]]-YEAR(TODAY())) -> 2.4356084e+08 | J33: =SUMIF('Database '!$A$11:$A$22,A33,'Database '!$G$11:$G$22)*(1+Table2[[#This Row],[Growth Percentage]])^(Table2[[#Headers],[2034]]-YEAR(TODAY())) -> 2.7278814e+08 | K33: =SUMIF('Database '!$A$11:$A$22,A33,'Database '!$G$11:$G$22)*(1+Table2[[#This Row],[Growth Percentage]])^(Table2[[#Headers],[2035]]-YEAR(TODAY())) -> 3.0552272e+08 | L33: =SUMIF('Database '!$A$11:$A$22,A33,'Database '!$G$11:$G$22)*(1+Table2[[#This Row],[Growth Percentage]])^(Table2[[#Headers],[2036]]-YEAR(TODAY())) -> 3.4218545e+08
A34: ='Database '!$A$15 -> BREN | B34: ='Database '!B28 -> 0.06 | C34: =SUMIF('Database '!$A$11:$A$22,A34,'Database '!$G$11:$G$22)*(1+Table2[[#This Row],[Growth Percentage]])^(Table2[[#Headers],[2027]]-YEAR(TODAY())) -> 65602765 | D34: =SUMIF('Database '!$A$11:$A$22,A34,'Database '!$G$11:$G$22)*(1+Table2[[#This Row],[Growth Percentage]])^(Table2[[#Headers],[2028]]-YEAR(TODAY())) -> 69538931 | E34: =SUMIF('Database '!$A$11:$A$22,A34,'Database '!$G$11:$G$22)*(1+Table2[[#This Row],[Growth Percentage]])^(Table2[[#Headers],[2029]]-YEAR(TODAY())) -> 73711267 | F34: =SUMIF('Database '!$A$11:$A$22,A34,'Database '!$G$11:$G$22)*(1+Table2[[#This Row],[Growth Percentage]])^(Table2[[#Headers],[2030]]-YEAR(TODAY())) -> 78133943 | G34: =SUMIF('Database '!$A$11:$A$22,A34,'Database '!$G$11:$G$22)*(1+Table2[[#This Row],[Growth Percentage]])^(Table2[[#Headers],[2031]]-YEAR(TODAY())) -> 82821980 | H34: =SUMIF('Database '!$A$11:$A$22,A34,'Database '!$G$11:$G$22)*(1+Table2[[#This Row],[Growth Percentage]])^(Table2[[#Headers],[2032]]-YEAR(TODAY())) -> 87791299 | I34: =SUMIF('Database '!$A$11:$A$22,A34,'Database '!$G$11:$G$22)*(1+Table2[[#This Row],[Growth Percentage]])^(Table2[[#Headers],[2033]]-YEAR(TODAY())) -> 93058777 | J34: =SUMIF('Database '!$A$11:$A$22,A34,'Database '!$G$11:$G$22)*(1+Table2[[#This Row],[Growth Percentage]])^(Table2[[#Headers],[2034]]-YEAR(TODAY())) -> 98642303 | K34: =SUMIF('Database '!$A$11:$A$22,A34,'Database '!$G$11:$G$22)*(1+Table2[[#This Row],[Growth Percentage]])^(Table2[[#Headers],[2035]]-YEAR(TODAY())) -> 1.0456084e+08 | L34: =SUMIF('Database '!$A$11:$A$22,A34,'Database '!$G$11:$G$22)*(1+Table2[[#This Row],[Growth Percentage]])^(Table2[[#Headers],[2036]]-YEAR(TODAY())) -> 1.1083449e+08
A35: ='Database '!$A$15 -> BREN | B35: ='Database '!C28 -> 0.07 | C35: =SUMIF('Database '!$A$11:$A$22,A35,'Database '!$G$11:$G$22)*(1+Table2[[#This Row],[Growth Percentage]])^(Table2[[#Headers],[2027]]-YEAR(TODAY())) -> 66221660 | D35: =SUMIF('Database '!$A$11:$A$22,A35,'Database '!$G$11:$G$22)*(1+Table2[[#This Row],[Growth Percentage]])^(Table2[[#Headers],[2028]]-YEAR(TODAY())) -> 70857176 | E35: =SUMIF('Database '!$A$11:$A$22,A35,'Database '!$G$11:$G$22)*(1+Table2[[#This Row],[Growth Percentage]])^(Table2[[#Headers],[2029]]-YEAR(TODAY())) -> 75817178 | F35: =SUMIF('Database '!$A$11:$A$22,A35,'Database '!$G$11:$G$22)*(1+Table2[[#This Row],[Growth Percentage]])^(Table2[[#Headers],[2030]]-YEAR(TODAY())) -> 81124380 | G35: =SUMIF('Database '!$A$11:$A$22,A35,'Database '!$G$11:$G$22)*(1+Table2[[#This Row],[Growth Percentage]])^(Table2[[#Headers],[2031]]-YEAR(TODAY())) -> 86803087 | H35: =SUMIF('Database '!$A$11:$A$22,A35,'Database '!$G$11:$G$22)*(1+Table2[[#This Row],[Growth Percentage]])^(Table2[[#Headers],[2032]]-YEAR(TODAY())) -> 92879303 | I35: =SUMIF('Database '!$A$11:$A$22,A35,'Database '!$G$11:$G$22)*(1+Table2[[#This Row],[Growth Percentage]])^(Table2[[#Headers],[2033]]-YEAR(TODAY())) -> 99380854 | J35: =SUMIF('Database '!$A$11:$A$22,A35,'Database '!$G$11:$G$22)*(1+Table2[[#This Row],[Growth Percentage]])^(Table2[[#Headers],[2034]]-YEAR(TODAY())) -> 1.0633751e+08 | K35: =SUMIF('Database '!$A$11:$A$22,A35,'Database '!$G$11:$G$22)*(1+Table2[[#This Row],[Growth Percentage]])^(Table2[[#Headers],[2035]]-YEAR(TODAY())) -> 1.1378114e+08 | L35: =SUMIF('Database '!$A$11:$A$22,A35,'Database '!$G$11:$G$22)*(1+Table2[[#This Row],[Growth Percentage]])^(Table2[[#Headers],[2036]]-YEAR(TODAY())) -> 1.2174582e+08
A36: ='Database '!$A$15 -> BREN | B36: ='Database '!D28 -> 0.08 | C36: =SUMIF('Database '!$A$11:$A$22,A36,'Database '!$G$11:$G$22)*(1+Table2[[#This Row],[Growth Percentage]])^(Table2[[#Headers],[2027]]-YEAR(TODAY())) -> 66840554 | D36: =SUMIF('Database '!$A$11:$A$22,A36,'Database '!$G$11:$G$22)*(1+Table2[[#This Row],[Growth Percentage]])^(Table2[[#Headers],[2028]]-YEAR(TODAY())) -> 72187798 | E36: =SUMIF('Database '!$A$11:$A$22,A36,'Database '!$G$11:$G$22)*(1+Table2[[#This Row],[Growth Percentage]])^(Table2[[#Headers],[2029]]-YEAR(TODAY())) -> 77962822 | F36: =SUMIF('Database '!$A$11:$A$22,A36,'Database '!$G$11:$G$22)*(1+Table2[[#This Row],[Growth Percentage]])^(Table2[[#Headers],[2030]]-YEAR(TODAY())) -> 84199847 | G36: =SUMIF('Database '!$A$11:$A$22,A36,'Database '!$G$11:$G$22)*(1+Table2[[#This Row],[Growth Percentage]])^(Table2[[#Headers],[2031]]-YEAR(TODAY())) -> 90935835 | H36: =SUMIF('Database '!$A$11:$A$22,A36,'Database '!$G$11:$G$22)*(1+Table2[[#This Row],[Growth Percentage]])^(Table2[[#Headers],[2032]]-YEAR(TODAY())) -> 98210702 | I36: =SUMIF('Database '!$A$11:$A$22,A36,'Database '!$G$11:$G$22)*(1+Table2[[#This Row],[Growth Percentage]])^(Table2[[#Headers],[2033]]-YEAR(TODAY())) -> 1.0606756e+08 | J36: =SUMIF('Database '!$A$11:$A$22,A36,'Database '!$G$11:$G$22)*(1+Table2[[#This Row],[Growth Percentage]])^(Table2[[#Headers],[2034]]-YEAR(TODAY())) -> 1.1455296e+08 | K36: =SUMIF('Database '!$A$11:$A$22,A36,'Database '!$G$11:$G$22)*(1+Table2[[#This Row],[Growth Percentage]])^(Table2[[#Headers],[2035]]-YEAR(TODAY())) -> 1.237172e+08 | L36: =SUMIF('Database '!$A$11:$A$22,A36,'Database '!$G$11:$G$22)*(1+Table2[[#This Row],[Growth Percentage]])^(Table2[[#Headers],[2036]]-YEAR(TODAY())) -> 1.3361458e+08
A37: ='Database '!$A$15 -> BREN | B37: ='Database '!E28 -> 0.09 | C37: =SUMIF('Database '!$A$11:$A$22,A37,'Database '!$G$11:$G$22)*(1+Table2[[#This Row],[Growth Percentage]])^(Table2[[#Headers],[2027]]-YEAR(TODAY())) -> 67459448 | D37: =SUMIF('Database '!$A$11:$A$22,A37,'Database '!$G$11:$G$22)*(1+Table2[[#This Row],[Growth Percentage]])^(Table2[[#Headers],[2028]]-YEAR(TODAY())) -> 73530798 | E37: =SUMIF('Database '!$A$11:$A$22,A37,'Database '!$G$11:$G$22)*(1+Table2[[#This Row],[Growth Percentage]])^(Table2[[#Headers],[2029]]-YEAR(TODAY())) -> 80148570 | F37: =SUMIF('Database '!$A$11:$A$22,A37,'Database '!$G$11:$G$22)*(1+Table2[[#This Row],[Growth Percentage]])^(Table2[[#Headers],[2030]]-YEAR(TODAY())) -> 87361941 | G37: =SUMIF('Database '!$A$11:$A$22,A37,'Database '!$G$11:$G$22)*(1+Table2[[#This Row],[Growth Percentage]])^(Table2[[#Headers],[2031]]-YEAR(TODAY())) -> 95224516 | H37: =SUMIF('Database '!$A$11:$A$22,A37,'Database '!$G$11:$G$22)*(1+Table2[[#This Row],[Growth Percentage]])^(Table2[[#Headers],[2032]]-YEAR(TODAY())) -> 1.0379472e+08 | I37: =SUMIF('Database '!$A$11:$A$22,A37,'Database '!$G$11:$G$22)*(1+Table2[[#This Row],[Growth Percentage]])^(Table2[[#Headers],[2033]]-YEAR(TODAY())) -> 1.1313625e+08 | J37: =SUMIF('Database '!$A$11:$A$22,A37,'Database '!$G$11:$G$22)*(1+Table2[[#This Row],[Growth Percentage]])^(Table2[[#Headers],[2034]]-YEAR(TODAY())) -> 1.2331851e+08 | K37: =SUMIF('Database '!$A$11:$A$22,A37,'Database '!$G$11:$G$22)*(1+Table2[[#This Row],[Growth Percentage]])^(Table2[[#Headers],[2035]]-YEAR(TODAY())) -> 1.3441717e+08 | L37: =SUMIF('Database '!$A$11:$A$22,A37,'Database '!$G$11:$G$22)*(1+Table2[[#This Row],[Growth Percentage]])^(Table2[[#Headers],[2036]]-YEAR(TODAY())) -> 1.4651472e+08
A38: ='Database '!$A$15 -> BREN | B38: ='Database '!F28 -> 0.095 | C38: =SUMIF('Database '!$A$11:$A$22,A38,'Database '!$G$11:$G$22)*(1+Table2[[#This Row],[Growth Percentage]])^(Table2[[#Headers],[2027]]-YEAR(TODAY())) -> 67768895 | D38: =SUMIF('Database '!$A$11:$A$22,A38,'Database '!$G$11:$G$22)*(1+Table2[[#This Row],[Growth Percentage]])^(Table2[[#Headers],[2028]]-YEAR(TODAY())) -> 74206940 | E38: =SUMIF('Database '!$A$11:$A$22,A38,'Database '!$G$11:$G$22)*(1+Table2[[#This Row],[Growth Percentage]])^(Table2[[#Headers],[2029]]-YEAR(TODAY())) -> 81256599 | F38: =SUMIF('Database '!$A$11:$A$22,A38,'Database '!$G$11:$G$22)*(1+Table2[[#This Row],[Growth Percentage]])^(Table2[[#Headers],[2030]]-YEAR(TODAY())) -> 88975976 | G38: =SUMIF('Database '!$A$11:$A$22,A38,'Database '!$G$11:$G$22)*(1+Table2[[#This Row],[Growth Percentage]])^(Table2[[#Headers],[2031]]-YEAR(TODAY())) -> 97428693 | H38: =SUMIF('Database '!$A$11:$A$22,A38,'Database '!$G$11:$G$22)*(1+Table2[[#This Row],[Growth Percentage]])^(Table2[[#Headers],[2032]]-YEAR(TODAY())) -> 1.0668442e+08 | I38: =SUMIF('Database '!$A$11:$A$22,A38,'Database '!$G$11:$G$22)*(1+Table2[[#This Row],[Growth Percentage]])^(Table2[[#Headers],[2033]]-YEAR(TODAY())) -> 1.1681944e+08 | J38: =SUMIF('Database '!$A$11:$A$22,A38,'Database '!$G$11:$G$22)*(1+Table2[[#This Row],[Growth Percentage]])^(Table2[[#Headers],[2034]]-YEAR(TODAY())) -> 1.2791729e+08 | K38: =SUMIF('Database '!$A$11:$A$22,A38,'Database '!$G$11:$G$22)*(1+Table2[[#This Row],[Growth Percentage]])^(Table2[[#Headers],[2035]]-YEAR(TODAY())) -> 1.4006943e+08 | L38: =SUMIF('Database '!$A$11:$A$22,A38,'Database '!$G$11:$G$22)*(1+Table2[[#This Row],[Growth Percentage]])^(Table2[[#Headers],[2036]]-YEAR(TODAY())) -> 1.5337602e+08
A39: ='Database '!$A$15 -> BREN | B39: ='Database '!G28 -> 0.1 | C39: =SUMIF('Database '!$A$11:$A$22,A39,'Database '!$G$11:$G$22)*(1+Table2[[#This Row],[Growth Percentage]])^(Table2[[#Headers],[2027]]-YEAR(TODAY())) -> 68078342 | D39: =SUMIF('Database '!$A$11:$A$22,A39,'Database '!$G$11:$G$22)*(1+Table2[[#This Row],[Growth Percentage]])^(Table2[[#Headers],[2028]]-YEAR(TODAY())) -> 74886176 | E39: =SUMIF('Database '!$A$11:$A$22,A39,'Database '!$G$11:$G$22)*(1+Table2[[#This Row],[Growth Percentage]])^(Table2[[#Headers],[2029]]-YEAR(TODAY())) -> 82374793 | F39: =SUMIF('Database '!$A$11:$A$22,A39,'Database '!$G$11:$G$22)*(1+Table2[[#This Row],[Growth Percentage]])^(Table2[[#Headers],[2030]]-YEAR(TODAY())) -> 90612273 | G39: =SUMIF('Database '!$A$11:$A$22,A39,'Database '!$G$11:$G$22)*(1+Table2[[#This Row],[Growth Percentage]])^(Table2[[#Headers],[2031]]-YEAR(TODAY())) -> 99673500 | H39: =SUMIF('Database '!$A$11:$A$22,A39,'Database '!$G$11:$G$22)*(1+Table2[[#This Row],[Growth Percentage]])^(Table2[[#Headers],[2032]]-YEAR(TODAY())) -> 1.0964085e+08 | I39: =SUMIF('Database '!$A$11:$A$22,A39,'Database '!$G$11:$G$22)*(1+Table2[[#This Row],[Growth Percentage]])^(Table2[[#Headers],[2033]]-YEAR(TODAY())) -> 1.2060493e+08 | J39: =SUMIF('Database '!$A$11:$A$22,A39,'Database '!$G$11:$G$22)*(1+Table2[[#This Row],[Growth Percentage]])^(Table2[[#Headers],[2034]]-YEAR(TODAY())) -> 1.3266543e+08 | K39: =SUMIF('Database '!$A$11:$A$22,A39,'Database '!$G$11:$G$22)*(1+Table2[[#This Row],[Growth Percentage]])^(Table2[[#Headers],[2035]]-YEAR(TODAY())) -> 1.4593197e+08 | L39: =SUMIF('Database '!$A$11:$A$22,A39,'Database '!$G$11:$G$22)*(1+Table2[[#This Row],[Growth Percentage]])^(Table2[[#Headers],[2036]]-YEAR(TODAY())) -> 1.6052517e+08
A40: ='Database '!$A$15 -> BREN | B40: ='Database '!H28 -> 0.11 | C40: =SUMIF('Database '!$A$11:$A$22,A40,'Database '!$G$11:$G$22)*(1+Table2[[#This Row],[Growth Percentage]])^(Table2[[#Headers],[2027]]-YEAR(TODAY())) -> 68697236 | D40: =SUMIF('Database '!$A$11:$A$22,A40,'Database '!$G$11:$G$22)*(1+Table2[[#This Row],[Growth Percentage]])^(Table2[[#Headers],[2028]]-YEAR(TODAY())) -> 76253931 | E40: =SUMIF('Database '!$A$11:$A$22,A40,'Database '!$G$11:$G$22)*(1+Table2[[#This Row],[Growth Percentage]])^(Table2[[#Headers],[2029]]-YEAR(TODAY())) -> 84641864 | F40: =SUMIF('Database '!$A$11:$A$22,A40,'Database '!$G$11:$G$22)*(1+Table2[[#This Row],[Growth Percentage]])^(Table2[[#Headers],[2030]]-YEAR(TODAY())) -> 93952469 | G40: =SUMIF('Database '!$A$11:$A$22,A40,'Database '!$G$11:$G$22)*(1+Table2[[#This Row],[Growth Percentage]])^(Table2[[#Headers],[2031]]-YEAR(TODAY())) -> 1.0428724e+08 | H40: =SUMIF('Database '!$A$11:$A$22,A40,'Database '!$G$11:$G$22)*(1+Table2[[#This Row],[Growth Percentage]])^(Table2[[#Headers],[2032]]-YEAR(TODAY())) -> 1.1575884e+08 | I40: =SUMIF('Database '!$A$11:$A$22,A40,'Database '!$G$11:$G$22)*(1+Table2[[#This Row],[Growth Percentage]])^(Table2[[#Headers],[2033]]-YEAR(TODAY())) -> 1.2849231e+08 | J40: =SUMIF('Database '!$A$11:$A$22,A40,'Database '!$G$11:$G$22)*(1+Table2[[#This Row],[Growth Percentage]])^(Table2[[#Headers],[2034]]-YEAR(TODAY())) -> 1.4262646e+08 | K40: =SUMIF('Database '!$A$11:$A$22,A40,'Database '!$G$11:$G$22)*(1+Table2[[#This Row],[Growth Percentage]])^(Table2[[#Headers],[2035]]-YEAR(TODAY())) -> 1.5831537e+08 | L40: =SUMIF('Database '!$A$11:$A$22,A40,'Database '!$G$11:$G$22)*(1+Table2[[#This Row],[Growth Percentage]])^(Table2[[#Headers],[2036]]-YEAR(TODAY())) -> 1.7573007e+08
A41: ='Database '!$A$15 -> BREN | B41: ='Database '!I28 -> 0.12 | C41: =SUMIF('Database '!$A$11:$A$22,A41,'Database '!$G$11:$G$22)*(1+Table2[[#This Row],[Growth Percentage]])^(Table2[[#Headers],[2027]]-YEAR(TODAY())) -> 69316130 | D41: =SUMIF('Database '!$A$11:$A$22,A41,'Database '!$G$11:$G$22)*(1+Table2[[#This Row],[Growth Percentage]])^(Table2[[#Headers],[2028]]-YEAR(TODAY())) -> 77634065 | E41: =SUMIF('Database '!$A$11:$A$22,A41,'Database '!$G$11:$G$22)*(1+Table2[[#This Row],[Growth Percentage]])^(Table2[[#Headers],[2029]]-YEAR(TODAY())) -> 86950153 | F41: =SUMIF('Database '!$A$11:$A$22,A41,'Database '!$G$11:$G$22)*(1+Table2[[#This Row],[Growth Percentage]])^(Table2[[#Headers],[2030]]-YEAR(TODAY())) -> 97384171 | G41: =SUMIF('Database '!$A$11:$A$22,A41,'Database '!$G$11:$G$22)*(1+Table2[[#This Row],[Growth Percentage]])^(Table2[[#Headers],[2031]]-YEAR(TODAY())) -> 1.0907027e+08 | H41: =SUMIF('Database '!$A$11:$A$22,A41,'Database '!$G$11:$G$22)*(1+Table2[[#This Row],[Growth Percentage]])^(Table2[[#Headers],[2032]]-YEAR(TODAY())) -> 1.221587e+08 | I41: =SUMIF('Database '!$A$11:$A$22,A41,'Database '!$G$11:$G$22)*(1+Table2[[#This Row],[Growth Percentage]])^(Table2[[#Headers],[2033]]-YEAR(TODAY())) -> 1.3681775e+08 | J41: =SUMIF('Database '!$A$11:$A$22,A41,'Database '!$G$11:$G$22)*(1+Table2[[#This Row],[Growth Percentage]])^(Table2[[#Headers],[2034]]-YEAR(TODAY())) -> 1.5323588e+08 | K41: =SUMIF('Database '!$A$11:$A$22,A41,'Database '!$G$11:$G$22)*(1+Table2[[#This Row],[Growth Percentage]])^(Table2[[#Headers],[2035]]-YEAR(TODAY())) -> 1.7162418e+08 | L41: =SUMIF('Database '!$A$11:$A$22,A41,'Database '!$G$11:$G$22)*(1+Table2[[#This Row],[Growth Percentage]])^(Table2[[#Headers],[2036]]-YEAR(TODAY())) -> 1.9221909e+08
A42: ='Database '!$A$16 -> GOTO | B42: ='Database '!B28 -> 0.06 | C42: =SUMIF('Database '!$A$11:$A$22,A42,'Database '!$G$11:$G$22)*(1+Table2[[#This Row],[Growth Percentage]])^(Table2[[#Headers],[2027]]-YEAR(TODAY())) -> 4751182.3 | D42: =SUMIF('Database '!$A$11:$A$22,A42,'Database '!$G$11:$G$22)*(1+Table2[[#This Row],[Growth Percentage]])^(Table2[[#Headers],[2028]]-YEAR(TODAY())) -> 5036253.3 | E42: =SUMIF('Database '!$A$11:$A$22,A42,'Database '!$G$11:$G$22)*(1+Table2[[#This Row],[Growth Percentage]])^(Table2[[#Headers],[2029]]-YEAR(TODAY())) -> 5338428.5 | F42: =SUMIF('Database '!$A$11:$A$22,A42,'Database '!$G$11:$G$22)*(1+Table2[[#This Row],[Growth Percentage]])^(Table2[[#Headers],[2030]]-YEAR(TODAY())) -> 5658734.2 | G42: =SUMIF('Database '!$A$11:$A$22,A42,'Database '!$G$11:$G$22)*(1+Table2[[#This Row],[Growth Percentage]])^(Table2[[#Headers],[2031]]-YEAR(TODAY())) -> 5998258.2 | H42: =SUMIF('Database '!$A$11:$A$22,A42,'Database '!$G$11:$G$22)*(1+Table2[[#This Row],[Growth Percentage]])^(Table2[[#Headers],[2032]]-YEAR(TODAY())) -> 6358153.7 | I42: =SUMIF('Database '!$A$11:$A$22,A42,'Database '!$G$11:$G$22)*(1+Table2[[#This Row],[Growth Percentage]])^(Table2[[#Headers],[2033]]-YEAR(TODAY())) -> 6739642.9 | J42: =SUMIF('Database '!$A$11:$A$22,A42,'Database '!$G$11:$G$22)*(1+Table2[[#This Row],[Growth Percentage]])^(Table2[[#Headers],[2034]]-YEAR(TODAY())) -> 7144021.5 | K42: =SUMIF('Database '!$A$11:$A$22,A42,'Database '!$G$11:$G$22)*(1+Table2[[#This Row],[Growth Percentage]])^(Table2[[#Headers],[2035]]-YEAR(TODAY())) -> 7572662.8 | L42: =SUMIF('Database '!$A$11:$A$22,A42,'Database '!$G$11:$G$22)*(1+Table2[[#This Row],[Growth Percentage]])^(Table2[[#Headers],[2036]]-YEAR(TODAY())) -> 8027022.6
A43: ='Database '!$A$16 -> GOTO | B43: ='Database '!C28 -> 0.07 | C43: =SUMIF('Database '!$A$11:$A$22,A43,'Database '!$G$11:$G$22)*(1+Table2[[#This Row],[Growth Percentage]])^(Table2[[#Headers],[2027]]-YEAR(TODAY())) -> 4796004.8 | D43: =SUMIF('Database '!$A$11:$A$22,A43,'Database '!$G$11:$G$22)*(1+Table2[[#This Row],[Growth Percentage]])^(Table2[[#Headers],[2028]]-YEAR(TODAY())) -> 5131725.1 | E43: =SUMIF('Database '!$A$11:$A$22,A43,'Database '!$G$11:$G$22)*(1+Table2[[#This Row],[Growth Percentage]])^(Table2[[#Headers],[2029]]-YEAR(TODAY())) -> 5490945.9 | F43: =SUMIF('Database '!$A$11:$A$22,A43,'Database '!$G$11:$G$22)*(1+Table2[[#This Row],[Growth Percentage]])^(Table2[[#Headers],[2030]]-YEAR(TODAY())) -> 5875312.1 | G43: =SUMIF('Database '!$A$11:$A$22,A43,'Database '!$G$11:$G$22)*(1+Table2[[#This Row],[Growth Percentage]])^(Table2[[#Headers],[2031]]-YEAR(TODAY())) -> 6286583.9 | H43: =SUMIF('Database '!$A$11:$A$22,A43,'Database '!$G$11:$G$22)*(1+Table2[[#This Row],[Growth Percentage]])^(Table2[[#Headers],[2032]]-YEAR(TODAY())) -> 6726644.8 | I43: =SUMIF('Database '!$A$11:$A$22,A43,'Database '!$G$11:$G$22)*(1+Table2[[#This Row],[Growth Percentage]])^(Table2[[#Headers],[2033]]-YEAR(TODAY())) -> 7197510 | J43: =SUMIF('Database '!$A$11:$A$22,A43,'Database '!$G$11:$G$22)*(1+Table2[[#This Row],[Growth Percentage]])^(Table2[[#Headers],[2034]]-YEAR(TODAY())) -> 7701335.7 | K43: =SUMIF('Database '!$A$11:$A$22,A43,'Database '!$G$11:$G$22)*(1+Table2[[#This Row],[Growth Percentage]])^(Table2[[#Headers],[2035]]-YEAR(TODAY())) -> 8240429.2 | L43: =SUMIF('Database '!$A$11:$A$22,A43,'Database '!$G$11:$G$22)*(1+Table2[[#This Row],[Growth Percentage]])^(Table2[[#Headers],[2036]]-YEAR(TODAY())) -> 8817259.2
A44: ='Database '!$A$16 -> GOTO | B44: ='Database '!D28 -> 0.08 | C44: =SUMIF('Database '!$A$11:$A$22,A44,'Database '!$G$11:$G$22)*(1+Table2[[#This Row],[Growth Percentage]])^(Table2[[#Headers],[2027]]-YEAR(TODAY())) -> 4840827.3 | D44: =SUMIF('Database '!$A$11:$A$22,A44,'Database '!$G$11:$G$22)*(1+Table2[[#This Row],[Growth Percentage]])^(Table2[[#Headers],[2028]]-YEAR(TODAY())) -> 5228093.4 | E44: =SUMIF('Database '!$A$11:$A$22,A44,'Database '!$G$11:$G$22)*(1+Table2[[#This Row],[Growth Percentage]])^(Table2[[#Headers],[2029]]-YEAR(TODAY())) -> 5646340.9 | F44: =SUMIF('Database '!$A$11:$A$22,A44,'Database '!$G$11:$G$22)*(1+Table2[[#This Row],[Growth Percentage]])^(Table2[[#Headers],[2030]]-YEAR(TODAY())) -> 6098048.2 | G44: =SUMIF('Database '!$A$11:$A$22,A44,'Database '!$G$11:$G$22)*(1+Table2[[#This Row],[Growth Percentage]])^(Table2[[#Headers],[2031]]-YEAR(TODAY())) -> 6585892.1 | H44: =SUMIF('Database '!$A$11:$A$22,A44,'Database '!$G$11:$G$22)*(1+Table2[[#This Row],[Growth Percentage]])^(Table2[[#Headers],[2032]]-YEAR(TODAY())) -> 7112763.4 | I44: =SUMIF('Database '!$A$11:$A$22,A44,'Database '!$G$11:$G$22)*(1+Table2[[#This Row],[Growth Percentage]])^(Table2[[#Headers],[2033]]-YEAR(TODAY())) -> 7681784.5 | J44: =SUMIF('Database '!$A$11:$A$22,A44,'Database '!$G$11:$G$22)*(1+Table2[[#This Row],[Growth Percentage]])^(Table2[[#Headers],[2034]]-YEAR(TODAY())) -> 8296327.2 | K44: =SUMIF('Database '!$A$11:$A$22,A44,'Database '!$G$11:$G$22)*(1+Table2[[#This Row],[Growth Percentage]])^(Table2[[#Headers],[2035]]-YEAR(TODAY())) -> 8960033.4 | L44: =SUMIF('Database '!$A$11:$A$22,A44,'Database '!$G$11:$G$22)*(1+Table2[[#This Row],[Growth Percentage]])^(Table2[[#Headers],[2036]]-YEAR(TODAY())) -> 9676836.1
A45: ='Database '!$A$16 -> GOTO | B45: ='Database '!E28 -> 0.09 | C45: =SUMIF('Database '!$A$11:$A$22,A45,'Database '!$G$11:$G$22)*(1+Table2[[#This Row],[Growth Percentage]])^(Table2[[#Headers],[2027]]-YEAR(TODAY())) -> 4885649.7 | D45: =SUMIF('Database '!$A$11:$A$22,A45,'Database '!$G$11:$G$22)*(1+Table2[[#This Row],[Growth Percentage]])^(Table2[[#Headers],[2028]]-YEAR(TODAY())) -> 5325358.2 | E45: =SUMIF('Database '!$A$11:$A$22,A45,'Database '!$G$11:$G$22)*(1+Table2[[#This Row],[Growth Percentage]])^(Table2[[#Headers],[2029]]-YEAR(TODAY())) -> 5804640.5 | F45: =SUMIF('Database '!$A$11:$A$22,A45,'Database '!$G$11:$G$22)*(1+Table2[[#This Row],[Growth Percentage]])^(Table2[[#Headers],[2030]]-YEAR(TODAY())) -> 6327058.1 | G45: =SUMIF('Database '!$A$11:$A$22,A45,'Database '!$G$11:$G$22)*(1+Table2[[#This Row],[Growth Percentage]])^(Table2[[#Headers],[2031]]-YEAR(TODAY())) -> 6896493.3 | H45: =SUMIF('Database '!$A$11:$A$22,A45,'Database '!$G$11:$G$22)*(1+Table2[[#This Row],[Growth Percentage]])^(Table2[[#Headers],[2032]]-YEAR(TODAY())) -> 7517177.7 | I45: =SUMIF('Database '!$A$11:$A$22,A45,'Database '!$G$11:$G$22)*(1+Table2[[#This Row],[Growth Percentage]])^(Table2[[#Headers],[2033]]-YEAR(TODAY())) -> 8193723.7 | J45: =SUMIF('Database '!$A$11:$A$22,A45,'Database '!$G$11:$G$22)*(1+Table2[[#This Row],[Growth Percentage]])^(Table2[[#Headers],[2034]]-YEAR(TODAY())) -> 8931158.9 | K45: =SUMIF('Database '!$A$11:$A$22,A45,'Database '!$G$11:$G$22)*(1+Table2[[#This Row],[Growth Percentage]])^(Table2[[#Headers],[2035]]-YEAR(TODAY())) -> 9734963.2 | L45: =SUMIF('Database '!$A$11:$A$22,A45,'Database '!$G$11:$G$22)*(1+Table2[[#This Row],[Growth Percentage]])^(Table2[[#Headers],[2036]]-YEAR(TODAY())) -> 10611110
A46: ='Database '!$A$16 -> GOTO | B46: ='Database '!F28 -> 0.095 | C46: =SUMIF('Database '!$A$11:$A$22,A46,'Database '!$G$11:$G$22)*(1+Table2[[#This Row],[Growth Percentage]])^(Table2[[#Headers],[2027]]-YEAR(TODAY())) -> 4908061 | D46: =SUMIF('Database '!$A$11:$A$22,A46,'Database '!$G$11:$G$22)*(1+Table2[[#This Row],[Growth Percentage]])^(Table2[[#Headers],[2028]]-YEAR(TODAY())) -> 5374326.8 | E46: =SUMIF('Database '!$A$11:$A$22,A46,'Database '!$G$11:$G$22)*(1+Table2[[#This Row],[Growth Percentage]])^(Table2[[#Headers],[2029]]-YEAR(TODAY())) -> 5884887.8 | F46: =SUMIF('Database '!$A$11:$A$22,A46,'Database '!$G$11:$G$22)*(1+Table2[[#This Row],[Growth Percentage]])^(Table2[[#Headers],[2030]]-YEAR(TODAY())) -> 6443952.2 | G46: =SUMIF('Database '!$A$11:$A$22,A46,'Database '!$G$11:$G$22)*(1+Table2[[#This Row],[Growth Percentage]])^(Table2[[#Headers],[2031]]-YEAR(TODAY())) -> 7056127.6 | H46: =SUMIF('Database '!$A$11:$A$22,A46,'Database '!$G$11:$G$22)*(1+Table2[[#This Row],[Growth Percentage]])^(Table2[[#Headers],[2032]]-YEAR(TODAY())) -> 7726459.7 | I46: =SUMIF('Database '!$A$11:$A$22,A46,'Database '!$G$11:$G$22)*(1+Table2[[#This Row],[Growth Percentage]])^(Table2[[#Headers],[2033]]-YEAR(TODAY())) -> 8460473.4 | J46: =SUMIF('Database '!$A$11:$A$22,A46,'Database '!$G$11:$G$22)*(1+Table2[[#This Row],[Growth Percentage]])^(Table2[[#Headers],[2034]]-YEAR(TODAY())) -> 9264218.4 | K46: =SUMIF('Database '!$A$11:$A$22,A46,'Database '!$G$11:$G$22)*(1+Table2[[#This Row],[Growth Percentage]])^(Table2[[#Headers],[2035]]-YEAR(TODAY())) -> 10144319 | L46: =SUMIF('Database '!$A$11:$A$22,A46,'Database '!$G$11:$G$22)*(1+Table2[[#This Row],[Growth Percentage]])^(Table2[[#Headers],[2036]]-YEAR(TODAY())) -> 11108029
A47: ='Database '!$A$16 -> GOTO | B47: ='Database '!G28 -> 0.1 | C47: =SUMIF('Database '!$A$11:$A$22,A47,'Database '!$G$11:$G$22)*(1+Table2[[#This Row],[Growth Percentage]])^(Table2[[#Headers],[2027]]-YEAR(TODAY())) -> 4930472.2 | D47: =SUMIF('Database '!$A$11:$A$22,A47,'Database '!$G$11:$G$22)*(1+Table2[[#This Row],[Growth Percentage]])^(Table2[[#Headers],[2028]]-YEAR(TODAY())) -> 5423519.4 | E47: =SUMIF('Database '!$A$11:$A$22,A47,'Database '!$G$11:$G$22)*(1+Table2[[#This Row],[Growth Percentage]])^(Table2[[#Headers],[2029]]-YEAR(TODAY())) -> 5965871.4 | F47: =SUMIF('Database '!$A$11:$A$22,A47,'Database '!$G$11:$G$22)*(1+Table2[[#This Row],[Growth Percentage]])^(Table2[[#Headers],[2030]]-YEAR(TODAY())) -> 6562458.5 | G47: =SUMIF('Database '!$A$11:$A$22,A47,'Database '!$G$11:$G$22)*(1+Table2[[#This Row],[Growth Percentage]])^(Table2[[#Headers],[2031]]-YEAR(TODAY())) -> 7218704.4 | H47: =SUMIF('Database '!$A$11:$A$22,A47,'Database '!$G$11:$G$22)*(1+Table2[[#This Row],[Growth Percentage]])^(Table2[[#Headers],[2032]]-YEAR(TODAY())) -> 7940574.8 | I47: =SUMIF('Database '!$A$11:$A$22,A47,'Database '!$G$11:$G$22)*(1+Table2[[#This Row],[Growth Percentage]])^(Table2[[#Headers],[2033]]-YEAR(TODAY())) -> 8734632.3 | J47: =SUMIF('Database '!$A$11:$A$22,A47,'Database '!$G$11:$G$22)*(1+Table2[[#This Row],[Growth Percentage]])^(Table2[[#Headers],[2034]]-YEAR(TODAY())) -> 9608095.5 | K47: =SUMIF('Database '!$A$11:$A$22,A47,'Database '!$G$11:$G$22)*(1+Table2[[#This Row],[Growth Percentage]])^(Table2[[#Headers],[2035]]-YEAR(TODAY())) -> 10568905 | L47: =SUMIF('Database '!$A$11:$A$22,A47,'Database '!$G$11:$G$22)*(1+Table2[[#This Row],[Growth Percentage]])^(Table2[[#Headers],[2036]]-YEAR(TODAY())) -> 11625796
